Workbook

Sheet Contents
A1: This workbook supplements CBO’s report How Changes in Economic Conditions Might Affect the Federal Budget: 2025 to 2035.
A2: www.cbo.gov/publication/61198
A5: Contents
A7: 1. Interactive Table: How Changes in Productivity Growth Might Affect the Federal Budget
A8: 2. Interactive Table: How Changes in Labor Force Growth Might Affect the Federal Budget
A9: 3. Interactive Table: How Changes in Interest Rates Might Affect the Federal Budget
A10: 4. Interactive Table: How Changes in Inflation and Interest Rates Might Affect the Federal Budget
A11: 5. Illustrative Scenario: How Productivity Growth That Was 0.1 Percentage Point Slower Each Year Than It Is in CBO’s Forecast Might Aﬀect the Federal Budget
A12: 6. Illustrative Scenario: How Labor Force Growth That Was 0.1 Percentage Point Slower Each Year Than It Is in CBO’s Forecast Might Aﬀect the Federal Budget
A13: 7. Illustrative Scenario: How Interest Rates That Were 0.1 Percentage Point Higher Each Year Than They Are in CBO’s Forecast Might Aﬀect the Federal Budget
A14: 8. Illustrative Scenario: How Inflation and Interest Rates That Were 0.1 Percentage Point Higher Each Year Than They Are in CBO’s Forecast Might Aﬀect the Federal Budget
A17: About This Workbook
... A29: Because the scalability of the rules of thumb is limited, only moderate changes in economic variables in this workbook will produce reasonable approximations of the estimates that CBO’s broader set of models would produce. To determine the limits of the workbook, CBO ran simulations using several values for year-by-year differences for each of the four variables. The agency found that the workbook produced plausible estimates when differences in productivity growth ranged from −0.5 percentage points to 0.5 percentage points, differences in labor force growth ranged from −0.75 percentage points to 0.75 percentage points, and differences in interest rates and inflation ranged from −1.0 percentage point to 1.0 percentage point. Any scenario with differences outside those ranges cannot be analyzed with this workbook and would require a more detailed analysis.

Sheet 1. Productivity
A1: This workbook supplements CBO’s report How Changes in Economic Conditions Might Affect the Federal Budget: 2025 to 2035.
A2: www.cbo.gov/publication/61198
A5: To create an alternative scenario for productivity growth, enter values between -0.5 percentage points and 0.5 percentage points in each of the green cells. (Only the green cells can be edited; all other cells are locked. Values outside of the specified range will produce errors.) The change in budgetary outcomes relative to those in CBO’s baseline will be calculated and appear automatically. Values for key economic indicators are shown below those budgetary effects.
A7: 1. Interactive Table: How Changes in Productivity Growth Might Affect the Federal Budget
B9: 2024 | C9: 2025 | D9: 2026 | E9: 2027 | F9: 2028 | G9: 2029 | H9: 2030 | I9: 2031 | J9: 2032 | K9: 2033 | L9: 2034 | M9: 2035
C11: User-specified scenario for annual productivity growth
O12: These initial values are the same as those used to generate the illustrative scenario shown in Worksheet 5, “Productivity_CBO.”
A13: Increase or decrease (-) in productivity growth relative to CBO’s January 2025 baseline (percentage points) | B13: n.a. | C13: 0 | D13: 0.1 | E13: 0.2 | F13: 0.3 | G13: 0.4 | H13: 0.5 | I13: 0.5 | J13: 0.5 | K13: 0.5 | L13: 0.5 | M13: 0.5
A14: =IF($A$19,"Please keep values in the range [-0.5, 0.5] percentage points per year.","")
A15: Productivity growth (percent)a
A16: January 2025 baseline | B16: 0.98 | C16: 0.983 | D16: 1.015 | E16: 1.058 | F16: 1.105 | G16: 1.129 | H16: 1.126 | I16: 1.125 | J16: 1.121 | K16: 1.116 | L16: 1.114 | M16: 1.112
A17: User-specified scenario | B17: =IF($A$19,"n.a.",B16) -> 0.98 | C17: =IF($A$19,"n.a.",C16+C13) -> 0.983 | D17: =IF($A$19,"n.a.",D16+D13) -> 1.115 | E17: =IF($A$19,"n.a.",E16+E13) -> 1.258 | F17: =IF($A$19,"n.a.",F16+F13) -> 1.405 | G17: =IF($A$19,"n.a.",G16+G13) -> 1.529 | H17: =IF($A$19,"n.a.",H16+H13) -> 1.626 | I17: =IF($A$19,"n.a.",I16+I13) -> 1.625 | J17: =IF($A$19,"n.a.",J16+J13) -> 1.621 | ... M17: =IF($A$19,"n.a.",M16+M13) -> 1.612
A19: =IF(OR(MAX(C13:M13)>0.5,MIN(C13:M13)<-0.5),1,0) -> 0
C21: Budgetary effects (billions of dollars) | N21: Total
N22: 2026- | O22: 2026-
B23: 2024 | C23: 2025 | D23: 2026 | E23: 2027 | F23: 2028 | G23: 2029 | H23: 2030 | I23: 2031 | J23: 2032 | K23: 2033 | L23: 2034 | M23: 2035 | N23: 2030 | O23: 2035
A24: Changes in revenues | B24: n.a. | C24: =IF($A$19,"n.a.",ROUND('5. Productivity_CBO'!C11/('5. Productivity_CBO'!C57-'5. Productivity_CBO'!C56)*(ROUND('1. Productivity'!C70,1)-ROUND('1. Productivity'!C69,1)),3)) -> 0 | D24: =IF($A$19,"n.a.",ROUND('5. Productivity_CBO'!D11/('5. Productivity_CBO'!D57-'5. Productivity_CBO'!D56)*(ROUND('1. Productivity'!D70,1)-ROUND('1. Productivity'!D69,1)),3)) -> 4.692 | E24: =IF($A$19,"n.a.",ROUND('5. Productivity_CBO'!E11/('5. Productivity_CBO'!E57-'5. Productivity_CBO'!E56)*(ROUND('1. Productivity'!E70,1)-ROUND('1. Productivity'!E69,1)),3)) -> 16.899 | F24: =IF($A$19,"n.a.",ROUND('5. Productivity_CBO'!F11/('5. Productivity_CBO'!F57-'5. Productivity_CBO'!F56)*(ROUND('1. Productivity'!F70,1)-ROUND('1. Productivity'!F69,1)),3)) -> 37.689 | G24: =IF($A$19,"n.a.",ROUND('5. Productivity_CBO'!G11/('5. Productivity_CBO'!G57-'5. Productivity_CBO'!G56)*(ROUND('1. Productivity'!G70,1)-ROUND('1. Productivity'!G69,1)),3)) -> 68.355 | H24: =IF($A$19,"n.a.",ROUND('5. Productivity_CBO'!H11/('5. Productivity_CBO'!H57-'5. Productivity_CBO'!H56)*(ROUND('1. Productivity'!H70,1)-ROUND('1. Productivity'!H69,1)),3)) -> 110.403 | I24: =IF($A$19,"n.a.",ROUND('5. Productivity_CBO'!I11/('5. Productivity_CBO'!I57-'5. Productivity_CBO'!I56)*(ROUND('1. Productivity'!I70,1)-ROUND('1. Productivity'!I69,1)),3)) -> 159.169 | J24: =IF($A$19,"n.a.",ROUND('5. Productivity_CBO'!J11/('5. Productivity_CBO'!J57-'5. Productivity_CBO'!J56)*(ROUND('1. Productivity'!J70,1)-ROUND('1. Productivity'!J69,1)),3)) -> 213.498 | ... M24: =IF($A$19,"n.a.",ROUND('5. Productivity_CBO'!M11/('5. Productivity_CBO'!M57-'5. Productivity_CBO'!M56)*(ROUND('1. Productivity'!M70,1)-ROUND('1. Productivity'!M69,1)),3)) -> 411.038 | N24: =IF($A$19,"n.a.",SUM(D24:H24)) -> 238.038 | O24: =IF($A$19,"n.a.",SUM(D24:M24)) -> 1633.737
A26: Changes in outlays
A27: Mandatory outlays | B27: n.a. | C27: =IF($A$19,"n.a.",ROUND('5. Productivity_CBO'!C14/('5. Productivity_CBO'!C57-'5. Productivity_CBO'!C56)*(ROUND('1. Productivity'!C70,1)-ROUND('1. Productivity'!C69,1)),3)) -> 0 | D27: =IF($A$19,"n.a.",ROUND('5. Productivity_CBO'!D14/('5. Productivity_CBO'!D57-'5. Productivity_CBO'!D56)*(ROUND('1. Productivity'!D70,1)-ROUND('1. Productivity'!D69,1)),3)) -> 0.207 | E27: =IF($A$19,"n.a.",ROUND('5. Productivity_CBO'!E14/('5. Productivity_CBO'!E57-'5. Productivity_CBO'!E56)*(ROUND('1. Productivity'!E70,1)-ROUND('1. Productivity'!E69,1)),3)) -> 0.949 | F27: =IF($A$19,"n.a.",ROUND('5. Productivity_CBO'!F14/('5. Productivity_CBO'!F57-'5. Productivity_CBO'!F56)*(ROUND('1. Productivity'!F70,1)-ROUND('1. Productivity'!F69,1)),3)) -> 2.604 | G27: =IF($A$19,"n.a.",ROUND('5. Productivity_CBO'!G14/('5. Productivity_CBO'!G57-'5. Productivity_CBO'!G56)*(ROUND('1. Productivity'!G70,1)-ROUND('1. Productivity'!G69,1)),3)) -> 4.579 | H27: =IF($A$19,"n.a.",ROUND('5. Productivity_CBO'!H14/('5. Productivity_CBO'!H57-'5. Productivity_CBO'!H56)*(ROUND('1. Productivity'!H70,1)-ROUND('1. Productivity'!H69,1)),3)) -> 7.712 | I27: =IF($A$19,"n.a.",ROUND('5. Productivity_CBO'!I14/('5. Productivity_CBO'!I57-'5. Productivity_CBO'!I56)*(ROUND('1. Productivity'!I70,1)-ROUND('1. Productivity'!I69,1)),3)) -> 11.444 | J27: =IF($A$19,"n.a.",ROUND('5. Productivity_CBO'!J14/('5. Productivity_CBO'!J57-'5. Productivity_CBO'!J56)*(ROUND('1. Productivity'!J70,1)-ROUND('1. Productivity'!J69,1)),3)) -> 15.949 | ... M27: =IF($A$19,"n.a.",ROUND('5. Productivity_CBO'!M14/('5. Productivity_CBO'!M57-'5. Productivity_CBO'!M56)*(ROUND('1. Productivity'!M70,1)-ROUND('1. Productivity'!M69,1)),3)) -> 34.417 | N27: =IF($A$19,"n.a.",SUM(D27:H27)) -> 16.051 | O27: =IF($A$19,"n.a.",SUM(D27:M27)) -> 126.708
A28: Discretionary outlaysb | B28: n.a. | C28: =IF($A$19,"n.a.",0) -> 0 | D28: =IF($A$19,"n.a.",0) -> 0 | E28: =IF($A$19,"n.a.",0) -> 0 | F28: =IF($A$19,"n.a.",0) -> 0 | G28: =IF($A$19,"n.a.",0) -> 0 | H28: =IF($A$19,"n.a.",0) -> 0 | I28: =IF($A$19,"n.a.",0) -> 0 | J28: =IF($A$19,"n.a.",0) -> 0 | ... M28: =IF($A$19,"n.a.",0) -> 0 | N28: =IF($A$19,"n.a.",SUM(D28:H28)) -> 0 | O28: =IF($A$19,"n.a.",SUM(D28:M28)) -> 0
A29: Net interest outlays
A30: Effects from changes in interest rates | B30: n.a. | C30: {=IF($A$19,"n.a.",ROUND(SUMPRODUCT(TRANSPOSE($C117:$M117),C119:C129),3)+ROUND(C131*C117/('5. Productivity_CBO'!C63-'5. Productivity_CBO'!C62),3))} -> 0 | D30: {=IF($A$19,"n.a.",ROUND(SUMPRODUCT(TRANSPOSE($C117:$M117),D119:D129),3)+ROUND(D131*D117/('5. Productivity_CBO'!D63-'5. Productivity_CBO'!D62),3))} -> 0.723 | E30: {=IF($A$19,"n.a.",ROUND(SUMPRODUCT(TRANSPOSE($C117:$M117),E119:E129),3)+ROUND(E131*E117/('5. Productivity_CBO'!E63-'5. Productivity_CBO'!E62),3))} -> 3.246 | F30: {=IF($A$19,"n.a.",ROUND(SUMPRODUCT(TRANSPOSE($C117:$M117),F119:F129),3)+ROUND(F131*F117/('5. Productivity_CBO'!F63-'5. Productivity_CBO'!F62),3))} -> 8.33 | G30: {=IF($A$19,"n.a.",ROUND(SUMPRODUCT(TRANSPOSE($C117:$M117),G119:G129),3)+ROUND(G131*G117/('5. Productivity_CBO'!G63-'5. Productivity_CBO'!G62),3))} -> 16.642 | H30: {=IF($A$19,"n.a.",ROUND(SUMPRODUCT(TRANSPOSE($C117:$M117),H119:H129),3)+ROUND(H131*H117/('5. Productivity_CBO'!H63-'5. Productivity_CBO'!H62),3))} -> 29.165 | I30: {=IF($A$19,"n.a.",ROUND(SUMPRODUCT(TRANSPOSE($C117:$M117),I119:I129),3)+ROUND(I131*I117/('5. Productivity_CBO'!I63-'5. Productivity_CBO'!I62),3))} -> 45.488 | J30: {=IF($A$19,"n.a.",ROUND(SUMPRODUCT(TRANSPOSE($C117:$M117),J119:J129),3)+ROUND(J131*J117/('5. Productivity_CBO'!J63-'5. Productivity_CBO'!J62),3))} -> 65.076 | ... M30: {=IF($A$19,"n.a.",ROUND(SUMPRODUCT(TRANSPOSE($C117:$M117),M119:M129),3)+ROUND(M131*M117/('5. Productivity_CBO'!M63-'5. Productivity_CBO'!M62),3))} -> 138.07 | N30: =IF($A$19,"n.a.",SUM(D30:H30)) -> 58.106 | O30: =IF($A$19,"n.a.",SUM(D30:M30)) -> 505.16
A31: Debt service | B31: n.a. | C31: {=IF($A$19,"n.a.",ROUND(SUMPRODUCT($C133:$M133,TRANSPOSE(C135:C145)),3) + ROUND(C147*(-C133)/('5. Productivity_CBO'!C24+'5. Productivity_CBO'!C18),3))} -> 0 | D31: {=IF($A$19,"n.a.",ROUND(SUMPRODUCT($C133:$M133,TRANSPOSE(D135:D145)),3) + ROUND(D147*(-D133)/('5. Productivity_CBO'!D24+'5. Productivity_CBO'!D18),3))} -> -0.069 | E31: {=IF($A$19,"n.a.",ROUND(SUMPRODUCT($C133:$M133,TRANSPOSE(E135:E145)),3) + ROUND(E147*(-E133)/('5. Productivity_CBO'!E24+'5. Productivity_CBO'!E18),3))} -> -0.366 | F31: {=IF($A$19,"n.a.",ROUND(SUMPRODUCT($C133:$M133,TRANSPOSE(F135:F145)),3) + ROUND(F147*(-F133)/('5. Productivity_CBO'!F24+'5. Productivity_CBO'!F18),3))} -> -1.065 | G31: {=IF($A$19,"n.a.",ROUND(SUMPRODUCT($C133:$M133,TRANSPOSE(G135:G145)),3) + ROUND(G147*(-G133)/('5. Productivity_CBO'!G24+'5. Productivity_CBO'!G18),3))} -> -2.367 | H31: {=IF($A$19,"n.a.",ROUND(SUMPRODUCT($C133:$M133,TRANSPOSE(H135:H145)),3) + ROUND(H147*(-H133)/('5. Productivity_CBO'!H24+'5. Productivity_CBO'!H18),3))} -> -4.479 | I31: {=IF($A$19,"n.a.",ROUND(SUMPRODUCT($C133:$M133,TRANSPOSE(I135:I145)),3) + ROUND(I147*(-I133)/('5. Productivity_CBO'!I24+'5. Productivity_CBO'!I18),3))} -> -7.535 | J31: {=IF($A$19,"n.a.",ROUND(SUMPRODUCT($C133:$M133,TRANSPOSE(J135:J145)),3) + ROUND(J147*(-J133)/('5. Productivity_CBO'!J24+'5. Productivity_CBO'!J18),3))} -> -11.643 | ... M31: {=IF($A$19,"n.a.",ROUND(SUMPRODUCT($C133:$M133,TRANSPOSE(M135:M145)),3) + ROUND(M147*(-M133)/('5. Productivity_CBO'!M24+'5. Productivity_CBO'!M18),3))} -> -31.032 | N31: =IF($A$19,"n.a.",SUM(D31:H31)) -> -8.346 | O31: =IF($A$19,"n.a.",SUM(D31:M31)) -> -98.724
B32: ____ | C32: ____ | D32: ____ | E32: ____ | F32: ____ | G32: ____ | H32: ____ | I32: ____ | J32: ____ | K32: ____ | L32: ____ | M32: ____ | N32: ____ | O32: ____
A33: Subtotal, net interest outlays | B33: n.a. | C33: =IF($A$19,"n.a.",C30+C31) -> 0 | D33: =IF($A$19,"n.a.",D30+D31) -> 0.654 | E33: =IF($A$19,"n.a.",E30+E31) -> 2.88 | F33: =IF($A$19,"n.a.",F30+F31) -> 7.265 | G33: =IF($A$19,"n.a.",G30+G31) -> 14.275 | H33: =IF($A$19,"n.a.",H30+H31) -> 24.686 | I33: =IF($A$19,"n.a.",I30+I31) -> 37.953 | J33: =IF($A$19,"n.a.",J30+J31) -> 53.433 | ... M33: =IF($A$19,"n.a.",M30+M31) -> 107.038 | N33: =IF($A$19,"n.a.",SUM(D33:H33)) -> 49.76 | O33: =IF($A$19,"n.a.",SUM(D33:M33)) -> 406.436
A35: Total change in outlays | B35: n.a. | C35: =IF($A$19,"n.a.",C27+C28+C33) -> 0 | D35: =IF($A$19,"n.a.",D27+D28+D33) -> 0.861 | E35: =IF($A$19,"n.a.",E27+E28+E33) -> 3.829 | F35: =IF($A$19,"n.a.",F27+F28+F33) -> 9.869 | G35: =IF($A$19,"n.a.",G27+G28+G33) -> 18.854 | H35: =IF($A$19,"n.a.",H27+H28+H33) -> 32.398 | I35: =IF($A$19,"n.a.",I27+I28+I33) -> 49.397 | J35: =IF($A$19,"n.a.",J27+J28+J33) -> 69.382 | ... M35: =IF($A$19,"n.a.",M27+M28+M33) -> 141.455 | N35: =IF($A$19,"n.a.",SUM(D35:H35)) -> 65.811 | O35: =IF($A$19,"n.a.",SUM(D35:M35)) -> 533.144
A37: Increase (-) or decrease in the deficit relative to CBO’s baseline | B37: n.a. | C37: =IF($A$19,"n.a.",C24-C35) -> 0 | D37: =IF($A$19,"n.a.",D24-D35) -> 3.831 | E37: =IF($A$19,"n.a.",E24-E35) -> 13.07 | F37: =IF($A$19,"n.a.",F24-F35) -> 27.82 | G37: =IF($A$19,"n.a.",G24-G35) -> 49.501 | H37: =IF($A$19,"n.a.",H24-H35) -> 78.005 | I37: =IF($A$19,"n.a.",I24-I35) -> 109.772 | J37: =IF($A$19,"n.a.",J24-J35) -> 144.116 | ... M37: =IF($A$19,"n.a.",M24-M35) -> 269.583 | N37: =IF($A$19,"n.a.",SUM(D37:H37)) -> 172.227 | O37: =IF($A$19,"n.a.",SUM(D37:M37)) -> 1100.593
A39: Deficit (-) or surplus
A40: January 2025 baseline | B40: -1832.381 | C40: -1865.251 | D40: -1713.258 | E40: -1686.942 | F40: -1910.776 | G40: -1938.268 | H40: -2139.721 | I40: -2232.786 | J40: -2370.582 | K40: -2637.299 | L40: -2597.25 | M40: -2531.378 | N40: -9388.965 | O40: -21758.26
A41: User-specified scenario | B41: =IF($A$19,"n.a.",B40) -> -1832.381 | C41: =IF($A$19,"n.a.",C40+C37) -> -1865.251 | D41: =IF($A$19,"n.a.",D40+D37) -> -1709.427 | E41: =IF($A$19,"n.a.",E40+E37) -> -1673.872 | F41: =IF($A$19,"n.a.",F40+F37) -> -1882.956 | G41: =IF($A$19,"n.a.",G40+G37) -> -1888.767 | H41: =IF($A$19,"n.a.",H40+H37) -> -2061.716 | I41: =IF($A$19,"n.a.",I40+I37) -> -2123.014 | J41: =IF($A$19,"n.a.",J40+J37) -> -2226.466 | ... M41: =IF($A$19,"n.a.",M40+M37) -> -2261.795 | N41: =IF($A$19,"n.a.",SUM(D41:H41)) -> -9216.738 | O41: =IF($A$19,"n.a.",SUM(D41:M41)) -> -20657.667
A43: Debt held by the public
A44: January 2025 baseline | B44: 28199.313 | C44: 30102.749 | D44: 31882.633 | E44: 33636.105 | F44: 35600.64 | G44: 37580.5 | H44: 39747.651 | I44: 41992.385 | J44: 44371.755 | K44: 46985.029 | L44: 49555.504 | M44: 52055.866 | N44: n.a. | O44: n.a.
A45: User-specified scenario | B45: =IF($A$19,"n.a.",B44) -> 28199.313 | C45: =IF($A$19,"n.a.",C44-SUM($C37:C37)) -> 30102.749 | D45: =IF($A$19,"n.a.",D44-SUM($C37:D37)) -> 31878.802 | E45: =IF($A$19,"n.a.",E44-SUM($C37:E37)) -> 33619.204 | F45: =IF($A$19,"n.a.",F44-SUM($C37:F37)) -> 35555.919 | G45: =IF($A$19,"n.a.",G44-SUM($C37:G37)) -> 37486.278 | H45: =IF($A$19,"n.a.",H44-SUM($C37:H37)) -> 39575.424 | I45: =IF($A$19,"n.a.",I44-SUM($C37:I37)) -> 41710.386 | J45: =IF($A$19,"n.a.",J44-SUM($C37:J37)) -> 43945.64 | ... M45: =IF($A$19,"n.a.",M44-SUM($C37:M37)) -> 50955.273 | N45: n.a. | O45: n.a.
A47: Deficit (-) or surplus (percentage of GDP)
A48: January 2025 baseline | B48: -6.3562158 | C48: -6.1894147 | D48: -5.4664504 | E48: -5.184518 | F48: -5.659123 | G48: -5.5304586 | H48: -5.8793652 | I48: -5.9080768 | J48: -6.0393242 | K48: -6.4690633 | L48: -6.1356563 | M48: -5.7614482 | N48: -5.5528141 | O48: -5.830748
A49: User-specified scenario | B49: =IF($A$19,"n.a.",B48) -> -6.3562158 | C49: =IF($A$19,"n.a.",ROUND(C41/C70*100,3)) -> -6.189 | D49: =IF($A$19,"n.a.",ROUND(D41/D70*100,3)) -> -5.45 | E49: =IF($A$19,"n.a.",ROUND(E41/E70*100,3)) -> -5.13 | F49: =IF($A$19,"n.a.",ROUND(F41/F70*100,3)) -> -5.544 | G49: =IF($A$19,"n.a.",ROUND(G41/G70*100,3)) -> -5.335 | H49: =IF($A$19,"n.a.",ROUND(H41/H70*100,3)) -> -5.577 | I49: =IF($A$19,"n.a.",ROUND(I41/I70*100,3)) -> -5.498 | J49: =IF($A$19,"n.a.",ROUND(J41/J70*100,3)) -> -5.518 | ... M49: =IF($A$19,"n.a.",ROUND(M41/M70*100,3)) -> -4.913 | N49: =IF($A$19,"n.a.",ROUND(SUM(D41:H41)/SUM(D70:H70)*100,3)) -> -5.411 | O49: =IF($A$19,"n.a.",ROUND(SUM(D41:M41)/SUM(D70:M70)*100,3)) -> -5.414
A51: Debt held by the public (percentage of GDP)
A52: January 2025 baseline | B52: 97.818585 | C52: 99.889183 | D52: 101.72714 | E52: 103.37462 | F52: 105.438 | G52: 107.22841 | H52: 109.21562 | I52: 111.1142 | J52: 113.04204 | K52: 115.25016 | L52: 117.06826 | M52: 118.47981 | N52: n.a. | O52: n.a.
A53: User-specified scenario | B53: =IF($A$19,"n.a.",B52) -> 97.818585 | C53: =IF($A$19,"n.a.",ROUND(C45/C70*100,3)) -> 99.889 | D53: =IF($A$19,"n.a.",ROUND(D45/D70*100,3)) -> 101.631 | E53: =IF($A$19,"n.a.",ROUND(E45/E70*100,3)) -> 103.038 | F53: =IF($A$19,"n.a.",ROUND(F45/F70*100,3)) -> 104.693 | G53: =IF($A$19,"n.a.",ROUND(G45/G70*100,3)) -> 105.885 | H53: =IF($A$19,"n.a.",ROUND(H45/H70*100,3)) -> 107.062 | I53: =IF($A$19,"n.a.",ROUND(I45/I70*100,3)) -> 108.024 | J53: =IF($A$19,"n.a.",ROUND(J45/J70*100,3)) -> 108.916 | ... M53: =IF($A$19,"n.a.",ROUND(M45/M70*100,3)) -> 110.693 | N53: n.a. | O53: n.a.
B56: Economic indicators in CBO’s January 2025 baseline and under the user-specified scenario
B58: 2024 | C58: 2025 | D58: 2026 | E58: 2027 | F58: 2028 | G58: 2029 | H58: 2030 | I58: 2031 | J58: 2032 | K58: 2033 | L58: 2034 | M58: 2035
A59: Real GDP growth (percent)
A60: January 2025 baseline | B60: 2.734 | C60: 2.124 | D60: 1.827 | E60: 1.763 | F60: 1.744 | G60: 1.786 | H60: 1.821 | I60: 1.822 | J60: 1.842 | K60: 1.826 | L60: 1.797 | M60: 1.76
A61: User-specified scenario | B61: =IF($A$19,"n.a.",B60) -> 2.734 | C61: =IF($A$19,"n.a.",ROUND((C64/B64-1)*100,3)) -> 2.125 | D61: =IF($A$19,"n.a.",ROUND((D64/C64-1)*100,3)) -> 1.938 | E61: =IF($A$19,"n.a.",ROUND((E64/D64-1)*100,3)) -> 1.988 | F61: =IF($A$19,"n.a.",ROUND((F64/E64-1)*100,3)) -> 2.088 | G61: =IF($A$19,"n.a.",ROUND((G64/F64-1)*100,3)) -> 2.25 | H61: =IF($A$19,"n.a.",ROUND((H64/G64-1)*100,3)) -> 2.411 | I61: =IF($A$19,"n.a.",ROUND((I64/H64-1)*100,3)) -> 2.429 | J61: =IF($A$19,"n.a.",ROUND((J64/I64-1)*100,3)) -> 2.466 | ... M61: =IF($A$19,"n.a.",ROUND((M64/L64-1)*100,3)) -> 2.428
A62: Real GDP (billions of 2017 dollars)
A63: January 2025 baseline | B63: 23290.9 | C63: 23785.8 | D63: 24220.5 | E63: 24647.6 | F63: 25077.7 | G63: 25525.6 | H63: 25990.7 | I63: 26464.3 | J63: 26952 | K63: 27444.4 | L63: 27937.8 | M63: 28429.6
A64: User-specified scenario | B64: =IF($A$19,"n.a.",B63) -> 23290.9 | C64: =IF($A$19,"n.a.",ROUND(C63*(1+$C108*C115),1)) -> 23785.8 | D64: =IF($A$19,"n.a.",ROUND(D63*(1+$D108*C115+$C108*D115),1)) -> 24246.8 | E64: =IF($A$19,"n.a.",ROUND(E63*(1+$E108*C115+$D108*D115+$C108*E115),1)) -> 24728.8 | F64: =IF($A$19,"n.a.",ROUND(F63*(1+$F108*C115+$E108*D115+$D108*E115+$C108*F115),1)) -> 25245.1 | G64: =IF($A$19,"n.a.",ROUND(G63*(1+$G108*C115+$F108*D115+$E108*E115+$D108*F115+$C108*G115),1)) -> 25813.1 | H64: =IF($A$19,"n.a.",ROUND(H63*(1+$H108*C115+$G108*D115+$F108*E115+$E108*F115+$D108*G115+$C108*H115),1)) -> 26435.5 | I64: =IF($A$19,"n.a.",ROUND(I63*(1+$I108*C115+$H108*D115+$G108*E115+$F108*F115+$E108*G115+$D108*H115+$C108*I115),1)) -> 27077.5 | J64: =IF($A$19,"n.a.",ROUND(J63*(1+$J108*C115+$I108*D115+$H108*E115+$G108*F115+$F108*G115+$E108*H115+$D108*I115+$C108*J115),1)) -> 27745.2 | K64: =IF($A$19,"n.a.",ROUND(K63*(1+$K108*C115+$J108*D115+$I108*E115+$H108*F115+$G108*G115+$F108*H115+$E108*I115+$D108*J115+$C108*K115),1)) -> 28429.3 | L64: =IF($A$19,"n.a.",ROUND(L63*(1+$L108*C115+$K108*D115+$J108*E115+$I108*F115+$H108*G115+$G108*H115+$F108*I115+$E108*J115+$D108*K115+$C108*L115),1)) -> 29126.2 | M64: =IF($A$19,"n.a.",ROUND(M63*(1+$M108*C115+$L108*D115+$K108*E115+$J108*F115+$I108*G115+$H108*H115+$G108*I115+$F108*J115+$E108*K115+$D108*L115+$C108*M115),1)) -> 29833.3
A65: Nominal GDP (billions of dollars)
A66: January 2025 baseline | B66: 29166.2 | C66: 30441.1 | D66: 31640.6 | E66: 32841 | F66: 34078.4 | G66: 35378.4 | H66: 36738.8 | I66: 38151.3 | J66: 39626.7 | K66: 41154.2 | L66: 42727.6 | M66: 44345.4
A67: User-specified scenario | B67: =IF($A$19,"n.a.",B66) -> 29166.2 | C67: =IF($A$19,"n.a.",ROUND(C64/C63*C66,1)) -> 30441.1 | D67: =IF($A$19,"n.a.",ROUND(D64/D63*D66,1)) -> 31675 | E67: =IF($A$19,"n.a.",ROUND(E64/E63*E66,1)) -> 32949.2 | F67: =IF($A$19,"n.a.",ROUND(F64/F63*F66,1)) -> 34305.9 | G67: =IF($A$19,"n.a.",ROUND(G64/G63*G66,1)) -> 35776.9 | H67: =IF($A$19,"n.a.",ROUND(H64/H63*H66,1)) -> 37367.5 | I67: =IF($A$19,"n.a.",ROUND(I64/I63*I66,1)) -> 39035.3 | J67: =IF($A$19,"n.a.",ROUND(J64/J63*J66,1)) -> 40792.9 | ... M67: =IF($A$19,"n.a.",ROUND(M64/M63*M66,1)) -> 46534.9
A68: Nominal GDP (billions of dollars, by fiscal year)
A69: January 2025 baseline | B69: 28823 | C69: 30136.1 | D69: 31341.3 | E69: 32538.1 | F69: 33764.5 | G69: 35047.1 | H69: 36393.7 | I69: 37792.1 | J69: 39252.4 | K69: 40767.9 | L69: 42330.4 | M69: 43936.5
A70: User-specified scenario | B70: =IF($A$19,"n.a.",B69) -> 28823 | C70: =IF($A$19,"n.a.",ROUND(C69+(C67-C66)*0.75+(B67-B66)*0.25,1)) -> 30136.1 | D70: =IF($A$19,"n.a.",ROUND(D69+(D67-D66)*0.75+(C67-C66)*0.25,1)) -> 31367.1 | E70: =IF($A$19,"n.a.",ROUND(E69+(E67-E66)*0.75+(D67-D66)*0.25,1)) -> 32627.9 | F70: =IF($A$19,"n.a.",ROUND(F69+(F67-F66)*0.75+(E67-E66)*0.25,1)) -> 33962.2 | G70: =IF($A$19,"n.a.",ROUND(G69+(G67-G66)*0.75+(F67-F66)*0.25,1)) -> 35402.9 | H70: =IF($A$19,"n.a.",ROUND(H69+(H67-H66)*0.75+(G67-G66)*0.25,1)) -> 36964.9 | I70: =IF($A$19,"n.a.",ROUND(I69+(I67-I66)*0.75+(H67-H66)*0.25,1)) -> 38612.3 | J70: =IF($A$19,"n.a.",ROUND(J69+(J67-J66)*0.75+(I67-I66)*0.25,1)) -> 40348.1 | ... M70: =IF($A$19,"n.a.",ROUND(M69+(M67-M66)*0.75+(L67-L66)*0.25,1)) -> 46033
A71: Labor force (millions of people)
A72: January 2025 baseline | B72: 168.243 | C72: 170.662 | D72: 173.375 | E72: 174.006 | F72: 174.614 | G72: 175.295 | H72: 176.03 | I72: 176.801 | J72: 177.558 | K72: 178.176 | L72: 178.795 | M72: 179.386
A73: User-specified scenario | B73: =IF($A$19,"n.a.",B72) -> 168.243 | C73: =IF($A$19,"n.a.",ROUND(C72*(1+$C110*C115),3)) -> 170.662 | D73: =IF($A$19,"n.a.",ROUND(D72*(1+$D110*C115+$C110*D115),3)) -> 173.404 | E73: =IF($A$19,"n.a.",ROUND(E72*(1+$E110*C115+$D110*D117+$C110*E115),3)) -> 174.106 | F73: =IF($A$19,"n.a.",ROUND(F72*(1+$F110*C115+$E110*D115+$D110*E115+$C110*F115),3)) -> 174.793 | G73: =IF($A$19,"n.a.",ROUND(G72*(1+$G110*C115+$F110*D115+$E110*E115+$D110*F115+$C110*G115),3)) -> 175.599 | H73: =IF($A$19,"n.a.",ROUND(H72*(1+$H110*C115+$G110*D115+$F110*E115+$E110*F115+$D110*G115+$C110*H115),3)) -> 176.493 | I73: =IF($A$19,"n.a.",ROUND(I72*(1+$I110*C115+$H110*D115+$G110*E115+$F110*F115+$E110*G115+$D110*H115+$C110*I115),3)) -> 177.431 | J73: =IF($A$19,"n.a.",ROUND(J72*(1+$J110*C115+$I110*D115+$H110*E115+$G110*F115+$F110*G115+$E110*H115+$D110*I115+$C110*J115),3)) -> 178.362 | K73: =IF($A$19,"n.a.",ROUND(K72*(1+$K110*C115+$J110*D115+$I110*E115+$H110*F115+$G110*G115+$F110*H115+$E110*I115+$D110*J115+$C110*K115),3)) -> 179.16 | L73: =IF($A$19,"n.a.",ROUND(L72*(1+$L110*C115+$K110*D115+$J110*E115+$I110*F115+$H110*G115+$G110*H115+$F110*I115+$E110*J115+$D110*K115+$C110*L115),3)) -> 179.966 | M73: =IF($A$19,"n.a.",ROUND(M72*(1+$M110*C115+$L110*D115+$K110*E115+$J110*F115+$I110*G115+$H110*H115+$G110*I115+$F110*J115+$E110*K115+$D110*L115+$C110*M115),3)) -> 180.75
A74: Interest rate on 10-year Treasury notes (percent)
A75: January 2025 baseline | B75: 4.188 | C75: 4.093 | D75: 3.935 | E75: 3.914 | F75: 3.894 | G75: 3.871 | H75: 3.85 | I75: 3.836 | J75: 3.826 | K75: 3.815 | L75: 3.797 | M75: 3.772
A76: User-specified scenario | B76: =IF($A$19,"n.a.",B75) -> 4.188 | C76: =IF($A$19,"n.a.",ROUND(C75+$C109*C13,3)) -> 4.093 | D76: =IF($A$19,"n.a.",ROUND(D75+$D109*C13+$C109*D13,3)) -> 3.947 | E76: =IF($A$19,"n.a.",ROUND(E75+$E109*C13+$D109*D13+$C109*E13,3)) -> 3.951 | F76: =IF($A$19,"n.a.",ROUND(F75+$F109*C13+$E109*D13+$D109*E13+$C109*F13,3)) -> 3.966 | G76: =IF($A$19,"n.a.",ROUND(G75+$G109*C13+$F109*D13+$E109*E13+$D109*F13+$C109*G13,3)) -> 3.989 | H76: =IF($A$19,"n.a.",ROUND(H75+$H109*C13+$G109*D13+$F109*E13+$E109*F13+$D109*G13+$C109*H13,3)) -> 4.024 | I76: =IF($A$19,"n.a.",ROUND(I75+$I109*C13+$H109*D13+$G109*E13+$F109*F13+$E109*G13+$D109*H13+$C109*I13,3)) -> 4.064 | J76: =IF($A$19,"n.a.",ROUND(J75+$J109*C13+$I109*D13+$H109*E13+$G109*F13+$F109*G13+$E109*H13+$D109*I13+$C109*J13,3)) -> 4.105 | K76: =IF($A$19,"n.a.",ROUND(K75+$K109*C13+$J109*D13+$I109*E13+$H109*F13+$G109*G13+$F109*H13+$E109*I13+$D109*J13+$C109*K13,3)) -> 4.143 | L76: =IF($A$19,"n.a.",ROUND(L75+$L109*C13+$K109*D13+$J109*E13+$I109*F13+$H109*G13+$G109*H13+$F109*I13+$E109*J13+$D109*K13+$C109*L13,3)) -> 4.172 | M76: =IF($A$19,"n.a.",ROUND(M75+$M109*C13+$L109*D13+$K109*E13+$J109*F13+$I109*G13+$H109*H13+$G109*I13+$F109*J13+$E109*K13+$D109*L13+$C109*M13,3)) -> 4.192
A77: Inflation (percent)c
A78: January 2025 baseline | B78: 2.413 | C78: 2.198 | D78: 2.075 | E78: 1.995 | F78: 1.988 | G78: 1.992 | H78: 1.987 | I78: 1.986 | J78: 1.987 | K78: 1.991 | L78: 1.989 | M78: 1.99
A79: User-specified scenario | B79: =IF($A$19,"n.a.",B78) -> 2.413 | C79: =IF($A$19,"n.a.",C78) -> 2.198 | D79: =IF($A$19,"n.a.",D78) -> 2.075 | E79: =IF($A$19,"n.a.",E78) -> 1.995 | F79: =IF($A$19,"n.a.",F78) -> 1.988 | G79: =IF($A$19,"n.a.",G78) -> 1.992 | H79: =IF($A$19,"n.a.",H78) -> 1.987 | I79: =IF($A$19,"n.a.",I78) -> 1.986 | ... M79: =IF($A$19,"n.a.",M78) -> 1.99
A80: GDP price index (2017 = 100)
A81: January 2025 baseline | B81: 125.223 | C81: 127.976 | D81: 130.631 | E81: 133.238 | F81: 135.887 | G81: 138.595 | H81: 141.349 | I81: 144.157 | J81: 147.023 | K81: 149.95 | L81: 152.934 | M81: 155.979
A82: User-specified scenario | B82: =IF($A$19,"n.a.",B81) -> 125.223 | C82: =IF($A$19,"n.a.",C81) -> 127.976 | D82: =IF($A$19,"n.a.",D81) -> 130.631 | E82: =IF($A$19,"n.a.",E81) -> 133.238 | F82: =IF($A$19,"n.a.",F81) -> 135.887 | G82: =IF($A$19,"n.a.",G81) -> 138.595 | H82: =IF($A$19,"n.a.",H81) -> 141.349 | I82: =IF($A$19,"n.a.",I81) -> 144.157 | ... M82: =IF($A$19,"n.a.",M81) -> 155.979
A83: Employment cost index (December 2005 = 100)d
A84: January 2025 baseline | B84: 168.291 | C84: 174.156 | D84: 180 | E84: 185.768 | F84: 191.526 | G84: 197.325 | H84: 203.213 | I84: 209.221 | J84: 215.381 | K84: 221.716 | L84: 228.225 | M84: 234.91
A85: User-specified scenario | B85: =IF($A$19,"n.a.",B84) -> 168.291 | C85: =IF($A$19,"n.a.",ROUND((C67/C73)/(C66/C72)*C84,3)) -> 174.156 | D85: =IF($A$19,"n.a.",ROUND((D67/D73)/(D66/D72)*D84,3)) -> 180.166 | E85: =IF($A$19,"n.a.",ROUND((E67/E73)/(E66/E72)*E84,3)) -> 186.273 | F85: =IF($A$19,"n.a.",ROUND((F67/F73)/(F66/F72)*F84,3)) -> 192.607 | G85: =IF($A$19,"n.a.",ROUND((G67/G73)/(G66/G72)*G84,3)) -> 199.202 | H85: =IF($A$19,"n.a.",ROUND((H67/H73)/(H66/H72)*H84,3)) -> 206.148 | I85: =IF($A$19,"n.a.",ROUND((I67/I73)/(I66/I72)*I84,3)) -> 213.309 | J85: =IF($A$19,"n.a.",ROUND((J67/J73)/(J66/J72)*J84,3)) -> 220.72 | ... M85: =IF($A$19,"n.a.",ROUND((M67/M73)/(M66/M72)*M84,3)) -> 244.648
A88: Data source: Congressional Budget Office.
A90: Real values are nominal values that have been adjusted to remove the effects of changes in prices.
A92: See the “Contents” worksheet for a brief discussion of the formulas used in these tables.
A94: Unless otherwise noted, economic indicators are calendar year averages.
A96: GDP = gross domestic product; n.a. = not applicable.
A98: a. Measured using the index for potential total factor productivity in the nonfarm business sector. Total factor productivity is calculated as the average real output per unit of combined labor and capital services. Although all productivity-related indexes change in this scenario, the table shows only the effects on the index for potential total factor productivity in the nonfarm business sector.
A100: b. Discretionary outlays do not change in the user-specified scenario.
A102: c. Measured using the GDP price index.
A104: d. The employment cost index for wages and salaries of workers in private industry.
A107: Parameters
A108: Real GDP | C108: 1.095609 | D108: 0.040825 | E108: 0.037559 | F108: 0.035649 | G108: 0.034294 | H108: 0.033242 | I108: 0.032383 | J108: 0.031657 | K108: 0.031028 | L108: 0.030473 | M108: 0.029976
A109: Interest Rates | C109: 0.123846 | D109: 0.117642 | E109: 0.112054 | F109: 0.106971 | G109: 0.102282 | H109: 0.097875 | I109: 0.093639 | J109: 0.089462 | K109: 0.085232 | L109: 0.08084 | M109: 0.076172
A110: Labor Force | C110: 0.168606 | D110: 0.006104 | E110: 0.00581 | F110: 0.005631 | G110: 0.00533 | H110: 0.005257 | I110: 0.004987 | J110: 0.004913 | K110: 0.005026 | L110: 0.004653 | M110: 0.004408
A113: Productivity Index Base | B113: 100 | C113: =B113*(1+C16/100) -> 100.983 | D113: =C113*(1+D16/100) -> 102.00798 | E113: =D113*(1+E16/100) -> 103.08722 | F113: =E113*(1+F16/100) -> 104.22634 | G113: =F113*(1+G16/100) -> 105.40305 | H113: =G113*(1+H16/100) -> 106.58989 | I113: =H113*(1+I16/100) -> 107.78903 | J113: =I113*(1+J16/100) -> 108.99734 | ... M113: =L113*(1+M16/100) -> 112.68076
A114: Productivity Index Scenario | B114: 100 | C114: =B114*(1+C17/100) -> 100.983 | D114: =C114*(1+D17/100) -> 102.10896 | E114: =D114*(1+E17/100) -> 103.39349 | F114: =E114*(1+F17/100) -> 104.84617 | G114: =F114*(1+G17/100) -> 106.44927 | H114: =G114*(1+H17/100) -> 108.18013 | I114: =H114*(1+I17/100) -> 109.93806 | J114: =I114*(1+J17/100) -> 111.72016 | ... M114: =L114*(1+M17/100) -> 117.21742
A115: Productivity Deviation | C115: =C114/C113-1 -> 0 | D115: =D114/D113-1 -> 0.00098995199 | E115: =E114/E113-1 -> 0.0029709727 | F115: =F114/F113-1 -> 0.0059470005 | G115: =G114/G113-1 -> 0.0099258671 | H115: =H114/H113-1 -> 0.014919271 | I115: =I114/I113-1 -> 0.019937413 | J115: =J114/J113-1 -> 0.024980566 | ... M115: =M114/M113-1 -> 0.0402612
A117: Interest Rate Change | C117: =C76-C75 -> 0 | D117: =D76-D75 -> 0.012 | E117: =E76-E75 -> 0.037 | F117: =F76-F75 -> 0.072 | G117: =G76-G75 -> 0.118 | H117: =H76-H75 -> 0.174 | I117: =I76-I75 -> 0.228 | J117: =J76-J75 -> 0.279 | ... M117: =M76-M75 -> 0.42
A119: Interest Change Matrix | C119: 52.194 | D119: 72.44 | E119: 41.604 | F119: 33.166 | G119: 27.507 | H119: 24.802 | I119: 18.083 | J119: 16.269 | K119: 12.265 | L119: 12.07 | M119: 10.215
C120: 0 | D120: 54.98 | E120: 76.133 | F120: 43.307 | G120: 34.496 | H120: 28.579 | I120: 25.954 | J120: 19.027 | K120: 16.892 | L120: 12.59 | M120: 12.39
C121: 0 | D121: 0 | E121: 56.723 | F121: 80.096 | G121: 45.121 | H121: 35.912 | I121: 29.72 | J121: 27.184 | K121: 20.037 | L121: 17.55 | M121: 12.931
C122: 0 | D122: 0 | E122: 0 | F122: 60.441 | G122: 85.403 | H122: 48.331 | I122: 38.578 | J122: 31.995 | K122: 28.98 | L122: 21.3 | M122: 18.656
C123: 0 | D123: 0 | E123: 0 | F123: 0 | G123: 63.893 | H123: 89.099 | I123: 50.653 | J123: 40.547 | K123: 33.7 | L123: 30.224 | M123: 22.152
C124: 0 | D124: 0 | E124: 0 | F124: 0 | G124: 0 | H124: 68.037 | I124: 94.484 | J124: 53.69 | K124: 43.116 | L124: 35.888 | M124: 32.186
C125: 0 | D125: 0 | E125: 0 | F125: 0 | G125: 0 | H125: 0 | I125: 70.948 | J125: 99.77 | K125: 56.668 | L125: 45.654 | M125: 38.056
C126: 0 | D126: 0 | E126: 0 | F126: 0 | G126: 0 | H126: 0 | I126: 0 | J126: 74.688 | K126: 103.9 | L126: 58.811 | M126: 47.381
C127: 0 | D127: 0 | E127: 0 | F127: 0 | G127: 0 | H127: 0 | I127: 0 | J127: 0 | K127: 78.212 | L127: 110.358 | M127: 62.251
C128: 0 | D128: 0 | E128: 0 | F128: 0 | G128: 0 | H128: 0 | I128: 0 | J128: 0 | K128: 0 | L128: 81.424 | M128: 113.933
C129: 0 | D129: 0 | E129: 0 | F129: 0 | G129: 0 | H129: 0 | I129: 0 | J129: 0 | K129: 0 | L129: 0 | M129: 85.108
A131: Net Interest Residual | C131: 0.03 | D131: -0.125 | E131: -0.221 | F131: -0.316 | G131: -0.413 | H131: -0.63 | I131: -0.89 | J131: -1.152 | K131: -1.361 | L131: -1.577 | M131: -1.843
A133: Deficit for Debt Service | C133: =C27+C28+C30-C24 -> 0 | D133: =D27+D28+D30-D24 -> -3.762 | E133: =E27+E28+E30-E24 -> -12.704 | F133: =F27+F28+F30-F24 -> -26.755 | G133: =G27+G28+G30-G24 -> -47.134 | H133: =H27+H28+H30-H24 -> -73.526 | I133: =I27+I28+I30-I24 -> -102.237 | J133: =J27+J28+J30-J24 -> -132.473 | ... M133: =M27+M28+M30-M24 -> -238.551
A135: Debt Service Matrix | C135: 0.0105 | D135: 0.0379 | E135: 0.0373 | F135: 0.0383 | G135: 0.0393 | H135: 0.0403 | I135: 0.0411 | J135: 0.0422 | K135: 0.0432 | L135: 0.0445 | M135: 0.0456
C136: 0 | D136: 0.0185 | E136: 0.0365 | F136: 0.0378 | G136: 0.0387 | H136: 0.0398 | I136: 0.041 | J136: 0.042 | K136: 0.0432 | L136: 0.0445 | M136: 0.0459
...

Sheet 2. Labor Force
A1: This workbook supplements CBO’s report How Changes in Economic Conditions Might Affect the Federal Budget: 2025 to 2035.
A2: www.cbo.gov/publication/61198
A5: To create an alternative scenario for labor force growth, enter values between -0.75 percentage points and 0.75 percentage points in each of the green cells. (Only the green cells can be edited; all other cells are locked. Values outside of the specified range will produce errors.) The change in budgetary outcomes relative to those in CBO’s baseline will be calculated and appear automatically. Values for key economic indicators are shown below those budgetary effects.
A7: 2. Interactive Table: How Changes in Labor Force Growth Might Affect the Federal Budget
B9: 2024 | C9: 2025 | D9: 2026 | E9: 2027 | F9: 2028 | G9: 2029 | H9: 2030 | I9: 2031 | J9: 2032 | K9: 2033 | L9: 2034 | M9: 2035
C11: User-specified scenario for annual labor force growth
O12: These initial values are the same as those used to generate the illustrative scenario shown in Worksheet 6, “Labor Force_CBO.”
A13: Increase or decrease (-) in labor force growth relative to CBO’s January 2025 baseline (percentage points) | B13: n.a. | C13: -0.1 | D13: -0.1 | E13: -0.1 | F13: -0.1 | G13: -0.1 | H13: -0.1 | I13: -0.1 | J13: -0.1 | K13: -0.1 | L13: -0.1 | M13: -0.1
A14: =IF($A$19,"Please keep values in the range [-0.75, 0.75] percentage points per year.","")
A15: Labor force growth (percent)
A16: January 2025 baseline | B16: 0.67 | C16: 1.438 | D16: 1.589 | E16: 0.364 | F16: 0.349 | G16: 0.389 | H16: 0.419 | I16: 0.437 | J16: 0.428 | K16: 0.348 | L16: 0.347 | M16: 0.33
A17: User-specified scenarioa | B17: =IF($A$19,"n.a.",B16) -> 0.67 | C17: =IF($A$19,"n.a.",(C73/B73-1)*100) -> 1.3444839 | D17: =IF($A$19,"n.a.",(D73/C73-1)*100) -> 1.4955573 | E17: =IF($A$19,"n.a.",(E73/D73-1)*100) -> 0.26927855 | F17: =IF($A$19,"n.a.",(F73/E73-1)*100) -> 0.25472421 | G17: =IF($A$19,"n.a.",(G73/F73-1)*100) -> 0.29546513 | H17: =IF($A$19,"n.a.",(H73/G73-1)*100) -> 0.32439806 | I17: =IF($A$19,"n.a.",(I73/H73-1)*100) -> 0.34277292 | J17: =IF($A$19,"n.a.",(J73/I73-1)*100) -> 0.33306195 | ... M17: =IF($A$19,"n.a.",(M73/L73-1)*100) -> 0.23543493
A19: =IF(OR(MAX(C13:M13)>0.75,MIN(C13:M13)<-0.75),1,0) -> 0
C21: Budgetary effects (billions of dollars) | N21: Total
N22: 2026- | O22: 2026-
B23: 2024 | C23: 2025 | D23: 2026 | E23: 2027 | F23: 2028 | G23: 2029 | H23: 2030 | I23: 2031 | J23: 2032 | K23: 2033 | L23: 2034 | M23: 2035 | N23: 2030 | O23: 2035
A24: Changes in revenues | B24: n.a. | C24: =IF($A$19,"n.a.",ROUND('6. Labor Force_CBO'!C11/('6. Labor Force_CBO'!C57-'6. Labor Force_CBO'!C56)*(ROUND('2. Labor Force'!C70,1)-ROUND('2. Labor Force'!C69,1)),3)) -> -1.649 | D24: =IF($A$19,"n.a.",ROUND('6. Labor Force_CBO'!D11/('6. Labor Force_CBO'!D57-'6. Labor Force_CBO'!D56)*(ROUND('2. Labor Force'!D70,1)-ROUND('2. Labor Force'!D69,1)),3)) -> -4.283 | E24: =IF($A$19,"n.a.",ROUND('6. Labor Force_CBO'!E11/('6. Labor Force_CBO'!E57-'6. Labor Force_CBO'!E56)*(ROUND('2. Labor Force'!E70,1)-ROUND('2. Labor Force'!E69,1)),3)) -> -7.2 | F24: =IF($A$19,"n.a.",ROUND('6. Labor Force_CBO'!F11/('6. Labor Force_CBO'!F57-'6. Labor Force_CBO'!F56)*(ROUND('2. Labor Force'!F70,1)-ROUND('2. Labor Force'!F69,1)),3)) -> -10.373 | G24: =IF($A$19,"n.a.",ROUND('6. Labor Force_CBO'!G11/('6. Labor Force_CBO'!G57-'6. Labor Force_CBO'!G56)*(ROUND('2. Labor Force'!G70,1)-ROUND('2. Labor Force'!G69,1)),3)) -> -13.878 | H24: =IF($A$19,"n.a.",ROUND('6. Labor Force_CBO'!H11/('6. Labor Force_CBO'!H57-'6. Labor Force_CBO'!H56)*(ROUND('2. Labor Force'!H70,1)-ROUND('2. Labor Force'!H69,1)),3)) -> -17.782 | I24: =IF($A$19,"n.a.",ROUND('6. Labor Force_CBO'!I11/('6. Labor Force_CBO'!I57-'6. Labor Force_CBO'!I56)*(ROUND('2. Labor Force'!I70,1)-ROUND('2. Labor Force'!I69,1)),3)) -> -22.053 | J24: =IF($A$19,"n.a.",ROUND('6. Labor Force_CBO'!J11/('6. Labor Force_CBO'!J57-'6. Labor Force_CBO'!J56)*(ROUND('2. Labor Force'!J70,1)-ROUND('2. Labor Force'!J69,1)),3)) -> -26.788 | ... M24: =IF($A$19,"n.a.",ROUND('6. Labor Force_CBO'!M11/('6. Labor Force_CBO'!M57-'6. Labor Force_CBO'!M56)*(ROUND('2. Labor Force'!M70,1)-ROUND('2. Labor Force'!M69,1)),3)) -> -43.764 | N24: =IF($A$19,"n.a.",SUM(D24:H24)) -> -53.516 | O24: =IF($A$19,"n.a.",SUM(D24:M24)) -> -215.642
A26: Changes in outlays
A27: Mandatory outlays | B27: n.a. | C27: =IF($A$19,"n.a.",ROUND('6. Labor Force_CBO'!C14/('6. Labor Force_CBO'!C57-'6. Labor Force_CBO'!C56)*(ROUND('2. Labor Force'!C70,1)-ROUND('2. Labor Force'!C69,1)),3)) -> 0.281 | D27: =IF($A$19,"n.a.",ROUND('6. Labor Force_CBO'!D14/('6. Labor Force_CBO'!D57-'6. Labor Force_CBO'!D56)*(ROUND('2. Labor Force'!D70,1)-ROUND('2. Labor Force'!D69,1)),3)) -> 0.74 | E27: =IF($A$19,"n.a.",ROUND('6. Labor Force_CBO'!E14/('6. Labor Force_CBO'!E57-'6. Labor Force_CBO'!E56)*(ROUND('2. Labor Force'!E70,1)-ROUND('2. Labor Force'!E69,1)),3)) -> 1.211 | F27: =IF($A$19,"n.a.",ROUND('6. Labor Force_CBO'!F14/('6. Labor Force_CBO'!F57-'6. Labor Force_CBO'!F56)*(ROUND('2. Labor Force'!F70,1)-ROUND('2. Labor Force'!F69,1)),3)) -> 1.733 | G27: =IF($A$19,"n.a.",ROUND('6. Labor Force_CBO'!G14/('6. Labor Force_CBO'!G57-'6. Labor Force_CBO'!G56)*(ROUND('2. Labor Force'!G70,1)-ROUND('2. Labor Force'!G69,1)),3)) -> 2.29 | H27: =IF($A$19,"n.a.",ROUND('6. Labor Force_CBO'!H14/('6. Labor Force_CBO'!H57-'6. Labor Force_CBO'!H56)*(ROUND('2. Labor Force'!H70,1)-ROUND('2. Labor Force'!H69,1)),3)) -> 2.856 | I27: =IF($A$19,"n.a.",ROUND('6. Labor Force_CBO'!I14/('6. Labor Force_CBO'!I57-'6. Labor Force_CBO'!I56)*(ROUND('2. Labor Force'!I70,1)-ROUND('2. Labor Force'!I69,1)),3)) -> 3.532 | J27: =IF($A$19,"n.a.",ROUND('6. Labor Force_CBO'!J14/('6. Labor Force_CBO'!J57-'6. Labor Force_CBO'!J56)*(ROUND('2. Labor Force'!J70,1)-ROUND('2. Labor Force'!J69,1)),3)) -> 4.482 | ... M27: =IF($A$19,"n.a.",ROUND('6. Labor Force_CBO'!M14/('6. Labor Force_CBO'!M57-'6. Labor Force_CBO'!M56)*(ROUND('2. Labor Force'!M70,1)-ROUND('2. Labor Force'!M69,1)),3)) -> 7.304 | N27: =IF($A$19,"n.a.",SUM(D27:H27)) -> 8.83 | O27: =IF($A$19,"n.a.",SUM(D27:M27)) -> 35.906
A28: Discretionary outlaysb | B28: n.a. | C28: =IF($A$19,"n.a.",0) -> 0 | D28: =IF($A$19,"n.a.",0) -> 0 | E28: =IF($A$19,"n.a.",0) -> 0 | F28: =IF($A$19,"n.a.",0) -> 0 | G28: =IF($A$19,"n.a.",0) -> 0 | H28: =IF($A$19,"n.a.",0) -> 0 | I28: =IF($A$19,"n.a.",0) -> 0 | J28: =IF($A$19,"n.a.",0) -> 0 | ... M28: =IF($A$19,"n.a.",0) -> 0 | N28: =IF($A$19,"n.a.",SUM(D28:H28)) -> 0 | O28: =IF($A$19,"n.a.",SUM(D28:M28)) -> 0
A29: Net interest outlays
A30: Effects from changes in interest rates | B30: n.a. | C30: {=IF($A$19,"n.a.",ROUND(SUMPRODUCT(TRANSPOSE($C115:$M115),C117:C127),3)+ROUND(C129*C115/('6. Labor Force_CBO'!C63-'6. Labor Force_CBO'!C62),3))} -> -0.3 | D30: {=IF($A$19,"n.a.",ROUND(SUMPRODUCT(TRANSPOSE($C115:$M115),D117:D127),3)+ROUND(D129*D115/('6. Labor Force_CBO'!D63-'6. Labor Force_CBO'!D62),3))} -> -1.101 | E30: {=IF($A$19,"n.a.",ROUND(SUMPRODUCT(TRANSPOSE($C115:$M115),E117:E127),3)+ROUND(E129*E115/('6. Labor Force_CBO'!E63-'6. Labor Force_CBO'!E62),3))} -> -2.174 | F30: {=IF($A$19,"n.a.",ROUND(SUMPRODUCT(TRANSPOSE($C115:$M115),F117:F127),3)+ROUND(F129*F115/('6. Labor Force_CBO'!F63-'6. Labor Force_CBO'!F62),3))} -> -3.507 | G30: {=IF($A$19,"n.a.",ROUND(SUMPRODUCT(TRANSPOSE($C115:$M115),G117:G127),3)+ROUND(G129*G115/('6. Labor Force_CBO'!G63-'6. Labor Force_CBO'!G62),3))} -> -5.131 | H30: {=IF($A$19,"n.a.",ROUND(SUMPRODUCT(TRANSPOSE($C115:$M115),H117:H127),3)+ROUND(H129*H115/('6. Labor Force_CBO'!H63-'6. Labor Force_CBO'!H62),3))} -> -7.009 | I30: {=IF($A$19,"n.a.",ROUND(SUMPRODUCT(TRANSPOSE($C115:$M115),I117:I127),3)+ROUND(I129*I115/('6. Labor Force_CBO'!I63-'6. Labor Force_CBO'!I62),3))} -> -9.071 | J30: {=IF($A$19,"n.a.",ROUND(SUMPRODUCT(TRANSPOSE($C115:$M115),J117:J127),3)+ROUND(J129*J115/('6. Labor Force_CBO'!J63-'6. Labor Force_CBO'!J62),3))} -> -11.442 | ... M30: {=IF($A$19,"n.a.",ROUND(SUMPRODUCT(TRANSPOSE($C115:$M115),M117:M127),3)+ROUND(M129*M115/('6. Labor Force_CBO'!M63-'6. Labor Force_CBO'!M62),3))} -> -19.399 | N30: =IF($A$19,"n.a.",SUM(D30:H30)) -> -18.922 | O30: =IF($A$19,"n.a.",SUM(D30:M30)) -> -89.358
A31: Debt service | B31: n.a. | C31: {=IF($A$19,"n.a.",ROUND(SUMPRODUCT($C131:$M131,TRANSPOSE(C133:C143)),3) + ROUND((-C145)*C131/('6. Labor Force_CBO'!C24+'6. Labor Force_CBO'!C18),3))} -> 0.017 | D31: {=IF($A$19,"n.a.",ROUND(SUMPRODUCT($C131:$M131,TRANSPOSE(D133:D143)),3) + ROUND((-D145)*D131/('6. Labor Force_CBO'!D24+'6. Labor Force_CBO'!D18),3))} -> 0.138 | E31: {=IF($A$19,"n.a.",ROUND(SUMPRODUCT($C131:$M131,TRANSPOSE(E133:E143)),3) + ROUND((-E145)*E131/('6. Labor Force_CBO'!E24+'6. Labor Force_CBO'!E18),3))} -> 0.329 | F31: {=IF($A$19,"n.a.",ROUND(SUMPRODUCT($C131:$M131,TRANSPOSE(F133:F143)),3) + ROUND((-F145)*F131/('6. Labor Force_CBO'!F24+'6. Labor Force_CBO'!F18),3))} -> 0.609 | G31: {=IF($A$19,"n.a.",ROUND(SUMPRODUCT($C131:$M131,TRANSPOSE(G133:G143)),3) + ROUND((-G145)*G131/('6. Labor Force_CBO'!G24+'6. Labor Force_CBO'!G18),3))} -> 0.982 | H31: {=IF($A$19,"n.a.",ROUND(SUMPRODUCT($C131:$M131,TRANSPOSE(H133:H143)),3) + ROUND((-H145)*H131/('6. Labor Force_CBO'!H24+'6. Labor Force_CBO'!H18),3))} -> 1.457 | I31: {=IF($A$19,"n.a.",ROUND(SUMPRODUCT($C131:$M131,TRANSPOSE(I133:I143)),3) + ROUND((-I145)*I131/('6. Labor Force_CBO'!I24+'6. Labor Force_CBO'!I18),3))} -> 2.036 | J31: {=IF($A$19,"n.a.",ROUND(SUMPRODUCT($C131:$M131,TRANSPOSE(J133:J143)),3) + ROUND((-J145)*J131/('6. Labor Force_CBO'!J24+'6. Labor Force_CBO'!J18),3))} -> 2.743 | ... M31: {=IF($A$19,"n.a.",ROUND(SUMPRODUCT($C131:$M131,TRANSPOSE(M133:M143)),3) + ROUND((-M145)*M131/('6. Labor Force_CBO'!M24+'6. Labor Force_CBO'!M18),3))} -> 5.776 | N31: =IF($A$19,"n.a.",SUM(D31:H31)) -> 3.515 | O31: =IF($A$19,"n.a.",SUM(D31:M31)) -> 22.254
B32: ____ | C32: ____ | D32: ____ | E32: ____ | F32: ____ | G32: ____ | H32: ____ | I32: ____ | J32: ____ | K32: ____ | L32: ____ | M32: ____ | N32: ____ | O32: ____
A33: Subtotal, net interest outlays | B33: n.a. | C33: =IF($A$19,"n.a.",C30+C31) -> -0.283 | D33: =IF($A$19,"n.a.",D30+D31) -> -0.963 | E33: =IF($A$19,"n.a.",E30+E31) -> -1.845 | F33: =IF($A$19,"n.a.",F30+F31) -> -2.898 | G33: =IF($A$19,"n.a.",G30+G31) -> -4.149 | H33: =IF($A$19,"n.a.",H30+H31) -> -5.552 | I33: =IF($A$19,"n.a.",I30+I31) -> -7.035 | J33: =IF($A$19,"n.a.",J30+J31) -> -8.699 | ... M33: =IF($A$19,"n.a.",M30+M31) -> -13.623 | N33: =IF($A$19,"n.a.",SUM(D33:H33)) -> -15.407 | O33: =IF($A$19,"n.a.",SUM(D33:M33)) -> -67.104
A35: Total change in outlays | B35: n.a. | C35: =IF($A$19,"n.a.",C27+C28+C33) -> -0.002 | D35: =IF($A$19,"n.a.",D27+D28+D33) -> -0.223 | E35: =IF($A$19,"n.a.",E27+E28+E33) -> -0.634 | F35: =IF($A$19,"n.a.",F27+F28+F33) -> -1.165 | G35: =IF($A$19,"n.a.",G27+G28+G33) -> -1.859 | H35: =IF($A$19,"n.a.",H27+H28+H33) -> -2.696 | I35: =IF($A$19,"n.a.",I27+I28+I33) -> -3.503 | J35: =IF($A$19,"n.a.",J27+J28+J33) -> -4.217 | ... M35: =IF($A$19,"n.a.",M27+M28+M33) -> -6.319 | N35: =IF($A$19,"n.a.",SUM(D35:H35)) -> -6.577 | O35: =IF($A$19,"n.a.",SUM(D35:M35)) -> -31.198
A37: Increase (-) or decrease in the deficit relative to CBO’s baseline | B37: n.a. | C37: =IF($A$19,"n.a.",C24-C35) -> -1.647 | D37: =IF($A$19,"n.a.",D24-D35) -> -4.06 | E37: =IF($A$19,"n.a.",E24-E35) -> -6.566 | F37: =IF($A$19,"n.a.",F24-F35) -> -9.208 | G37: =IF($A$19,"n.a.",G24-G35) -> -12.019 | H37: =IF($A$19,"n.a.",H24-H35) -> -15.086 | I37: =IF($A$19,"n.a.",I24-I35) -> -18.55 | J37: =IF($A$19,"n.a.",J24-J35) -> -22.571 | ... M37: =IF($A$19,"n.a.",M24-M35) -> -37.445 | N37: =IF($A$19,"n.a.",SUM(D37:H37)) -> -46.939 | O37: =IF($A$19,"n.a.",SUM(D37:M37)) -> -184.444
A39: Deficit (-) or surplus
A40: January 2025 baseline | B40: -1832.381 | C40: -1865.251 | D40: -1713.258 | E40: -1686.942 | F40: -1910.776 | G40: -1938.268 | H40: -2139.721 | I40: -2232.786 | J40: -2370.582 | K40: -2637.299 | L40: -2597.25 | M40: -2531.378 | N40: -9388.965 | O40: -21758.26
A41: User-specified scenario | B41: =IF($A$19,"n.a.",B40) -> -1832.381 | C41: =IF($A$19,"n.a.",C40+C37) -> -1866.898 | D41: =IF($A$19,"n.a.",D40+D37) -> -1717.318 | E41: =IF($A$19,"n.a.",E40+E37) -> -1693.508 | F41: =IF($A$19,"n.a.",F40+F37) -> -1919.984 | G41: =IF($A$19,"n.a.",G40+G37) -> -1950.287 | H41: =IF($A$19,"n.a.",H40+H37) -> -2154.807 | I41: =IF($A$19,"n.a.",I40+I37) -> -2251.336 | J41: =IF($A$19,"n.a.",J40+J37) -> -2393.153 | ... M41: =IF($A$19,"n.a.",M40+M37) -> -2568.823 | N41: =IF($A$19,"n.a.",SUM(D41:H41)) -> -9435.904 | O41: =IF($A$19,"n.a.",SUM(D41:M41)) -> -21942.704
A43: Debt held by the public
A44: January 2025 baseline | B44: 28199.313 | C44: 30102.749 | D44: 31882.633 | E44: 33636.105 | F44: 35600.64 | G44: 37580.5 | H44: 39747.651 | I44: 41992.385 | J44: 44371.755 | K44: 46985.029 | L44: 49555.504 | M44: 52055.866 | N44: n.a. | O44: n.a.
A45: User-specified scenario | B45: =IF($A$19,"n.a.",B44) -> 28199.313 | C45: =IF($A$19,"n.a.",C44-SUM($C37:C37)) -> 30104.396 | D45: =IF($A$19,"n.a.",D44-SUM($C37:D37)) -> 31888.34 | E45: =IF($A$19,"n.a.",E44-SUM($C37:E37)) -> 33648.378 | F45: =IF($A$19,"n.a.",F44-SUM($C37:F37)) -> 35622.121 | G45: =IF($A$19,"n.a.",G44-SUM($C37:G37)) -> 37614 | H45: =IF($A$19,"n.a.",H44-SUM($C37:H37)) -> 39796.237 | I45: =IF($A$19,"n.a.",I44-SUM($C37:I37)) -> 42059.521 | J45: =IF($A$19,"n.a.",J44-SUM($C37:J37)) -> 44461.462 | ... M45: =IF($A$19,"n.a.",M44-SUM($C37:M37)) -> 52241.957 | N45: n.a. | O45: n.a.
A47: Deficit (-) or surplus (percentage of GDP)
A48: January 2025 baseline | B48: -6.3562158 | C48: -6.1894147 | D48: -5.4664504 | E48: -5.184518 | F48: -5.659123 | G48: -5.5304586 | H48: -5.8793652 | I48: -5.9080768 | J48: -6.0393242 | K48: -6.4690633 | L48: -6.1356563 | M48: -5.7614482 | N48: -5.5528141 | O48: -5.830748
A49: User-specified scenario | B49: =IF($A$19,"n.a.",B48) -> -6.3562158 | C49: =IF($A$19,"n.a.",ROUND(C41/C70*100,3)) -> -6.197 | D49: =IF($A$19,"n.a.",ROUND(D41/D70*100,3)) -> -5.484 | E49: =IF($A$19,"n.a.",ROUND(E41/E70*100,3)) -> -5.212 | F49: =IF($A$19,"n.a.",ROUND(F41/F70*100,3)) -> -5.698 | G49: =IF($A$19,"n.a.",ROUND(G41/G70*100,3)) -> -5.579 | H49: =IF($A$19,"n.a.",ROUND(H41/H70*100,3)) -> -5.94 | I49: =IF($A$19,"n.a.",ROUND(I41/I70*100,3)) -> -5.98 | J49: =IF($A$19,"n.a.",ROUND(J41/J70*100,3)) -> -6.124 | ... M49: =IF($A$19,"n.a.",ROUND(M41/M70*100,3)) -> -5.885 | N49: =IF($A$19,"n.a.",ROUND(SUM(D41:H41)/SUM(D70:H70)*100,3)) -> -5.592 | O49: =IF($A$19,"n.a.",ROUND(SUM(D41:M41)/SUM(D70:M70)*100,3)) -> -5.903
A51: Debt held by the public (percentage of GDP)
A52: January 2025 baseline | B52: 97.818585 | C52: 99.889183 | D52: 101.72714 | E52: 103.37462 | F52: 105.438 | G52: 107.22841 | H52: 109.21562 | I52: 111.1142 | J52: 113.04204 | K52: 115.25016 | L52: 117.06826 | M52: 118.47981 | N52: n.a. | O52: n.a.
A53: User-specified scenario | B53: =IF($A$19,"n.a.",B52) -> 97.818585 | C53: =IF($A$19,"n.a.",ROUND(C45/C70*100,3)) -> 99.934 | D53: =IF($A$19,"n.a.",ROUND(D45/D70*100,3)) -> 101.839 | E53: =IF($A$19,"n.a.",ROUND(E45/E70*100,3)) -> 103.565 | F53: =IF($A$19,"n.a.",ROUND(F45/F70*100,3)) -> 105.719 | G53: =IF($A$19,"n.a.",ROUND(G45/G70*100,3)) -> 107.608 | H53: =IF($A$19,"n.a.",ROUND(H45/H70*100,3)) -> 109.705 | I53: =IF($A$19,"n.a.",ROUND(I45/I70*100,3)) -> 111.723 | J53: =IF($A$19,"n.a.",ROUND(J45/J70*100,3)) -> 113.782 | ... M53: =IF($A$19,"n.a.",ROUND(M45/M70*100,3)) -> 119.679 | N53: n.a. | O53: n.a.
B56: Economic indicators in CBO’s January 2025 baseline and under the user-specified scenario
B58: 2024 | C58: 2025 | D58: 2026 | E58: 2027 | F58: 2028 | G58: 2029 | H58: 2030 | I58: 2031 | J58: 2032 | K58: 2033 | L58: 2034 | M58: 2035
A59: Real GDP growth (percent)
A60: January 2025 baseline | B60: 2.734 | C60: 2.124 | D60: 1.827 | E60: 1.763 | F60: 1.744 | G60: 1.786 | H60: 1.821 | I60: 1.822 | J60: 1.842 | K60: 1.826 | L60: 1.797 | M60: 1.76
A61: User-specified scenario | B61: =IF($A$19,"n.a.",B60) -> 2.734 | C61: =IF($A$19,"n.a.",ROUND((C64/B64-1)*100,3)) -> 2.072 | D61: =IF($A$19,"n.a.",ROUND((D64/C64-1)*100,3)) -> 1.773 | E61: =IF($A$19,"n.a.",ROUND((E64/D64-1)*100,3)) -> 1.706 | F61: =IF($A$19,"n.a.",ROUND((F64/E64-1)*100,3)) -> 1.686 | G61: =IF($A$19,"n.a.",ROUND((G64/F64-1)*100,3)) -> 1.726 | H61: =IF($A$19,"n.a.",ROUND((H64/G64-1)*100,3)) -> 1.76 | I61: =IF($A$19,"n.a.",ROUND((I64/H64-1)*100,3)) -> 1.759 | J61: =IF($A$19,"n.a.",ROUND((J64/I64-1)*100,3)) -> 1.778 | ... M61: =IF($A$19,"n.a.",ROUND((M64/L64-1)*100,3)) -> 1.691
A62: Real GDP (billions of 2017 dollars)
A63: January 2025 baseline | B63: 23290.9 | C63: 23785.8 | D63: 24220.5 | E63: 24647.6 | F63: 25077.7 | G63: 25525.6 | H63: 25990.7 | I63: 26464.3 | J63: 26952 | K63: 27444.4 | L63: 27937.8 | M63: 28429.6
A64: User-specified scenario | B64: =IF($A$19,"n.a.",B63) -> 23290.9 | C64: =IF($A$19,"n.a.",ROUND(C63*(1+$C108*C113),1)) -> 23773.5 | D64: =IF($A$19,"n.a.",ROUND(D63*(1+$D108*C113+$C108*D113),1)) -> 24195 | E64: =IF($A$19,"n.a.",ROUND(E63*(1+$E108*C113+$D108*D113+$C108*E113),1)) -> 24607.8 | F64: =IF($A$19,"n.a.",ROUND(F63*(1+$F108*C113+$E108*D113+$D108*E113+$C108*F113),1)) -> 25022.7 | G64: =IF($A$19,"n.a.",ROUND(G63*(1+$G108*C113+$F108*D113+$E108*E113+$D108*F113+$C108*G113),1)) -> 25454.5 | H64: =IF($A$19,"n.a.",ROUND(H63*(1+$H108*C113+$G108*D113+$F108*E113+$E108*F113+$D108*G113+$C108*H113),1)) -> 25902.5 | I64: =IF($A$19,"n.a.",ROUND(I63*(1+$I108*C113+$H108*D113+$G108*E113+$F108*F113+$E108*G113+$D108*H113+$C108*I113),1)) -> 26358.1 | J64: =IF($A$19,"n.a.",ROUND(J63*(1+$J108*C113+$I108*D113+$H108*E113+$G108*F113+$F108*G113+$E108*H113+$D108*I113+$C108*J113),1)) -> 26826.7 | K64: =IF($A$19,"n.a.",ROUND(K63*(1+$K108*C113+$J108*D113+$I108*E113+$H108*F113+$G108*G113+$F108*H113+$E108*I113+$D108*J113+$C108*K113),1)) -> 27299 | L64: =IF($A$19,"n.a.",ROUND(L63*(1+$L108*C113+$K108*D113+$J108*E113+$I108*F113+$H108*G113+$G108*H113+$F108*I113+$E108*J113+$D108*K113+$C108*L113),1)) -> 27771.2 | M64: =IF($A$19,"n.a.",ROUND(M63*(1+$M108*C113+$L108*D113+$K108*E113+$J108*F113+$I108*G113+$H108*H113+$G108*I113+$F108*J113+$E108*K113+$D108*L113+$C108*M113),1)) -> 28240.8
A65: Nominal GDP (billions of dollars)
A66: January 2025 baseline | B66: 29166.2 | C66: 30441.1 | D66: 31640.6 | E66: 32841 | F66: 34078.4 | G66: 35378.4 | H66: 36738.8 | I66: 38151.3 | J66: 39626.7 | K66: 41154.2 | L66: 42727.6 | M66: 44345.4
A67: User-specified scenario | B67: =IF($A$19,"n.a.",B66) -> 29166.2 | C67: =IF($A$19,"n.a.",ROUND(C64/C63*C66,1)) -> 30425.4 | D67: =IF($A$19,"n.a.",ROUND(D64/D63*D66,1)) -> 31607.3 | E67: =IF($A$19,"n.a.",ROUND(E64/E63*E66,1)) -> 32788 | F67: =IF($A$19,"n.a.",ROUND(F64/F63*F66,1)) -> 34003.7 | G67: =IF($A$19,"n.a.",ROUND(G64/G63*G66,1)) -> 35279.9 | H67: =IF($A$19,"n.a.",ROUND(H64/H63*H66,1)) -> 36614.1 | I67: =IF($A$19,"n.a.",ROUND(I64/I63*I66,1)) -> 37998.2 | J67: =IF($A$19,"n.a.",ROUND(J64/J63*J66,1)) -> 39442.5 | ... M67: =IF($A$19,"n.a.",ROUND(M64/M63*M66,1)) -> 44050.9
A68: Nominal GDP (billions of dollars, by fiscal year)
A69: January 2025 baseline | B69: 28823 | C69: 30136.1 | D69: 31341.3 | E69: 32538.1 | F69: 33764.5 | G69: 35047.1 | H69: 36393.7 | I69: 37792.1 | J69: 39252.4 | K69: 40767.9 | L69: 42330.4 | M69: 43936.5
A70: User-specified scenario | B70: =IF($A$19,"n.a.",B69) -> 28823 | C70: =IF($A$19,"n.a.",ROUND(C69+(C67-C66)*0.75+(B67-B66)*0.25,1)) -> 30124.3 | D70: =IF($A$19,"n.a.",ROUND(D69+(D67-D66)*0.75+(C67-C66)*0.25,1)) -> 31312.4 | E70: =IF($A$19,"n.a.",ROUND(E69+(E67-E66)*0.75+(D67-D66)*0.25,1)) -> 32490 | F70: =IF($A$19,"n.a.",ROUND(F69+(F67-F66)*0.75+(E67-E66)*0.25,1)) -> 33695.2 | G70: =IF($A$19,"n.a.",ROUND(G69+(G67-G66)*0.75+(F67-F66)*0.25,1)) -> 34954.6 | H70: =IF($A$19,"n.a.",ROUND(H69+(H67-H66)*0.75+(G67-G66)*0.25,1)) -> 36275.6 | I70: =IF($A$19,"n.a.",ROUND(I69+(I67-I66)*0.75+(H67-H66)*0.25,1)) -> 37646.1 | J70: =IF($A$19,"n.a.",ROUND(J69+(J67-J66)*0.75+(I67-I66)*0.25,1)) -> 39076 | ... M70: =IF($A$19,"n.a.",ROUND(M69+(M67-M66)*0.75+(L67-L66)*0.25,1)) -> 43651.9
A71: Labor force (millions of people)
A72: January 2025 baseline | B72: 168.243 | C72: 170.662 | D72: 173.375 | E72: 174.006 | F72: 174.614 | G72: 175.295 | H72: 176.03 | I72: 176.801 | J72: 177.558 | K72: 178.176 | L72: 178.795 | M72: 179.386
A73: User-specified scenario | B73: =IF($A$19,"n.a.",B72) -> 168.243 | C73: =IF($A$19,"n.a.",ROUND(C72*(1+C113),3)) -> 170.505 | D73: =IF($A$19,"n.a.",ROUND(D72*(1+D113),3)) -> 173.055 | E73: =IF($A$19,"n.a.",ROUND(E72*(1+E113),3)) -> 173.521 | F73: =IF($A$19,"n.a.",ROUND(F72*(1+F113),3)) -> 173.963 | G73: =IF($A$19,"n.a.",ROUND(G72*(1+G113),3)) -> 174.477 | H73: =IF($A$19,"n.a.",ROUND(H72*(1+H113),3)) -> 175.043 | I73: =IF($A$19,"n.a.",ROUND(I72*(1+I113),3)) -> 175.643 | J73: =IF($A$19,"n.a.",ROUND(J72*(1+J113),3)) -> 176.228 | ... M73: =IF($A$19,"n.a.",ROUND(M72*(1+M113),3)) -> 177.536
A74: Interest rate on 10-year Treasury notes (percent)
A75: January 2025 baseline | B75: 4.188 | C75: 4.093 | D75: 3.935 | E75: 3.914 | F75: 3.894 | G75: 3.871 | H75: 3.85 | I75: 3.836 | J75: 3.826 | K75: 3.815 | L75: 3.797 | M75: 3.772
A76: User-specified scenario | B76: =IF($A$19,"n.a.",B75) -> 4.188 | C76: =IF($A$19,"n.a.",ROUND(C75+$C109*C13,3)) -> 4.087 | D76: =IF($A$19,"n.a.",ROUND(D75+$D109*C13+$C109*D13,3)) -> 3.924 | E76: =IF($A$19,"n.a.",ROUND(E75+$E109*C13+$D109*D13+$C109*E13,3)) -> 3.897 | F76: =IF($A$19,"n.a.",ROUND(F75+$F109*C13+$E109*D13+$D109*E13+$C109*F13,3)) -> 3.872 | G76: =IF($A$19,"n.a.",ROUND(G75+$G109*C13+$F109*D13+$E109*E13+$D109*F13+$C109*G13,3)) -> 3.844 | H76: =IF($A$19,"n.a.",ROUND(H75+$H109*C13+$G109*D13+$F109*E13+$E109*F13+$D109*G13+$C109*H13,3)) -> 3.818 | I76: =IF($A$19,"n.a.",ROUND(I75+$I109*C13+$H109*D13+$G109*E13+$F109*F13+$E109*G13+$D109*H13+$C109*I13,3)) -> 3.8 | J76: =IF($A$19,"n.a.",ROUND(J75+$J109*C13+$I109*D13+$H109*E13+$G109*F13+$F109*G13+$E109*H13+$D109*I13+$C109*J13,3)) -> 3.786 | K76: =IF($A$19,"n.a.",ROUND(K75+$K109*C13+$J109*D13+$I109*E13+$H109*F13+$G109*G13+$F109*H13+$E109*I13+$D109*J13+$C109*K13,3)) -> 3.77 | L76: =IF($A$19,"n.a.",ROUND(L75+$L109*C13+$K109*D13+$J109*E13+$I109*F13+$H109*G13+$G109*H13+$F109*I13+$E109*J13+$D109*K13+$C109*L13,3)) -> 3.749 | M76: =IF($A$19,"n.a.",ROUND(M75+$M109*C13+$L109*D13+$K109*E13+$J109*F13+$I109*G13+$H109*H13+$G109*I13+$F109*J13+$E109*K13+$D109*L13+$C109*M13,3)) -> 3.72
A77: Inflation (percent)c
A78: January 2025 baseline | B78: 2.413 | C78: 2.198 | D78: 2.075 | E78: 1.995 | F78: 1.988 | G78: 1.992 | H78: 1.987 | I78: 1.986 | J78: 1.987 | K78: 1.991 | L78: 1.989 | M78: 1.99
A79: User-specified scenario | B79: =IF($A$19,"n.a.",B78) -> 2.413 | C79: =IF($A$19,"n.a.",C78) -> 2.198 | D79: =IF($A$19,"n.a.",D78) -> 2.075 | E79: =IF($A$19,"n.a.",E78) -> 1.995 | F79: =IF($A$19,"n.a.",F78) -> 1.988 | G79: =IF($A$19,"n.a.",G78) -> 1.992 | H79: =IF($A$19,"n.a.",H78) -> 1.987 | I79: =IF($A$19,"n.a.",I78) -> 1.986 | ... M79: =IF($A$19,"n.a.",M78) -> 1.99
A80: GDP price index (2017 = 100)
A81: January 2025 baseline | B81: 125.223 | C81: 127.976 | D81: 130.631 | E81: 133.238 | F81: 135.887 | G81: 138.595 | H81: 141.349 | I81: 144.157 | J81: 147.023 | K81: 149.95 | L81: 152.934 | M81: 155.979
A82: User-specified scenario | B82: =IF($A$19,"n.a.",B81) -> 125.223 | C82: =IF($A$19,"n.a.",C81) -> 127.976 | D82: =IF($A$19,"n.a.",D81) -> 130.631 | E82: =IF($A$19,"n.a.",E81) -> 133.238 | F82: =IF($A$19,"n.a.",F81) -> 135.887 | G82: =IF($A$19,"n.a.",G81) -> 138.595 | H82: =IF($A$19,"n.a.",H81) -> 141.349 | I82: =IF($A$19,"n.a.",I81) -> 144.157 | ... M82: =IF($A$19,"n.a.",M81) -> 155.979
A83: Employment cost index (December 2005 = 100)d
A84: January 2025 baseline | B84: 168.291 | C84: 174.156 | D84: 180 | E84: 185.768 | F84: 191.526 | G84: 197.325 | H84: 203.213 | I84: 209.221 | J84: 215.381 | K84: 221.716 | L84: 228.225 | M84: 234.91
A85: User-specified scenario | B85: =IF($A$19,"n.a.",B84) -> 168.291 | C85: =IF($A$19,"n.a.",ROUND((C67/C73)/(C66/C72)*C84,3)) -> 174.226 | D85: =IF($A$19,"n.a.",ROUND((D67/D73)/(D66/D72)*D84,3)) -> 180.143 | E85: =IF($A$19,"n.a.",ROUND((E67/E73)/(E66/E72)*E84,3)) -> 185.987 | F85: =IF($A$19,"n.a.",ROUND((F67/F73)/(F66/F72)*F84,3)) -> 191.821 | G85: =IF($A$19,"n.a.",ROUND((G67/G73)/(G66/G72)*G84,3)) -> 197.698 | H85: =IF($A$19,"n.a.",ROUND((H67/H73)/(H66/H72)*H84,3)) -> 203.665 | I85: =IF($A$19,"n.a.",ROUND((I67/I73)/(I66/I72)*I84,3)) -> 209.755 | J85: =IF($A$19,"n.a.",ROUND((J67/J73)/(J66/J72)*J84,3)) -> 215.998 | ... M85: =IF($A$19,"n.a.",ROUND((M67/M73)/(M66/M72)*M84,3)) -> 235.782
A88: Data source: Congressional Budget Office.
A90: Real values are nominal values that have been adjusted to remove the effects of changes in prices.
A92: See the “Contents” worksheet for a brief discussion of the formulas used in these tables.
A94: Unless otherwise noted, economic indicators are calendar year averages.
A96: GDP = gross domestic product; n.a. = not applicable.
A98: a. The change in labor force growth is slightly different from the user-specified change because changes in the supply of labor would affect wage rates, which would in turn affect the growth of the labor force during the first five years of the agency’s forecast.
A100: b. Discretionary outlays do not change in the user-specified scenario.
A102: c. Measured using the GDP price index.
A104: d. The employment cost index for wages and salaries of workers in private industry.
A107: Parameters
A108: Real GDP | C108: 0.561846 | D108: 0.018374 | E108: 0.01723 | F108: 0.016561 | G108: 0.016086 | H108: 0.015717 | I108: 0.015416 | J108: 0.015162 | K108: 0.014941 | L108: 0.014747 | M108: 0.014573
A109: Interest Rates | C109: 0.058487 | D109: 0.056232 | E109: 0.053978 | F109: 0.051723 | G109: 0.049469 | H109: 0.047214 | I109: 0.04496 | J109: 0.042705 | K109: 0.040451 | L109: 0.038196 | M109: 0.035942
A110: Labor Force | C110: 0.936092 | D110: 0.936043 | E110: 0.93958 | F110: 0.941649 | G110: 0.943117 | H110: 0.944255 | I110: 0.945185 | J110: 0.945972 | K110: 0.946653 | L110: 0.947254 | M110: 0.947792
A112: Unadjusted Labor Force | B112: =B73 -> 168.243 | C112: =B112*(C72/B72+C13/100) -> 170.49376 | D112: =C112*(D72/C72+D13/100) -> 173.03359 | E112: =D112*(E72/D72+E13/100) -> 173.49031 | F112: =E112*(F72/E72+F13/100) -> 173.92302 | G112: =F112*(G72/F72+G13/100) -> 174.4274 | H112: =G112*(H72/G72+H13/100) -> 174.98434 | I112: =H112*(I72/H72+I13/100) -> 175.57577 | J112: =I112*(J72/I72+J13/100) -> 176.15195 | ... M112: =L112*(M72/L72+M13/100) -> 177.43393
A113: Adjusted Labor Force Deviation | C113: =C110*(C112/C72-1) -> -0.00092282363 | D113: =D110*(D112/D72-1) -> -0.0018432626 | E113: =E110*(E112/E72-1) -> -0.002784557 | F113: =F110*(F112/F72-1) -> -0.003726278 | G113: =G110*(G112/G72-1) -> -0.0046678226 | H113: =H110*(H112/H72-1) -> -0.0056091134 | I113: =I110*(I112/I72-1) -> -0.0065501109 | J113: =J110*(J112/J72-1) -> -0.0074909761 | ... M113: =M110*(M112/M72-1) -> -0.010313833
A115: Interest Rate Change | C115: =C76-C75 -> -0.006 | D115: =D76-D75 -> -0.011 | E115: =E76-E75 -> -0.017 | F115: =F76-F75 -> -0.022 | G115: =G76-G75 -> -0.027 | H115: =H76-H75 -> -0.032 | I115: =I76-I75 -> -0.036 | J115: =J76-J75 -> -0.04 | ... M115: =M76-M75 -> -0.052
A117: Interest Change Matrix | C117: 52.194 | D117: 72.44 | E117: 41.604 | F117: 33.166 | G117: 27.507 | H117: 24.802 | I117: 18.083 | J117: 16.269 | K117: 12.265 | L117: 12.07 | M117: 10.215
C118: 0 | D118: 54.98 | E118: 76.133 | F118: 43.307 | G118: 34.496 | H118: 28.579 | I118: 25.954 | J118: 19.027 | K118: 16.892 | L118: 12.59 | M118: 12.39
C119: 0 | D119: 0 | E119: 56.723 | F119: 80.096 | G119: 45.121 | H119: 35.912 | I119: 29.72 | J119: 27.184 | K119: 20.037 | L119: 17.55 | M119: 12.931
C120: 0 | D120: 0 | E120: 0 | F120: 60.441 | G120: 85.403 | H120: 48.331 | I120: 38.578 | J120: 31.995 | K120: 28.98 | L120: 21.3 | M120: 18.656
C121: 0 | D121: 0 | E121: 0 | F121: 0 | G121: 63.893 | H121: 89.099 | I121: 50.653 | J121: 40.547 | K121: 33.7 | L121: 30.224 | M121: 22.152
C122: 0 | D122: 0 | E122: 0 | F122: 0 | G122: 0 | H122: 68.037 | I122: 94.484 | J122: 53.69 | K122: 43.116 | L122: 35.888 | M122: 32.186
C123: 0 | D123: 0 | E123: 0 | F123: 0 | G123: 0 | H123: 0 | I123: 70.948 | J123: 99.77 | K123: 56.668 | L123: 45.654 | M123: 38.056
C124: 0 | D124: 0 | E124: 0 | F124: 0 | G124: 0 | H124: 0 | I124: 0 | J124: 74.688 | K124: 103.9 | L124: 58.811 | M124: 47.381
C125: 0 | D125: 0 | E125: 0 | F125: 0 | G125: 0 | H125: 0 | I125: 0 | J125: 0 | K125: 78.212 | L125: 110.358 | M125: 62.251
C126: 0 | D126: 0 | E126: 0 | F126: 0 | G126: 0 | H126: 0 | I126: 0 | J126: 0 | K126: 0 | L126: 81.424 | M126: 113.933
C127: 0 | D127: 0 | E127: 0 | F127: 0 | G127: 0 | H127: 0 | I127: 0 | J127: 0 | K127: 0 | L127: 0 | M127: 85.108
A129: Net Interest Residual | C129: 0.013 | D129: -0.062 | E129: -0.123 | F129: -0.14 | G129: -0.215 | H129: -0.289 | I129: -0.378 | J129: -0.577 | K129: -0.677 | L129: -0.791 | M129: -0.982
A131: Deficit for Debt Service | C131: =C27+C28+C30-C24 -> 1.63 | D131: =D27+D28+D30-D24 -> 3.922 | E131: =E27+E28+E30-E24 -> 6.237 | F131: =F27+F28+F30-F24 -> 8.599 | G131: =G27+G28+G30-G24 -> 11.037 | H131: =H27+H28+H30-H24 -> 13.629 | I131: =I27+I28+I30-I24 -> 16.514 | J131: =J27+J28+J30-J24 -> 19.828 | ... M131: =M27+M28+M30-M24 -> 31.669
A133: Debt Service Matrix | C133: 0.0105 | D133: 0.0379 | E133: 0.0373 | F133: 0.0383 | G133: 0.0393 | H133: 0.0403 | I133: 0.0411 | J133: 0.0422 | K133: 0.0432 | L133: 0.0445 | M133: 0.0456
C134: 0 | D134: 0.0185 | E134: 0.0365 | F134: 0.0378 | G134: 0.0387 | H134: 0.0398 | I134: 0.041 | J134: 0.042 | K134: 0.0432 | L134: 0.0445 | M134: 0.0459
C135: 0 | D135: 0 | E135: 0.0184 | F135: 0.036 | G135: 0.037 | H135: 0.0382 | I135: 0.0392 | J135: 0.0402 | K135: 0.0416 | L135: 0.0428 | M135: 0.044
...

Sheet 3. Interest Rates
A1: This workbook supplements CBO’s report How Changes in Economic Conditions Might Affect the Federal Budget: 2025 to 2035.
A2: www.cbo.gov/publication/61198
A5: To create an alternative scenario for interest rates, enter values between -1.0 percentage point and 1.0 percentage point in each of the green cells. (Only the green cells can be edited; all other cells are locked. Values outside of the specified range will produce errors.) The change in budgetary outcomes relative to those in CBO’s baseline will be calculated and appear automatically. Values for key economic indicators are shown below those budgetary effects.
A7: 3. Interactive Table: How Changes in Interest Rates Might Affect the Federal Budget
B9: 2024 | C9: 2025 | D9: 2026 | E9: 2027 | F9: 2028 | G9: 2029 | H9: 2030 | I9: 2031 | J9: 2032 | K9: 2033 | L9: 2034 | M9: 2035
C11: User-specified scenario for interest rates
O12: These initial values are the same as those used to generate the illustrative scenario shown in Worksheet 7, “Interest Rates_CBO.”
A13: Increase or decrease (-) in interest rates relative to CBO’s January 2025 baseline (percentage points) | B13: n.a. | C13: 0.1 | D13: 0.1 | E13: 0.1 | F13: 0.1 | G13: 0.1 | H13: 0.1 | I13: 0.1 | J13: 0.1 | K13: 0.1 | L13: 0.1 | M13: 0.1
A14: =IF($A$19,"Please keep values in the range [-1.0, 1.0] percentage point per year.","")
A15: Interest rate on 10-year Treasury notes (percent)a
A16: January 2025 baseline | B16: 4.188 | C16: 4.093 | D16: 3.935 | E16: 3.914 | F16: 3.894 | G16: 3.871 | H16: 3.85 | I16: 3.836 | J16: 3.826 | K16: 3.815 | L16: 3.797 | M16: 3.772
A17: User-specified scenario | B17: =IF($A$19,"n.a.",B16) -> 4.188 | C17: =IF($A$19,"n.a.",C16+C13) -> 4.193 | D17: =IF($A$19,"n.a.",D16+D13) -> 4.035 | E17: =IF($A$19,"n.a.",E16+E13) -> 4.014 | F17: =IF($A$19,"n.a.",F16+F13) -> 3.994 | G17: =IF($A$19,"n.a.",G16+G13) -> 3.971 | H17: =IF($A$19,"n.a.",H16+H13) -> 3.95 | I17: =IF($A$19,"n.a.",I16+I13) -> 3.936 | J17: =IF($A$19,"n.a.",J16+J13) -> 3.926 | ... M17: =IF($A$19,"n.a.",M16+M13) -> 3.872
A19: =IF(OR(MAX(C13:M13)>1,MIN(C13:M13)<-1),1,0) -> 0
C21: Budgetary effects (billions of dollars) | N21: Total
N22: 2026- | O22: 2026-
B23: 2024 | C23: 2025 | D23: 2026 | E23: 2027 | F23: 2028 | G23: 2029 | H23: 2030 | I23: 2031 | J23: 2032 | K23: 2033 | L23: 2034 | M23: 2035 | N23: 2030 | O23: 2035
A24: Changes in revenues | B24: n.a. | C24: {=IF($A$19,"n.a.",TRUNC(SUMPRODUCT($C13:$M13,TRANSPOSE(C108:C118))-C120*(C13*0.75),3))} -> -2.563 | D24: {=IF($A$19,"n.a.",TRUNC(SUMPRODUCT($C13:$M13,TRANSPOSE(D108:D118))-D120*(D13*0.75+C13*0.25),3))} -> -2.565 | E24: {=IF($A$19,"n.a.",TRUNC(SUMPRODUCT($C13:$M13,TRANSPOSE(E108:E118))-E120*(E13*0.75+D13*0.25),3))} -> -1.678 | F24: {=IF($A$19,"n.a.",TRUNC(SUMPRODUCT($C13:$M13,TRANSPOSE(F108:F118))-F120*(F13*0.75+E13*0.25),3))} -> -0.88 | G24: {=IF($A$19,"n.a.",TRUNC(SUMPRODUCT($C13:$M13,TRANSPOSE(G108:G118))-G120*(G13*0.75+F13*0.25),3))} -> -0.173 | H24: {=IF($A$19,"n.a.",TRUNC(SUMPRODUCT($C13:$M13,TRANSPOSE(H108:H118))-H120*(H13*0.75+G13*0.25),3))} -> 0.5 | I24: {=IF($A$19,"n.a.",TRUNC(SUMPRODUCT($C13:$M13,TRANSPOSE(I108:I118))-I120*(I13*0.75+H13*0.25),3))} -> 1.011 | J24: {=IF($A$19,"n.a.",TRUNC(SUMPRODUCT($C13:$M13,TRANSPOSE(J108:J118))-J120*(J13*0.75+I13*0.25),3))} -> 1.513 | K24: {=IF($A$19,"n.a.",TRUNC(SUMPRODUCT($C13:$M13,TRANSPOSE(K108:K118))-K120*(K13*0.75+J13*0.25),3))} -> 1.933 | ... M24: {=IF($A$19,"n.a.",TRUNC(SUMPRODUCT($C13:$M13,TRANSPOSE(M108:M118))-M120*(M13*0.75+L13*0.25),3))} -> 2.635 | N24: =IF($A$19,"n.a.",SUM(D24:H24)) -> -4.796 | O24: =IF($A$19,"n.a.",SUM(D24:M24)) -> 4.585
A26: Changes in outlays
A27: Mandatory outlays | B27: n.a. | C27: =IF($A$19,"n.a.",ROUND('7. Interest Rates_CBO'!C14*C122/('7. Interest Rates_CBO'!C63-'7. Interest Rates_CBO'!C62),3)) -> 0 | D27: =IF($A$19,"n.a.",ROUND('7. Interest Rates_CBO'!D14*D122/('7. Interest Rates_CBO'!D63-'7. Interest Rates_CBO'!D62),3)) -> 0 | E27: =IF($A$19,"n.a.",ROUND('7. Interest Rates_CBO'!E14*E122/('7. Interest Rates_CBO'!E63-'7. Interest Rates_CBO'!E62),3)) -> 0 | F27: =IF($A$19,"n.a.",ROUND('7. Interest Rates_CBO'!F14*F122/('7. Interest Rates_CBO'!F63-'7. Interest Rates_CBO'!F62),3)) -> 0 | G27: =IF($A$19,"n.a.",ROUND('7. Interest Rates_CBO'!G14*G122/('7. Interest Rates_CBO'!G63-'7. Interest Rates_CBO'!G62),3)) -> 0 | H27: =IF($A$19,"n.a.",ROUND('7. Interest Rates_CBO'!H14*H122/('7. Interest Rates_CBO'!H63-'7. Interest Rates_CBO'!H62),3)) -> 0 | I27: =IF($A$19,"n.a.",ROUND('7. Interest Rates_CBO'!I14*I122/('7. Interest Rates_CBO'!I63-'7. Interest Rates_CBO'!I62),3)) -> 0 | J27: =IF($A$19,"n.a.",ROUND('7. Interest Rates_CBO'!J14*J122/('7. Interest Rates_CBO'!J63-'7. Interest Rates_CBO'!J62),3)) -> 0 | ... M27: =IF($A$19,"n.a.",ROUND('7. Interest Rates_CBO'!M14*M122/('7. Interest Rates_CBO'!M63-'7. Interest Rates_CBO'!M62),3)) -> 0 | N27: =IF($A$19,"n.a.",SUM(D27:H27)) -> 0 | O27: =IF($A$19,"n.a.",SUM(D27:M27)) -> 0
A28: Discretionary outlaysb | B28: n.a. | C28: =IF($A$19,"n.a.",0) -> 0 | D28: =IF($A$19,"n.a.",0) -> 0 | E28: =IF($A$19,"n.a.",0) -> 0 | F28: =IF($A$19,"n.a.",0) -> 0 | G28: =IF($A$19,"n.a.",0) -> 0 | H28: =IF($A$19,"n.a.",0) -> 0 | I28: =IF($A$19,"n.a.",0) -> 0 | J28: =IF($A$19,"n.a.",0) -> 0 | ... M28: =IF($A$19,"n.a.",0) -> 0 | N28: =IF($A$19,"n.a.",SUM(D28:H28)) -> 0 | O28: =IF($A$19,"n.a.",SUM(D28:M28)) -> 0
A29: Net interest outlays
A30: Effects from changes in interest rates | B30: n.a. | C30: {=IF($A$19,"n.a.",ROUND(SUMPRODUCT(TRANSPOSE($C122:$M122),C124:C134),3)+ROUND(C136*C122/('7. Interest Rates_CBO'!C63-'7. Interest Rates_CBO'!C62),3))} -> 5.219 | D30: {=IF($A$19,"n.a.",ROUND(SUMPRODUCT(TRANSPOSE($C122:$M122),D124:D134),3)+ROUND(D136*D122/('7. Interest Rates_CBO'!D63-'7. Interest Rates_CBO'!D62),3))} -> 12.742 | E30: {=IF($A$19,"n.a.",ROUND(SUMPRODUCT(TRANSPOSE($C122:$M122),E124:E134),3)+ROUND(E136*E122/('7. Interest Rates_CBO'!E63-'7. Interest Rates_CBO'!E62),3))} -> 17.446 | F30: {=IF($A$19,"n.a.",ROUND(SUMPRODUCT(TRANSPOSE($C122:$M122),F124:F134),3)+ROUND(F136*F122/('7. Interest Rates_CBO'!F63-'7. Interest Rates_CBO'!F62),3))} -> 21.701 | G30: {=IF($A$19,"n.a.",ROUND(SUMPRODUCT(TRANSPOSE($C122:$M122),G124:G134),3)+ROUND(G136*G122/('7. Interest Rates_CBO'!G63-'7. Interest Rates_CBO'!G62),3))} -> 25.642 | H30: {=IF($A$19,"n.a.",ROUND(SUMPRODUCT(TRANSPOSE($C122:$M122),H124:H134),3)+ROUND(H136*H122/('7. Interest Rates_CBO'!H63-'7. Interest Rates_CBO'!H62),3))} -> 29.476 | I30: {=IF($A$19,"n.a.",ROUND(SUMPRODUCT(TRANSPOSE($C122:$M122),I124:I134),3)+ROUND(I136*I122/('7. Interest Rates_CBO'!I63-'7. Interest Rates_CBO'!I62),3))} -> 32.842 | J30: {=IF($A$19,"n.a.",ROUND(SUMPRODUCT(TRANSPOSE($C122:$M122),J124:J134),3)+ROUND(J136*J122/('7. Interest Rates_CBO'!J63-'7. Interest Rates_CBO'!J62),3))} -> 36.317 | ... M30: {=IF($A$19,"n.a.",ROUND(SUMPRODUCT(TRANSPOSE($C122:$M122),M124:M134),3)+ROUND(M136*M122/('7. Interest Rates_CBO'!M63-'7. Interest Rates_CBO'!M62),3))} -> 45.526 | N30: =IF($A$19,"n.a.",SUM(D30:H30)) -> 107.007 | O30: =IF($A$19,"n.a.",SUM(D30:M30)) -> 303.656
A31: Debt service | B31: n.a. | C31: {=IF($A$19,"n.a.",ROUND(SUMPRODUCT($C138:$M138,TRANSPOSE(C140:C150)),3) + ROUND((-C152)*C138/('7. Interest Rates_CBO'!C24+'7. Interest Rates_CBO'!C18),3))} -> 0.083 | D31: {=IF($A$19,"n.a.",ROUND(SUMPRODUCT($C138:$M138,TRANSPOSE(D140:D150)),3) + ROUND((-D152)*D138/('7. Interest Rates_CBO'!D24+'7. Interest Rates_CBO'!D18),3))} -> 0.593 | E31: {=IF($A$19,"n.a.",ROUND(SUMPRODUCT($C138:$M138,TRANSPOSE(E140:E150)),3) + ROUND((-E152)*E138/('7. Interest Rates_CBO'!E24+'7. Interest Rates_CBO'!E18),3))} -> 1.239 | F31: {=IF($A$19,"n.a.",ROUND(SUMPRODUCT($C138:$M138,TRANSPOSE(F140:F150)),3) + ROUND((-F152)*F138/('7. Interest Rates_CBO'!F24+'7. Interest Rates_CBO'!F18),3))} -> 2.035 | G31: {=IF($A$19,"n.a.",ROUND(SUMPRODUCT($C138:$M138,TRANSPOSE(G140:G150)),3) + ROUND((-G152)*G138/('7. Interest Rates_CBO'!G24+'7. Interest Rates_CBO'!G18),3))} -> 2.966 | H31: {=IF($A$19,"n.a.",ROUND(SUMPRODUCT($C138:$M138,TRANSPOSE(H140:H150)),3) + ROUND((-H152)*H138/('7. Interest Rates_CBO'!H24+'7. Interest Rates_CBO'!H18),3))} -> 4.043 | I31: {=IF($A$19,"n.a.",ROUND(SUMPRODUCT($C138:$M138,TRANSPOSE(I140:I150)),3) + ROUND((-I152)*I138/('7. Interest Rates_CBO'!I24+'7. Interest Rates_CBO'!I18),3))} -> 5.24 | J31: {=IF($A$19,"n.a.",ROUND(SUMPRODUCT($C138:$M138,TRANSPOSE(J140:J150)),3) + ROUND((-J152)*J138/('7. Interest Rates_CBO'!J24+'7. Interest Rates_CBO'!J18),3))} -> 6.579 | ... M31: {=IF($A$19,"n.a.",ROUND(SUMPRODUCT($C138:$M138,TRANSPOSE(M140:M150)),3) + ROUND((-M152)*M138/('7. Interest Rates_CBO'!M24+'7. Interest Rates_CBO'!M18),3))} -> 11.428 | N31: =IF($A$19,"n.a.",SUM(D31:H31)) -> 10.876 | O31: =IF($A$19,"n.a.",SUM(D31:M31)) -> 51.833
B32: ____ | C32: ____ | D32: ____ | E32: ____ | F32: ____ | G32: ____ | H32: ____ | I32: ____ | J32: ____ | K32: ____ | L32: ____ | M32: ____ | N32: ____ | O32: ____
A33: Subtotal, net interest outlays | B33: n.a. | C33: =IF($A$19,"n.a.",C30+C31) -> 5.302 | D33: =IF($A$19,"n.a.",D30+D31) -> 13.335 | E33: =IF($A$19,"n.a.",E30+E31) -> 18.685 | F33: =IF($A$19,"n.a.",F30+F31) -> 23.736 | G33: =IF($A$19,"n.a.",G30+G31) -> 28.608 | H33: =IF($A$19,"n.a.",H30+H31) -> 33.519 | I33: =IF($A$19,"n.a.",I30+I31) -> 38.082 | J33: =IF($A$19,"n.a.",J30+J31) -> 42.896 | ... M33: =IF($A$19,"n.a.",M30+M31) -> 56.954 | N33: =IF($A$19,"n.a.",SUM(D33:H33)) -> 117.883 | O33: =IF($A$19,"n.a.",SUM(D33:M33)) -> 355.489
A35: Total change in outlays | B35: n.a. | C35: =IF($A$19,"n.a.",C27+C28+C33) -> 5.302 | D35: =IF($A$19,"n.a.",D27+D28+D33) -> 13.335 | E35: =IF($A$19,"n.a.",E27+E28+E33) -> 18.685 | F35: =IF($A$19,"n.a.",F27+F28+F33) -> 23.736 | G35: =IF($A$19,"n.a.",G27+G28+G33) -> 28.608 | H35: =IF($A$19,"n.a.",H27+H28+H33) -> 33.519 | I35: =IF($A$19,"n.a.",I27+I28+I33) -> 38.082 | J35: =IF($A$19,"n.a.",J27+J28+J33) -> 42.896 | ... M35: =IF($A$19,"n.a.",M27+M28+M33) -> 56.954 | N35: =IF($A$19,"n.a.",SUM(D35:H35)) -> 117.883 | O35: =IF($A$19,"n.a.",SUM(D35:M35)) -> 355.489
A37: Increase (-) or decrease in the deficit relative to CBO's baseline | B37: n.a. | C37: =IF($A$19,"n.a.",C24-C35) -> -7.865 | D37: =IF($A$19,"n.a.",D24-D35) -> -15.9 | E37: =IF($A$19,"n.a.",E24-E35) -> -20.363 | F37: =IF($A$19,"n.a.",F24-F35) -> -24.616 | G37: =IF($A$19,"n.a.",G24-G35) -> -28.781 | H37: =IF($A$19,"n.a.",H24-H35) -> -33.019 | I37: =IF($A$19,"n.a.",I24-I35) -> -37.071 | J37: =IF($A$19,"n.a.",J24-J35) -> -41.383 | ... M37: =IF($A$19,"n.a.",M24-M35) -> -54.319 | N37: =IF($A$19,"n.a.",SUM(D37:H37)) -> -122.679 | O37: =IF($A$19,"n.a.",SUM(D37:M37)) -> -350.904
A39: Deficit (-) or surplus
A40: January 2025 baseline | B40: -1832.381 | C40: -1865.251 | D40: -1713.258 | E40: -1686.942 | F40: -1910.776 | G40: -1938.268 | H40: -2139.721 | I40: -2232.786 | J40: -2370.582 | K40: -2637.299 | L40: -2597.25 | M40: -2531.378 | N40: -9388.965 | O40: -21758.26
A41: User-specified scenario | B41: =IF($A$19,"n.a.",B40) -> -1832.381 | C41: =IF($A$19,"n.a.",C40+C37) -> -1873.116 | D41: =IF($A$19,"n.a.",D40+D37) -> -1729.158 | E41: =IF($A$19,"n.a.",E40+E37) -> -1707.305 | F41: =IF($A$19,"n.a.",F40+F37) -> -1935.392 | G41: =IF($A$19,"n.a.",G40+G37) -> -1967.049 | H41: =IF($A$19,"n.a.",H40+H37) -> -2172.74 | I41: =IF($A$19,"n.a.",I40+I37) -> -2269.857 | J41: =IF($A$19,"n.a.",J40+J37) -> -2411.965 | ... M41: =IF($A$19,"n.a.",M40+M37) -> -2585.697 | N41: =IF($A$19,"n.a.",SUM(D41:H41)) -> -9511.644 | O41: =IF($A$19,"n.a.",SUM(D41:M41)) -> -22109.164
A43: Debt held by the public
A44: January 2025 baseline | B44: 28199.313 | C44: 30102.749 | D44: 31882.633 | E44: 33636.105 | F44: 35600.64 | G44: 37580.5 | H44: 39747.651 | I44: 41992.385 | J44: 44371.755 | K44: 46985.029 | L44: 49555.504 | M44: 52055.866 | N44: n.a. | O44: n.a.
A45: User-specified scenario | B45: =IF($A$19,"n.a.",B44) -> 28199.313 | C45: =IF($A$19,"n.a.",C44-SUM($C37:C37)) -> 30110.614 | D45: =IF($A$19,"n.a.",D44-SUM($C37:D37)) -> 31906.398 | E45: =IF($A$19,"n.a.",E44-SUM($C37:E37)) -> 33680.233 | F45: =IF($A$19,"n.a.",F44-SUM($C37:F37)) -> 35669.384 | G45: =IF($A$19,"n.a.",G44-SUM($C37:G37)) -> 37678.025 | H45: =IF($A$19,"n.a.",H44-SUM($C37:H37)) -> 39878.195 | I45: =IF($A$19,"n.a.",I44-SUM($C37:I37)) -> 42160 | J45: =IF($A$19,"n.a.",J44-SUM($C37:J37)) -> 44580.753 | ... M45: =IF($A$19,"n.a.",M44-SUM($C37:M37)) -> 52414.635 | N45: n.a. | O45: n.a.
A47: Deficit (-) or surplus (percentage of GDP)
A48: January 2025 baseline | B48: -6.3562158 | C48: -6.1894147 | D48: -5.4664504 | E48: -5.184518 | F48: -5.659123 | G48: -5.5304586 | H48: -5.8793652 | I48: -5.9080768 | J48: -6.0393242 | K48: -6.4690633 | L48: -6.1356563 | M48: -5.7614482 | N48: -5.5528141 | O48: -5.830748
A49: User-specified scenario | B49: =IF($A$19,"n.a.",B48) -> -6.3562158 | C49: =IF($A$19,"n.a.",ROUND(C41/C70*100,3)) -> -6.216 | D49: =IF($A$19,"n.a.",ROUND(D41/D70*100,3)) -> -5.517 | E49: =IF($A$19,"n.a.",ROUND(E41/E70*100,3)) -> -5.247 | F49: =IF($A$19,"n.a.",ROUND(F41/F70*100,3)) -> -5.732 | G49: =IF($A$19,"n.a.",ROUND(G41/G70*100,3)) -> -5.613 | H49: =IF($A$19,"n.a.",ROUND(H41/H70*100,3)) -> -5.97 | I49: =IF($A$19,"n.a.",ROUND(I41/I70*100,3)) -> -6.006 | J49: =IF($A$19,"n.a.",ROUND(J41/J70*100,3)) -> -6.145 | ... M49: =IF($A$19,"n.a.",ROUND(M41/M70*100,3)) -> -5.885 | N49: =IF($A$19,"n.a.",ROUND(SUM(D41:H41)/SUM(D70:H70)*100,3)) -> -5.625 | O49: =IF($A$19,"n.a.",ROUND(SUM(D41:M41)/SUM(D70:M70)*100,3)) -> -5.925
A51: Debt held by the public (percentage of GDP)
A52: January 2025 baseline | B52: 97.818585 | C52: 99.889183 | D52: 101.72714 | E52: 103.37462 | F52: 105.438 | G52: 107.22841 | H52: 109.21562 | I52: 111.1142 | J52: 113.04204 | K52: 115.25016 | L52: 117.06826 | M52: 118.47981 | N52: n.a. | O52: n.a.
A53: User-specified scenario | B53: =IF($A$19,"n.a.",B52) -> 97.818585 | C53: =IF($A$19,"n.a.",ROUND(C45/C70*100,3)) -> 99.915 | D53: =IF($A$19,"n.a.",ROUND(D45/D70*100,3)) -> 101.803 | E53: =IF($A$19,"n.a.",ROUND(E45/E70*100,3)) -> 103.51 | F53: =IF($A$19,"n.a.",ROUND(F45/F70*100,3)) -> 105.642 | G53: =IF($A$19,"n.a.",ROUND(G45/G70*100,3)) -> 107.507 | H53: =IF($A$19,"n.a.",ROUND(H45/H70*100,3)) -> 109.574 | I53: =IF($A$19,"n.a.",ROUND(I45/I70*100,3)) -> 111.558 | J53: =IF($A$19,"n.a.",ROUND(J45/J70*100,3)) -> 113.575 | ... M53: =IF($A$19,"n.a.",ROUND(M45/M70*100,3)) -> 119.296 | N53: n.a. | O53: n.a.
B56: Economic indicators in CBO’s January 2025 baseline and under the user-specified scenario
B58: 2024 | C58: 2025 | D58: 2026 | E58: 2027 | F58: 2028 | G58: 2029 | H58: 2030 | I58: 2031 | J58: 2032 | K58: 2033 | L58: 2034 | M58: 2035
A59: Real GDP growth (percent)
A60: January 2025 baseline | B60: 2.734 | C60: 2.124 | D60: 1.827 | E60: 1.763 | F60: 1.744 | G60: 1.786 | H60: 1.821 | I60: 1.822 | J60: 1.842 | K60: 1.826 | L60: 1.797 | M60: 1.76
A61: User-specified scenario | B61: =IF($A$19,"n.a.",B60) -> 2.734 | C61: =IF($A$19,"n.a.",C60) -> 2.124 | D61: =IF($A$19,"n.a.",D60) -> 1.827 | E61: =IF($A$19,"n.a.",E60) -> 1.763 | F61: =IF($A$19,"n.a.",F60) -> 1.744 | G61: =IF($A$19,"n.a.",G60) -> 1.786 | H61: =IF($A$19,"n.a.",H60) -> 1.821 | I61: =IF($A$19,"n.a.",I60) -> 1.822 | ... M61: =IF($A$19,"n.a.",M60) -> 1.76
A62: Real GDP (billions of 2017 dollars)
A63: January 2025 baseline | B63: 23290.9 | C63: 23785.8 | D63: 24220.5 | E63: 24647.6 | F63: 25077.7 | G63: 25525.6 | H63: 25990.7 | I63: 26464.3 | J63: 26952 | K63: 27444.4 | L63: 27937.8 | M63: 28429.6
A64: User-specified scenario | B64: =IF($A$19,"n.a.",B63) -> 23290.9 | C64: =IF($A$19,"n.a.",C63) -> 23785.8 | D64: =IF($A$19,"n.a.",D63) -> 24220.5 | E64: =IF($A$19,"n.a.",E63) -> 24647.6 | F64: =IF($A$19,"n.a.",F63) -> 25077.7 | G64: =IF($A$19,"n.a.",G63) -> 25525.6 | H64: =IF($A$19,"n.a.",H63) -> 25990.7 | I64: =IF($A$19,"n.a.",I63) -> 26464.3 | ... M64: =IF($A$19,"n.a.",M63) -> 28429.6
A65: Nominal GDP (billions of dollars)
A66: January 2025 baseline | B66: 29166.2 | C66: 30441.1 | D66: 31640.6 | E66: 32841 | F66: 34078.4 | G66: 35378.4 | H66: 36738.8 | I66: 38151.3 | J66: 39626.7 | K66: 41154.2 | L66: 42727.6 | M66: 44345.4
A67: User-specified scenario | B67: =IF($A$19,"n.a.",B66) -> 29166.2 | C67: =IF($A$19,"n.a.",C66) -> 30441.1 | D67: =IF($A$19,"n.a.",D66) -> 31640.6 | E67: =IF($A$19,"n.a.",E66) -> 32841 | F67: =IF($A$19,"n.a.",F66) -> 34078.4 | G67: =IF($A$19,"n.a.",G66) -> 35378.4 | H67: =IF($A$19,"n.a.",H66) -> 36738.8 | I67: =IF($A$19,"n.a.",I66) -> 38151.3 | ... M67: =IF($A$19,"n.a.",M66) -> 44345.4
A68: Nominal GDP (billions of dollars, by fiscal year)
A69: January 2025 baseline | B69: 28823 | C69: 30136.1 | D69: 31341.3 | E69: 32538.1 | F69: 33764.5 | G69: 35047.1 | H69: 36393.7 | I69: 37792.1 | J69: 39252.4 | K69: 40767.9 | L69: 42330.4 | M69: 43936.5
A70: User-specified scenario | B70: =IF($A$19,"n.a.",B69) -> 28823 | C70: =IF($A$19,"n.a.",C69) -> 30136.1 | D70: =IF($A$19,"n.a.",D69) -> 31341.3 | E70: =IF($A$19,"n.a.",E69) -> 32538.1 | F70: =IF($A$19,"n.a.",F69) -> 33764.5 | G70: =IF($A$19,"n.a.",G69) -> 35047.1 | H70: =IF($A$19,"n.a.",H69) -> 36393.7 | I70: =IF($A$19,"n.a.",I69) -> 37792.1 | ... M70: =IF($A$19,"n.a.",M69) -> 43936.5
A71: Labor force (millions of people)
A72: January 2025 baseline | B72: 168.243 | C72: 170.662 | D72: 173.375 | E72: 174.006 | F72: 174.614 | G72: 175.295 | H72: 176.03 | I72: 176.801 | J72: 177.558 | K72: 178.176 | L72: 178.795 | M72: 179.386
A73: User-specified scenario | B73: =IF($A$19,"n.a.",B72) -> 168.243 | C73: =IF($A$19,"n.a.",C72) -> 170.662 | D73: =IF($A$19,"n.a.",D72) -> 173.375 | E73: =IF($A$19,"n.a.",E72) -> 174.006 | F73: =IF($A$19,"n.a.",F72) -> 174.614 | G73: =IF($A$19,"n.a.",G72) -> 175.295 | H73: =IF($A$19,"n.a.",H72) -> 176.03 | I73: =IF($A$19,"n.a.",I72) -> 176.801 | ... M73: =IF($A$19,"n.a.",M72) -> 179.386
A74: Interest rate on 10-year Treasury notes (percent)
A75: January 2025 baseline | B75: 4.188 | C75: 4.093 | D75: 3.935 | E75: 3.914 | F75: 3.894 | G75: 3.871 | H75: 3.85 | I75: 3.836 | J75: 3.826 | K75: 3.815 | L75: 3.797 | M75: 3.772
A76: User-specified scenario | B76: =IF($A$19,"n.a.",B75) -> 4.188 | C76: =IF($A$19,"n.a.",ROUND(C75+C13,3)) -> 4.193 | D76: =IF($A$19,"n.a.",ROUND(D75+D13,3)) -> 4.035 | E76: =IF($A$19,"n.a.",ROUND(E75+E13,3)) -> 4.014 | F76: =IF($A$19,"n.a.",ROUND(F75+F13,3)) -> 3.994 | G76: =IF($A$19,"n.a.",ROUND(G75+G13,3)) -> 3.971 | H76: =IF($A$19,"n.a.",ROUND(H75+H13,3)) -> 3.95 | I76: =IF($A$19,"n.a.",ROUND(I75+I13,3)) -> 3.936 | J76: =IF($A$19,"n.a.",ROUND(J75+J13,3)) -> 3.926 | ... M76: =IF($A$19,"n.a.",ROUND(M75+M13,3)) -> 3.872
A77: Inflation (percent)c
A78: January 2025 baseline | B78: 2.413 | C78: 2.198 | D78: 2.075 | E78: 1.995 | F78: 1.988 | G78: 1.992 | H78: 1.987 | I78: 1.986 | J78: 1.987 | K78: 1.991 | L78: 1.989 | M78: 1.99
A79: User-specified scenario | B79: =IF($A$19,"n.a.",B78) -> 2.413 | C79: =IF($A$19,"n.a.",C78) -> 2.198 | D79: =IF($A$19,"n.a.",D78) -> 2.075 | E79: =IF($A$19,"n.a.",E78) -> 1.995 | F79: =IF($A$19,"n.a.",F78) -> 1.988 | G79: =IF($A$19,"n.a.",G78) -> 1.992 | H79: =IF($A$19,"n.a.",H78) -> 1.987 | I79: =IF($A$19,"n.a.",I78) -> 1.986 | ... M79: =IF($A$19,"n.a.",M78) -> 1.99
A80: GDP price index (2017 = 100)
A81: January 2025 baseline | B81: 125.223 | C81: 127.976 | D81: 130.631 | E81: 133.238 | F81: 135.887 | G81: 138.595 | H81: 141.349 | I81: 144.157 | J81: 147.023 | K81: 149.95 | L81: 152.934 | M81: 155.979
A82: User-specified scenario | B82: =IF($A$19,"n.a.",B81) -> 125.223 | C82: =IF($A$19,"n.a.",C81) -> 127.976 | D82: =IF($A$19,"n.a.",D81) -> 130.631 | E82: =IF($A$19,"n.a.",E81) -> 133.238 | F82: =IF($A$19,"n.a.",F81) -> 135.887 | G82: =IF($A$19,"n.a.",G81) -> 138.595 | H82: =IF($A$19,"n.a.",H81) -> 141.349 | I82: =IF($A$19,"n.a.",I81) -> 144.157 | ... M82: =IF($A$19,"n.a.",M81) -> 155.979
A83: Employment cost index (December 2005 = 100)d
A84: January 2025 baseline | B84: 168.291 | C84: 174.156 | D84: 180 | E84: 185.768 | F84: 191.526 | G84: 197.325 | H84: 203.213 | I84: 209.221 | J84: 215.381 | K84: 221.716 | L84: 228.225 | M84: 234.91
A85: User-specified scenario | B85: =IF($A$19,"n.a.",B84) -> 168.291 | C85: =IF($A$19,"n.a.",C84) -> 174.156 | D85: =IF($A$19,"n.a.",D84) -> 180 | E85: =IF($A$19,"n.a.",E84) -> 185.768 | F85: =IF($A$19,"n.a.",F84) -> 191.526 | G85: =IF($A$19,"n.a.",G84) -> 197.325 | H85: =IF($A$19,"n.a.",H84) -> 203.213 | I85: =IF($A$19,"n.a.",I84) -> 209.221 | ... M85: =IF($A$19,"n.a.",M84) -> 234.91
A88: Data source: Congressional Budget Office.
A90: Real values are nominal values that have been adjusted to remove the effects of changes in prices.
A92: See the “Contents” worksheet for a brief discussion of the formulas used in these tables.
A94: Unless otherwise noted, economic indicators are calendar year averages.
A96: GDP = gross domestic product; n.a. = not applicable.
A98: a. Although all interest rates change in this scenario, the table shows only the effects on the interest rate on 10-year Treasury notes.
A100: b. Discretionary outlays do not change in the user-specified scenario.
A102: c. Measured using the GDP price index.
A104: d. The employment cost index for wages and salaries of workers in private industry.
A107: Parameters
A108: Receipts Matrix | C108: 3.366015 | D108: 7.1344265 | E108: 3.9586524 | F108: 3.1787762 | G108: 2.5683348 | H108: 2.3651629 | I108: 1.7884586 | J108: 1.6276454 | K108: 1.1951171 | L108: 1.1698143 | M108: 1.0215589
C109: 0 | D109: 6.740815 | E109: 11.398476 | F109: 6.4757899 | G109: 5.1867778 | H109: 4.2336329 | I109: 3.8534222 | J109: 2.9446207 | K109: 2.6483769 | L109: 1.9667758 | M109: 1.9335182
C110: 0 | D110: 0 | E110: 8.9312261 | F110: 13.827504 | G110: 7.9073605 | H110: 6.3282635 | I110: 5.1828294 | J110: 4.6984024 | K110: 3.6037324 | L110: 3.2277211 | M110: 2.4067186
C111: 0 | D111: 0 | E111: 0 | F111: 10.31152 | G111: 15.482384 | H111: 8.8817367 | I111: 7.1062166 | J111: 5.8262285 | K111: 5.2749082 | L111: 4.0507085 | M111: 3.6232712
C112: 0 | D112: 0 | E112: 0 | F112: 0 | G112: 11.372028 | H112: 16.979846 | I112: 9.7360654 | J112: 7.7892466 | K112: 6.3862092 | L112: 5.7833796 | M112: 4.4393905
C113: 0 | D113: 0 | E113: 0 | F113: 0 | G113: 0 | H113: 12.108618 | I113: 17.482122 | J113: 10.074715 | K113: 8.056348 | L113: 6.6177484 | M113: 5.9799258
C114: 0 | D114: 0 | E114: 0 | F114: 0 | G114: 0 | H114: 0 | I114: 12.652144 | J114: 18.317511 | K114: 10.543613 | L114: 8.431541 | M114: 6.9247687
C115: 0 | D115: 0 | E115: 0 | F115: 0 | G115: 0 | H115: 0 | I115: 0 | J115: 13.378458 | K115: 19.216281 | L115: 11.083541 | M115: 8.8619166
C116: 0 | D116: 0 | E116: 0 | F116: 0 | G116: 0 | H116: 0 | I116: 0 | J116: 0 | K116: 13.83017 | L116: 19.655189 | M116: 11.347409
C117: 0 | D117: 0 | E117: 0 | F117: 0 | G117: 0 | H117: 0 | I117: 0 | J117: 0 | K117: 0 | L117: 14.308148 | M117: 20.263673
C118: 0 | D118: 0 | E118: 0 | F118: 0 | G118: 0 | H118: 0 | I118: 0 | J118: 0 | K118: 0 | L118: 0 | M118: 15.000353
A120: Offsets | C120: 38.674376 | D120: 39.52779 | E120: 41.076872 | F120: 42.599751 | G120: 44.250336 | H120: 45.889798 | I120: 47.685656 | J120: 49.520152 | K120: 51.424714 | L120: 53.397966 | M120: 55.443378
A122: Interest Rate Change | C122: =C76-C75 -> 0.1 | D122: =D76-D75 -> 0.1 | E122: =E76-E75 -> 0.1 | F122: =F76-F75 -> 0.1 | G122: =G76-G75 -> 0.1 | H122: =H76-H75 -> 0.1 | I122: =I76-I75 -> 0.1 | J122: =J76-J75 -> 0.1 | ... M122: =M76-M75 -> 0.1
A124: Interest Change Matrix | C124: 52.194 | D124: 72.44 | E124: 41.604 | F124: 33.166 | G124: 27.507 | H124: 24.802 | I124: 18.083 | J124: 16.269 | K124: 12.265 | L124: 12.07 | M124: 10.215
C125: 0 | D125: 54.98 | E125: 76.133 | F125: 43.307 | G125: 34.496 | H125: 28.579 | I125: 25.954 | J125: 19.027 | K125: 16.892 | L125: 12.59 | M125: 12.39
C126: 0 | D126: 0 | E126: 56.723 | F126: 80.096 | G126: 45.121 | H126: 35.912 | I126: 29.72 | J126: 27.184 | K126: 20.037 | L126: 17.55 | M126: 12.931
C127: 0 | D127: 0 | E127: 0 | F127: 60.441 | G127: 85.403 | H127: 48.331 | I127: 38.578 | J127: 31.995 | K127: 28.98 | L127: 21.3 | M127: 18.656
C128: 0 | D128: 0 | E128: 0 | F128: 0 | G128: 63.893 | H128: 89.099 | I128: 50.653 | J128: 40.547 | K128: 33.7 | L128: 30.224 | M128: 22.152
C129: 0 | D129: 0 | E129: 0 | F129: 0 | G129: 0 | H129: 68.037 | I129: 94.484 | J129: 53.69 | K129: 43.116 | L129: 35.888 | M129: 32.186
C130: 0 | D130: 0 | E130: 0 | F130: 0 | G130: 0 | H130: 0 | I130: 70.948 | J130: 99.77 | K130: 56.668 | L130: 45.654 | M130: 38.056
C131: 0 | D131: 0 | E131: 0 | F131: 0 | G131: 0 | H131: 0 | I131: 0 | J131: 74.688 | K131: 103.9 | L131: 58.811 | M131: 47.381
C132: 0 | D132: 0 | E132: 0 | F132: 0 | G132: 0 | H132: 0 | I132: 0 | J132: 0 | K132: 78.212 | L132: 110.358 | M132: 62.251
...

Sheet 4. Inflation and Interest
A1: This workbook supplements CBO’s report How Changes in Economic Conditions Might Affect the Federal Budget: 2025 to 2035.
A2: www.cbo.gov/publication/61198
A5: To create an alternative scenario for inflation and interest rates, enter values between -1.0 percentage point and 1.0 percentage point in each of the green cells. (Only the green cells can be edited; all other cells are locked. Values outside of the specified range will produce errors.) The change in budgetary outcomes relative to those in CBO’s baseline will be calculated and appear automatically. Values for key economic indicators are shown below those budgetary effects.
A7: 4. Interactive Table: How Changes in Inflation and Interest Rates Might Affect the Federal Budget
B9: 2024 | C9: 2025 | D9: 2026 | E9: 2027 | F9: 2028 | G9: 2029 | H9: 2030 | I9: 2031 | J9: 2032 | K9: 2033 | L9: 2034 | M9: 2035
C11: User-specified scenario for inflation and interest rates
O12: These initial values are the same as those used to generate the illustrative scenario shown in Worksheet 8, “Inflation and Interest_CBO.”
A13: Increase or decrease (-) in inflation relative to CBO’s January 2025 baseline (percentage points) | B13: n.a. | C13: 0.1 | D13: 0.1 | E13: 0.1 | F13: 0.1 | G13: 0.1 | H13: 0.1 | I13: 0.1 | J13: 0.1 | K13: 0.1 | L13: 0.1 | M13: 0.1
A14: Increase or decrease (-) in interest rates relative to CBO’s January 2025 baseline (percentage points) | B14: n.a. | C14: 0.1 | D14: 0.1 | E14: 0.1 | F14: 0.1 | G14: 0.1 | H14: 0.1 | I14: 0.1 | J14: 0.1 | K14: 0.1 | L14: 0.1 | M14: 0.1
A15: =IF($A$22,"Please keep values in the range [-1.0, 1.0] percentage point per year.","")
A16: Inflation (percent)a
A17: January 2025 baseline | B17: 2.413 | C17: 2.198 | D17: 2.075 | E17: 1.995 | F17: 1.988 | G17: 1.992 | H17: 1.987 | I17: 1.986 | J17: 1.987 | K17: 1.991 | L17: 1.989 | M17: 1.99
A18: User-specified scenario | B18: =IF($A$23,"n.a.",B17) -> 2.413 | C18: =IF($A$23,"n.a.",C17+C13) -> 2.298 | D18: =IF($A$23,"n.a.",D17+D13) -> 2.175 | E18: =IF($A$23,"n.a.",E17+E13) -> 2.095 | F18: =IF($A$23,"n.a.",F17+F13) -> 2.088 | G18: =IF($A$23,"n.a.",G17+G13) -> 2.092 | H18: =IF($A$23,"n.a.",H17+H13) -> 2.087 | I18: =IF($A$23,"n.a.",I17+I13) -> 2.086 | J18: =IF($A$23,"n.a.",J17+J13) -> 2.087 | ... M18: =IF($A$23,"n.a.",M17+M13) -> 2.09
A19: Interest rate on 10-year Treasury notes (percent)b
A20: January 2025 baseline | B20: 4.188 | C20: 4.093 | D20: 3.935 | E20: 3.914 | F20: 3.894 | G20: 3.871 | H20: 3.85 | I20: 3.836 | J20: 3.826 | K20: 3.815 | L20: 3.797 | M20: 3.772
A21: User-specified scenario | B21: =IF($A$23,"n.a.",B20) -> 4.188 | C21: =IF($A$23,"n.a.",C20+C14) -> 4.193 | D21: =IF($A$23,"n.a.",D20+D14) -> 4.035 | E21: =IF($A$23,"n.a.",E20+E14) -> 4.014 | F21: =IF($A$23,"n.a.",F20+F14) -> 3.994 | G21: =IF($A$23,"n.a.",G20+G14) -> 3.971 | H21: =IF($A$23,"n.a.",H20+H14) -> 3.95 | I21: =IF($A$23,"n.a.",I20+I14) -> 3.936 | J21: =IF($A$23,"n.a.",J20+J14) -> 3.926 | ... M21: =IF($A$23,"n.a.",M20+M14) -> 3.872
A23: =IF(OR(MAX(C13:M14)>1,MIN(C13:M14)<-1),1,0) -> 0
C25: Budgetary effects (billions of dollars) | N25: Total
N26: 2026- | O26: 2026-
B27: 2024 | C27: 2025 | D27: 2026 | E27: 2027 | F27: 2028 | G27: 2029 | H27: 2030 | I27: 2031 | J27: 2032 | K27: 2033 | L27: 2034 | M27: 2035 | N27: 2030 | O27: 2035
A28: Changes in revenues | B28: n.a. | C28: {=IF($A$23,"n.a.",ROUND(TRUNC(SUMPRODUCT($C14:$M14,TRANSPOSE(C113:C123))-C125*(C14*0.75),3)+('8. Inflation and Interest_CBO'!C11-'7. Interest Rates_CBO'!C11)/('8. Inflation and Interest_CBO'!C58-'8. Inflation and Interest_CBO'!C57)*(ROUND('4. Inflation and Interest'!C75,1)-ROUND('4. Inflation and Interest'!C74,1)),3))} -> 1.559 | D28: {=IF($A$23,"n.a.",ROUND(TRUNC(SUMPRODUCT($C14:$M14,TRANSPOSE(D113:D123))-D125*(D14*0.75+C14*0.25),3)+('8. Inflation and Interest_CBO'!D11-'7. Interest Rates_CBO'!D11)/('8. Inflation and Interest_CBO'!D58-'8. Inflation and Interest_CBO'!D57)*(ROUND('4. Inflation and Interest'!D75,1)-ROUND('4. Inflation and Interest'!D74,1)),3))} -> 7.261 | E28: {=IF($A$23,"n.a.",ROUND(TRUNC(SUMPRODUCT($C14:$M14,TRANSPOSE(E113:E123))-E125*(E14*0.75+D14*0.25),3)+('8. Inflation and Interest_CBO'!E11-'7. Interest Rates_CBO'!E11)/('8. Inflation and Interest_CBO'!E58-'8. Inflation and Interest_CBO'!E57)*(ROUND('4. Inflation and Interest'!E75,1)-ROUND('4. Inflation and Interest'!E74,1)),3))} -> 13.503 | F28: {=IF($A$23,"n.a.",ROUND(TRUNC(SUMPRODUCT($C14:$M14,TRANSPOSE(F113:F123))-F125*(F14*0.75+E14*0.25),3)+('8. Inflation and Interest_CBO'!F11-'7. Interest Rates_CBO'!F11)/('8. Inflation and Interest_CBO'!F58-'8. Inflation and Interest_CBO'!F57)*(ROUND('4. Inflation and Interest'!F75,1)-ROUND('4. Inflation and Interest'!F74,1)),3))} -> 19.902 | G28: {=IF($A$23,"n.a.",ROUND(TRUNC(SUMPRODUCT($C14:$M14,TRANSPOSE(G113:G123))-G125*(G14*0.75+F14*0.25),3)+('8. Inflation and Interest_CBO'!G11-'7. Interest Rates_CBO'!G11)/('8. Inflation and Interest_CBO'!G58-'8. Inflation and Interest_CBO'!G57)*(ROUND('4. Inflation and Interest'!G75,1)-ROUND('4. Inflation and Interest'!G74,1)),3))} -> 26.691 | H28: {=IF($A$23,"n.a.",ROUND(TRUNC(SUMPRODUCT($C14:$M14,TRANSPOSE(H113:H123))-H125*(H14*0.75+G14*0.25),3)+('8. Inflation and Interest_CBO'!H11-'7. Interest Rates_CBO'!H11)/('8. Inflation and Interest_CBO'!H58-'8. Inflation and Interest_CBO'!H57)*(ROUND('4. Inflation and Interest'!H75,1)-ROUND('4. Inflation and Interest'!H74,1)),3))} -> 33.925 | I28: {=IF($A$23,"n.a.",ROUND(TRUNC(SUMPRODUCT($C14:$M14,TRANSPOSE(I113:I123))-I125*(I14*0.75+H14*0.25),3)+('8. Inflation and Interest_CBO'!I11-'7. Interest Rates_CBO'!I11)/('8. Inflation and Interest_CBO'!I58-'8. Inflation and Interest_CBO'!I57)*(ROUND('4. Inflation and Interest'!I75,1)-ROUND('4. Inflation and Interest'!I74,1)),3))} -> 41.556 | J28: {=IF($A$23,"n.a.",ROUND(TRUNC(SUMPRODUCT($C14:$M14,TRANSPOSE(J113:J123))-J125*(J14*0.75+I14*0.25),3)+('8. Inflation and Interest_CBO'!J11-'7. Interest Rates_CBO'!J11)/('8. Inflation and Interest_CBO'!J58-'8. Inflation and Interest_CBO'!J57)*(ROUND('4. Inflation and Interest'!J75,1)-ROUND('4. Inflation and Interest'!J74,1)),3))} -> 49.813 | K28: {=IF($A$23,"n.a.",ROUND(TRUNC(SUMPRODUCT($C14:$M14,TRANSPOSE(K113:K123))-K125*(K14*0.75+J14*0.25),3)+('8. Inflation and Interest_CBO'!K11-'7. Interest Rates_CBO'!K11)/('8. Inflation and Interest_CBO'!K58-'8. Inflation and Interest_CBO'!K57)*(ROUND('4. Inflation and Interest'!K75,1)-ROUND('4. Inflation and Interest'!K74,1)),3))} -> 58.187 | ... M28: {=IF($A$23,"n.a.",ROUND(TRUNC(SUMPRODUCT($C14:$M14,TRANSPOSE(M113:M123))-M125*(M14*0.75+L14*0.25),3)+('8. Inflation and Interest_CBO'!M11-'7. Interest Rates_CBO'!M11)/('8. Inflation and Interest_CBO'!M58-'8. Inflation and Interest_CBO'!M57)*(ROUND('4. Inflation and Interest'!M75,1)-ROUND('4. Inflation and Interest'!M74,1)),3))} -> 77.183 | N28: =IF($A$23,"n.a.",SUM(D28:H28)) -> 101.282 | O28: =IF($A$23,"n.a.",SUM(D28:M28)) -> 395.472
A30: Changes in outlays
A31: Mandatory outlays | B31: n.a. | C31: =IF($A$23,"n.a.",ROUND('7. Interest Rates_CBO'!C14*C127/('7. Interest Rates_CBO'!C63-'7. Interest Rates_CBO'!C62)+('8. Inflation and Interest_CBO'!C14-'7. Interest Rates_CBO'!C14)/('8. Inflation and Interest_CBO'!C58-'8. Inflation and Interest_CBO'!C57)*(ROUND('4. Inflation and Interest'!C75,1)-ROUND('4. Inflation and Interest'!C74,1)),3)) -> 0.403 | D31: =IF($A$23,"n.a.",ROUND('7. Interest Rates_CBO'!D14*D127/('7. Interest Rates_CBO'!D63-'7. Interest Rates_CBO'!D62)+('8. Inflation and Interest_CBO'!D14-'7. Interest Rates_CBO'!D14)/('8. Inflation and Interest_CBO'!D58-'8. Inflation and Interest_CBO'!D57)*(ROUND('4. Inflation and Interest'!D75,1)-ROUND('4. Inflation and Interest'!D74,1)),3)) -> 3.296 | E31: =IF($A$23,"n.a.",ROUND('7. Interest Rates_CBO'!E14*E127/('7. Interest Rates_CBO'!E63-'7. Interest Rates_CBO'!E62)+('8. Inflation and Interest_CBO'!E14-'7. Interest Rates_CBO'!E14)/('8. Inflation and Interest_CBO'!E58-'8. Inflation and Interest_CBO'!E57)*(ROUND('4. Inflation and Interest'!E75,1)-ROUND('4. Inflation and Interest'!E74,1)),3)) -> 7.126 | F31: =IF($A$23,"n.a.",ROUND('7. Interest Rates_CBO'!F14*F127/('7. Interest Rates_CBO'!F63-'7. Interest Rates_CBO'!F62)+('8. Inflation and Interest_CBO'!F14-'7. Interest Rates_CBO'!F14)/('8. Inflation and Interest_CBO'!F58-'8. Inflation and Interest_CBO'!F57)*(ROUND('4. Inflation and Interest'!F75,1)-ROUND('4. Inflation and Interest'!F74,1)),3)) -> 11.473 | G31: =IF($A$23,"n.a.",ROUND('7. Interest Rates_CBO'!G14*G127/('7. Interest Rates_CBO'!G63-'7. Interest Rates_CBO'!G62)+('8. Inflation and Interest_CBO'!G14-'7. Interest Rates_CBO'!G14)/('8. Inflation and Interest_CBO'!G58-'8. Inflation and Interest_CBO'!G57)*(ROUND('4. Inflation and Interest'!G75,1)-ROUND('4. Inflation and Interest'!G74,1)),3)) -> 16.016 | H31: =IF($A$23,"n.a.",ROUND('7. Interest Rates_CBO'!H14*H127/('7. Interest Rates_CBO'!H63-'7. Interest Rates_CBO'!H62)+('8. Inflation and Interest_CBO'!H14-'7. Interest Rates_CBO'!H14)/('8. Inflation and Interest_CBO'!H58-'8. Inflation and Interest_CBO'!H57)*(ROUND('4. Inflation and Interest'!H75,1)-ROUND('4. Inflation and Interest'!H74,1)),3)) -> 21.023 | I31: =IF($A$23,"n.a.",ROUND('7. Interest Rates_CBO'!I14*I127/('7. Interest Rates_CBO'!I63-'7. Interest Rates_CBO'!I62)+('8. Inflation and Interest_CBO'!I14-'7. Interest Rates_CBO'!I14)/('8. Inflation and Interest_CBO'!I58-'8. Inflation and Interest_CBO'!I57)*(ROUND('4. Inflation and Interest'!I75,1)-ROUND('4. Inflation and Interest'!I74,1)),3)) -> 26.272 | J31: =IF($A$23,"n.a.",ROUND('7. Interest Rates_CBO'!J14*J127/('7. Interest Rates_CBO'!J63-'7. Interest Rates_CBO'!J62)+('8. Inflation and Interest_CBO'!J14-'7. Interest Rates_CBO'!J14)/('8. Inflation and Interest_CBO'!J58-'8. Inflation and Interest_CBO'!J57)*(ROUND('4. Inflation and Interest'!J75,1)-ROUND('4. Inflation and Interest'!J74,1)),3)) -> 32.243 | ... M31: =IF($A$23,"n.a.",ROUND('7. Interest Rates_CBO'!M14*M127/('7. Interest Rates_CBO'!M63-'7. Interest Rates_CBO'!M62)+('8. Inflation and Interest_CBO'!M14-'7. Interest Rates_CBO'!M14)/('8. Inflation and Interest_CBO'!M58-'8. Inflation and Interest_CBO'!M57)*(ROUND('4. Inflation and Interest'!M75,1)-ROUND('4. Inflation and Interest'!M74,1)),3)) -> 51.832 | N31: =IF($A$23,"n.a.",SUM(D31:H31)) -> 58.934 | O31: =IF($A$23,"n.a.",SUM(D31:M31)) -> 253.657
A32: Discretionary outlays | B32: n.a. | C32: =IF($A$23,"n.a.",'8. Inflation and Interest_CBO'!C15/('8. Inflation and Interest_CBO'!C58-'8. Inflation and Interest_CBO'!C57)*(ROUND('4. Inflation and Interest'!C75,1)-ROUND('4. Inflation and Interest'!C74,1))) -> 0 | D32: =IF($A$23,"n.a.",'8. Inflation and Interest_CBO'!D15/('8. Inflation and Interest_CBO'!D58-'8. Inflation and Interest_CBO'!D57)*(ROUND('4. Inflation and Interest'!D75,1)-ROUND('4. Inflation and Interest'!D74,1))) -> 1.088 | E32: =IF($A$23,"n.a.",'8. Inflation and Interest_CBO'!E15/('8. Inflation and Interest_CBO'!E58-'8. Inflation and Interest_CBO'!E57)*(ROUND('4. Inflation and Interest'!E75,1)-ROUND('4. Inflation and Interest'!E74,1))) -> 2.665 | F32: =IF($A$23,"n.a.",'8. Inflation and Interest_CBO'!F15/('8. Inflation and Interest_CBO'!F58-'8. Inflation and Interest_CBO'!F57)*(ROUND('4. Inflation and Interest'!F75,1)-ROUND('4. Inflation and Interest'!F74,1))) -> 4.464 | G32: =IF($A$23,"n.a.",'8. Inflation and Interest_CBO'!G15/('8. Inflation and Interest_CBO'!G58-'8. Inflation and Interest_CBO'!G57)*(ROUND('4. Inflation and Interest'!G75,1)-ROUND('4. Inflation and Interest'!G74,1))) -> 6.421 | H32: =IF($A$23,"n.a.",'8. Inflation and Interest_CBO'!H15/('8. Inflation and Interest_CBO'!H58-'8. Inflation and Interest_CBO'!H57)*(ROUND('4. Inflation and Interest'!H75,1)-ROUND('4. Inflation and Interest'!H74,1))) -> 8.545 | I32: =IF($A$23,"n.a.",'8. Inflation and Interest_CBO'!I15/('8. Inflation and Interest_CBO'!I58-'8. Inflation and Interest_CBO'!I57)*(ROUND('4. Inflation and Interest'!I75,1)-ROUND('4. Inflation and Interest'!I74,1))) -> 10.748 | J32: =IF($A$23,"n.a.",'8. Inflation and Interest_CBO'!J15/('8. Inflation and Interest_CBO'!J58-'8. Inflation and Interest_CBO'!J57)*(ROUND('4. Inflation and Interest'!J75,1)-ROUND('4. Inflation and Interest'!J74,1))) -> 13.046 | ... M32: =IF($A$23,"n.a.",'8. Inflation and Interest_CBO'!M15/('8. Inflation and Interest_CBO'!M58-'8. Inflation and Interest_CBO'!M57)*(ROUND('4. Inflation and Interest'!M75,1)-ROUND('4. Inflation and Interest'!M74,1))) -> 20.545 | N32: =IF($A$23,"n.a.",SUM(D32:H32)) -> 23.183 | O32: =IF($A$23,"n.a.",SUM(D32:M32)) -> 100.904
A33: Net interest outlays
A34: Effects from changes in interest rates | B34: n.a. | C34: {=IF($A$23,"n.a.",ROUND(SUMPRODUCT(TRANSPOSE($C127:$M127),C129:C139),3)+ROUND(C141*C127/('8. Inflation and Interest_CBO'!C64-'8. Inflation and Interest_CBO'!C63),3))} -> 5.219 | D34: {=IF($A$23,"n.a.",ROUND(SUMPRODUCT(TRANSPOSE($C127:$M127),D129:D139),3)+ROUND(D141*D127/('8. Inflation and Interest_CBO'!D64-'8. Inflation and Interest_CBO'!D63),3))} -> 12.742 | E34: {=IF($A$23,"n.a.",ROUND(SUMPRODUCT(TRANSPOSE($C127:$M127),E129:E139),3)+ROUND(E141*E127/('8. Inflation and Interest_CBO'!E64-'8. Inflation and Interest_CBO'!E63),3))} -> 17.446 | F34: {=IF($A$23,"n.a.",ROUND(SUMPRODUCT(TRANSPOSE($C127:$M127),F129:F139),3)+ROUND(F141*F127/('8. Inflation and Interest_CBO'!F64-'8. Inflation and Interest_CBO'!F63),3))} -> 21.701 | G34: {=IF($A$23,"n.a.",ROUND(SUMPRODUCT(TRANSPOSE($C127:$M127),G129:G139),3)+ROUND(G141*G127/('8. Inflation and Interest_CBO'!G64-'8. Inflation and Interest_CBO'!G63),3))} -> 25.642 | H34: {=IF($A$23,"n.a.",ROUND(SUMPRODUCT(TRANSPOSE($C127:$M127),H129:H139),3)+ROUND(H141*H127/('8. Inflation and Interest_CBO'!H64-'8. Inflation and Interest_CBO'!H63),3))} -> 29.476 | I34: {=IF($A$23,"n.a.",ROUND(SUMPRODUCT(TRANSPOSE($C127:$M127),I129:I139),3)+ROUND(I141*I127/('8. Inflation and Interest_CBO'!I64-'8. Inflation and Interest_CBO'!I63),3))} -> 32.842 | J34: {=IF($A$23,"n.a.",ROUND(SUMPRODUCT(TRANSPOSE($C127:$M127),J129:J139),3)+ROUND(J141*J127/('8. Inflation and Interest_CBO'!J64-'8. Inflation and Interest_CBO'!J63),3))} -> 36.317 | ... M34: {=IF($A$23,"n.a.",ROUND(SUMPRODUCT(TRANSPOSE($C127:$M127),M129:M139),3)+ROUND(M141*M127/('8. Inflation and Interest_CBO'!M64-'8. Inflation and Interest_CBO'!M63),3))} -> 45.526 | N34: =IF($A$23,"n.a.",SUM(D34:H34)) -> 107.007 | O34: =IF($A$23,"n.a.",SUM(D34:M34)) -> 303.656
A35: Effects from changes in inflationc | B35: n.a. | C35: {=IF($A$23,"n.a.",ROUND(SUMPRODUCT(TRANSPOSE($C159:$M159),C161:C171),3) + ROUND(C173*C159/0.1,3))} -> 2.059 | D35: {=IF($A$23,"n.a.",ROUND(SUMPRODUCT(TRANSPOSE($C159:$M159),D161:D171),3) + ROUND(D173*D159/0.1,3))} -> 1.801 | E35: {=IF($A$23,"n.a.",ROUND(SUMPRODUCT(TRANSPOSE($C159:$M159),E161:E171),3) + ROUND(E173*E159/0.1,3))} -> 1.736 | F35: {=IF($A$23,"n.a.",ROUND(SUMPRODUCT(TRANSPOSE($C159:$M159),F161:F171),3) + ROUND(F173*F159/0.1,3))} -> 1.603 | G35: {=IF($A$23,"n.a.",ROUND(SUMPRODUCT(TRANSPOSE($C159:$M159),G161:G171),3) + ROUND(G173*G159/0.1,3))} -> 1.466 | H35: {=IF($A$23,"n.a.",ROUND(SUMPRODUCT(TRANSPOSE($C159:$M159),H161:H171),3) + ROUND(H173*H159/0.1,3))} -> 1.4 | I35: {=IF($A$23,"n.a.",ROUND(SUMPRODUCT(TRANSPOSE($C159:$M159),I161:I171),3) + ROUND(I173*I159/0.1,3))} -> 1.412 | J35: {=IF($A$23,"n.a.",ROUND(SUMPRODUCT(TRANSPOSE($C159:$M159),J161:J171),3) + ROUND(J173*J159/0.1,3))} -> 1.421 | ... M35: {=IF($A$23,"n.a.",ROUND(SUMPRODUCT(TRANSPOSE($C159:$M159),M161:M171),3) + ROUND(M173*M159/0.1,3))} -> 1.52 | N35: =IF($A$23,"n.a.",SUM(D35:H35)) -> 8.006 | O35: =IF($A$23,"n.a.",SUM(D35:M35)) -> 15.24
A36: Debt service | B36: n.a. | C36: {=IF($A$23,"n.a.",ROUND(SUMPRODUCT($C143:$M143,TRANSPOSE(C145:C155)),3) + ROUND((-C157)*C143/('8. Inflation and Interest_CBO'!C25+'8. Inflation and Interest_CBO'!C19),3))} -> 0.066 | D36: {=IF($A$23,"n.a.",ROUND(SUMPRODUCT($C143:$M143,TRANSPOSE(D145:D155)),3) + ROUND((-D157)*D143/('8. Inflation and Interest_CBO'!D25+'8. Inflation and Interest_CBO'!D19),3))} -> 0.459 | E36: {=IF($A$23,"n.a.",ROUND(SUMPRODUCT($C143:$M143,TRANSPOSE(E145:E155)),3) + ROUND((-E157)*E143/('8. Inflation and Interest_CBO'!E25+'8. Inflation and Interest_CBO'!E19),3))} -> 0.968 | F36: {=IF($A$23,"n.a.",ROUND(SUMPRODUCT($C143:$M143,TRANSPOSE(F145:F155)),3) + ROUND((-F157)*F143/('8. Inflation and Interest_CBO'!F25+'8. Inflation and Interest_CBO'!F19),3))} -> 1.632 | G36: {=IF($A$23,"n.a.",ROUND(SUMPRODUCT($C143:$M143,TRANSPOSE(G145:G155)),3) + ROUND((-G157)*G143/('8. Inflation and Interest_CBO'!G25+'8. Inflation and Interest_CBO'!G19),3))} -> 2.44 | H36: {=IF($A$23,"n.a.",ROUND(SUMPRODUCT($C143:$M143,TRANSPOSE(H145:H155)),3) + ROUND((-H157)*H143/('8. Inflation and Interest_CBO'!H25+'8. Inflation and Interest_CBO'!H19),3))} -> 3.403 | I36: {=IF($A$23,"n.a.",ROUND(SUMPRODUCT($C143:$M143,TRANSPOSE(I145:I155)),3) + ROUND((-I157)*I143/('8. Inflation and Interest_CBO'!I25+'8. Inflation and Interest_CBO'!I19),3))} -> 4.501 | J36: {=IF($A$23,"n.a.",ROUND(SUMPRODUCT($C143:$M143,TRANSPOSE(J145:J155)),3) + ROUND((-J157)*J143/('8. Inflation and Interest_CBO'!J25+'8. Inflation and Interest_CBO'!J19),3))} -> 5.753 | ... M36: {=IF($A$23,"n.a.",ROUND(SUMPRODUCT($C143:$M143,TRANSPOSE(M145:M155)),3) + ROUND((-M157)*M143/('8. Inflation and Interest_CBO'!M25+'8. Inflation and Interest_CBO'!M19),3))} -> 10.456 | N36: =IF($A$23,"n.a.",SUM(D36:H36)) -> 8.902 | O36: =IF($A$23,"n.a.",SUM(D36:M36)) -> 45.516
B37: ____ | C37: ____ | D37: ____ | E37: ____ | F37: ____ | G37: ____ | H37: ____ | I37: ____ | J37: ____ | K37: ____ | L37: ____ | M37: ____ | N37: ____ | O37: ____
A38: Subtotal, net interest outlays | B38: n.a. | C38: =IF($A$23,"n.a.",C34+C36+C35) -> 7.344 | D38: =IF($A$23,"n.a.",D34+D36+D35) -> 15.002 | E38: =IF($A$23,"n.a.",E34+E36+E35) -> 20.15 | F38: =IF($A$23,"n.a.",F34+F36+F35) -> 24.936 | G38: =IF($A$23,"n.a.",G34+G36+G35) -> 29.548 | H38: =IF($A$23,"n.a.",H34+H36+H35) -> 34.279 | I38: =IF($A$23,"n.a.",I34+I36+I35) -> 38.755 | J38: =IF($A$23,"n.a.",J34+J36+J35) -> 43.491 | ... M38: =IF($A$23,"n.a.",M34+M36+M35) -> 57.502 | N38: =IF($A$23,"n.a.",SUM(D38:H38)) -> 123.915 | O38: =IF($A$23,"n.a.",SUM(D38:M38)) -> 364.412
A40: Total change in outlays | B40: n.a. | C40: =IF($A$23,"n.a.",C31+C32+C38) -> 7.747 | D40: =IF($A$23,"n.a.",D31+D32+D38) -> 19.386 | E40: =IF($A$23,"n.a.",E31+E32+E38) -> 29.941 | F40: =IF($A$23,"n.a.",F31+F32+F38) -> 40.873 | G40: =IF($A$23,"n.a.",G31+G32+G38) -> 51.985 | H40: =IF($A$23,"n.a.",H31+H32+H38) -> 63.847 | I40: =IF($A$23,"n.a.",I31+I32+I38) -> 75.775 | J40: =IF($A$23,"n.a.",J31+J32+J38) -> 88.78 | ... M40: =IF($A$23,"n.a.",M31+M32+M38) -> 129.879 | N40: =IF($A$23,"n.a.",SUM(D40:H40)) -> 206.032 | O40: =IF($A$23,"n.a.",SUM(D40:M40)) -> 718.973
A42: Increase (-) or decrease in the deficit relative to CBO’s baseline | B42: n.a. | C42: =IF($A$23,"n.a.",C28-C40) -> -6.188 | D42: =IF($A$23,"n.a.",D28-D40) -> -12.125 | E42: =IF($A$23,"n.a.",E28-E40) -> -16.438 | F42: =IF($A$23,"n.a.",F28-F40) -> -20.971 | G42: =IF($A$23,"n.a.",G28-G40) -> -25.294 | H42: =IF($A$23,"n.a.",H28-H40) -> -29.922 | I42: =IF($A$23,"n.a.",I28-I40) -> -34.219 | J42: =IF($A$23,"n.a.",J28-J40) -> -38.967 | ... M42: =IF($A$23,"n.a.",M28-M40) -> -52.696 | N42: =IF($A$23,"n.a.",SUM(D42:H42)) -> -104.75 | O42: =IF($A$23,"n.a.",SUM(D42:M42)) -> -323.501
A44: Deficit (-) or surplus
A45: January 2025 baseline | B45: -1832.381 | C45: -1865.251 | D45: -1713.258 | E45: -1686.942 | F45: -1910.776 | G45: -1938.268 | H45: -2139.721 | I45: -2232.786 | J45: -2370.582 | K45: -2637.299 | L45: -2597.25 | M45: -2531.378 | N45: -9388.965 | O45: -21758.26
A46: User-specified scenario | B46: =IF($A$23,"n.a.",B45) -> -1832.381 | C46: =IF($A$23,"n.a.",C45+C42) -> -1871.439 | D46: =IF($A$23,"n.a.",D45+D42) -> -1725.383 | E46: =IF($A$23,"n.a.",E45+E42) -> -1703.38 | F46: =IF($A$23,"n.a.",F45+F42) -> -1931.747 | G46: =IF($A$23,"n.a.",G45+G42) -> -1963.562 | H46: =IF($A$23,"n.a.",H45+H42) -> -2169.643 | I46: =IF($A$23,"n.a.",I45+I42) -> -2267.005 | J46: =IF($A$23,"n.a.",J45+J42) -> -2409.549 | ... M46: =IF($A$23,"n.a.",M45+M42) -> -2584.074 | N46: =IF($A$23,"n.a.",SUM(D46:H46)) -> -9493.715 | O46: =IF($A$23,"n.a.",SUM(D46:M46)) -> -22081.761
A48: Debt held by the public
A49: January 2025 baseline | B49: 28199.313 | C49: 30102.749 | D49: 31882.633 | E49: 33636.105 | F49: 35600.64 | G49: 37580.5 | H49: 39747.651 | I49: 41992.385 | J49: 44371.755 | K49: 46985.029 | L49: 49555.504 | M49: 52055.866 | N49: n.a. | O49: n.a.
A50: User-specified scenario | B50: =IF($A$23,"n.a.",B49) -> 28199.313 | C50: =IF($A$23,"n.a.",C49-SUM($C42:C42)) -> 30108.937 | D50: =IF($A$23,"n.a.",D49-SUM($C42:D42)) -> 31900.946 | E50: =IF($A$23,"n.a.",E49-SUM($C42:E42)) -> 33670.856 | F50: =IF($A$23,"n.a.",F49-SUM($C42:F42)) -> 35656.362 | G50: =IF($A$23,"n.a.",G49-SUM($C42:G42)) -> 37661.516 | H50: =IF($A$23,"n.a.",H49-SUM($C42:H42)) -> 39858.589 | I50: =IF($A$23,"n.a.",I49-SUM($C42:I42)) -> 42137.542 | J50: =IF($A$23,"n.a.",J49-SUM($C42:J42)) -> 44555.879 | ... M50: =IF($A$23,"n.a.",M49-SUM($C42:M42)) -> 52385.555 | N50: n.a. | O50: n.a.
A52: Deficit (-) or surplus (percentage of GDP)
A53: January 2025 baseline | B53: -6.3562158 | C53: -6.1894147 | D53: -5.4664504 | E53: -5.184518 | F53: -5.659123 | G53: -5.5304586 | H53: -5.8793652 | I53: -5.9080768 | J53: -6.0393242 | K53: -6.4690633 | L53: -6.1356563 | M53: -5.7614482 | N53: -5.5528141 | O53: -5.830748
A54: User-specified scenario | B54: =IF($A$23,"n.a.",B53) -> -6.3562158 | C54: =IF($A$23,"n.a.",ROUND(C46/C75*100,3)) -> -6.205 | D54: =IF($A$23,"n.a.",ROUND(D46/D75*100,3)) -> -5.496 | E54: =IF($A$23,"n.a.",ROUND(E46/E75*100,3)) -> -5.221 | F54: =IF($A$23,"n.a.",ROUND(F46/F75*100,3)) -> -5.7 | G54: =IF($A$23,"n.a.",ROUND(G46/G75*100,3)) -> -5.577 | H54: =IF($A$23,"n.a.",ROUND(H46/H75*100,3)) -> -5.928 | I54: =IF($A$23,"n.a.",ROUND(I46/I75*100,3)) -> -5.959 | J54: =IF($A$23,"n.a.",ROUND(J46/J75*100,3)) -> -6.092 | ... M54: =IF($A$23,"n.a.",ROUND(M46/M75*100,3)) -> -5.82 | N54: =IF($A$23,"n.a.",ROUND(SUM(D46:H46)/SUM(D75:H75)*100,3)) -> -5.594 | O54: =IF($A$23,"n.a.",ROUND(SUM(D46:M46)/SUM(D75:M75)*100,3)) -> -5.879
A56: Debt held by the public (percentage of GDP)
A57: January 2025 baseline | B57: 97.818585 | C57: 99.889183 | D57: 101.72714 | E57: 103.37462 | F57: 105.438 | G57: 107.22841 | H57: 109.21562 | I57: 111.1142 | J57: 113.04204 | K57: 115.25016 | L57: 117.06826 | M57: 118.47981 | N57: n.a. | O57: n.a.
A58: User-specified scenario | B58: =IF($A$23,"n.a.",B57) -> 97.818585 | C58: =IF($A$23,"n.a.",ROUND(C50/C75*100,3)) -> 99.836 | D58: =IF($A$23,"n.a.",ROUND(D50/D75*100,3)) -> 101.611 | E58: =IF($A$23,"n.a.",ROUND(E50/E75*100,3)) -> 103.202 | F58: =IF($A$23,"n.a.",ROUND(F50/F75*100,3)) -> 105.215 | G58: =IF($A$23,"n.a.",ROUND(G50/G75*100,3)) -> 106.96 | H58: =IF($A$23,"n.a.",ROUND(H50/H75*100,3)) -> 108.905 | I58: =IF($A$23,"n.a.",ROUND(I50/I75*100,3)) -> 110.763 | J58: =IF($A$23,"n.a.",ROUND(J50/J75*100,3)) -> 112.652 | ... M58: =IF($A$23,"n.a.",ROUND(M50/M75*100,3)) -> 117.98 | N58: n.a. | O58: n.a.
B61: Economic indicators in CBO’s January 2025 baseline and under the user-specified scenario
B63: 2024 | C63: 2025 | D63: 2026 | E63: 2027 | F63: 2028 | G63: 2029 | H63: 2030 | I63: 2031 | J63: 2032 | K63: 2033 | L63: 2034 | M63: 2035
A64: Real GDP growth (percent)
A65: January 2025 baseline | B65: 2.734 | C65: 2.124 | D65: 1.827 | E65: 1.763 | F65: 1.744 | G65: 1.786 | H65: 1.821 | I65: 1.822 | J65: 1.842 | K65: 1.826 | L65: 1.797 | M65: 1.76
A66: User-specified scenario | B66: =IF($A$23,"n.a.",B65) -> 2.734 | C66: =IF($A$23,"n.a.",C65) -> 2.124 | D66: =IF($A$23,"n.a.",D65) -> 1.827 | E66: =IF($A$23,"n.a.",E65) -> 1.763 | F66: =IF($A$23,"n.a.",F65) -> 1.744 | G66: =IF($A$23,"n.a.",G65) -> 1.786 | H66: =IF($A$23,"n.a.",H65) -> 1.821 | I66: =IF($A$23,"n.a.",I65) -> 1.822 | ... M66: =IF($A$23,"n.a.",M65) -> 1.76
A67: Real GDP (billions of 2017 dollars)
A68: January 2025 baseline | B68: 23290.9 | C68: 23785.8 | D68: 24220.5 | E68: 24647.6 | F68: 25077.7 | G68: 25525.6 | H68: 25990.7 | I68: 26464.3 | J68: 26952 | K68: 27444.4 | L68: 27937.8 | M68: 28429.6
A69: User-specified scenario | B69: =IF($A$23,"n.a.",B68) -> 23290.9 | C69: =IF($A$23,"n.a.",C68) -> 23785.8 | D69: =IF($A$23,"n.a.",D68) -> 24220.5 | E69: =IF($A$23,"n.a.",E68) -> 24647.6 | F69: =IF($A$23,"n.a.",F68) -> 25077.7 | G69: =IF($A$23,"n.a.",G68) -> 25525.6 | H69: =IF($A$23,"n.a.",H68) -> 25990.7 | I69: =IF($A$23,"n.a.",I68) -> 26464.3 | ... M69: =IF($A$23,"n.a.",M68) -> 28429.6
A70: Nominal GDP (billions of dollars)
A71: January 2025 baseline | B71: 29166.2 | C71: 30441.1 | D71: 31640.6 | E71: 32841 | F71: 34078.4 | G71: 35378.4 | H71: 36738.8 | I71: 38151.3 | J71: 39626.7 | K71: 41154.2 | L71: 42727.6 | M71: 44345.4
A72: User-specified scenario | B72: =IF($A$23,"n.a.",B71) -> 29166.2 | C72: =IF($A$23,"n.a.",ROUND(C71*(C87/C86),1)) -> 30470.8 | D72: =IF($A$23,"n.a.",ROUND(D71*(D87/D86),1)) -> 31702.6 | E72: =IF($A$23,"n.a.",ROUND(E71*(E87/E86),1)) -> 32937.6 | F72: =IF($A$23,"n.a.",ROUND(F71*(F87/F86),1)) -> 34212.1 | G72: =IF($A$23,"n.a.",ROUND(G71*(G87/G86),1)) -> 35552 | H72: =IF($A$23,"n.a.",ROUND(H71*(H87/H86),1)) -> 36955.3 | I72: =IF($A$23,"n.a.",ROUND(I71*(I87/I86),1)) -> 38413.8 | J72: =IF($A$23,"n.a.",ROUND(J71*(J87/J86),1)) -> 39938.5 | ... M72: =IF($A$23,"n.a.",ROUND(M71*(M87/M86),1)) -> 44825.9
A73: Nominal GDP (billions of dollars, by fiscal year)
A74: January 2025 baseline | B74: 28823 | C74: 30136.1 | D74: 31341.3 | E74: 32538.1 | F74: 33764.5 | G74: 35047.1 | H74: 36393.7 | I74: 37792.1 | J74: 39252.4 | K74: 40767.9 | L74: 42330.4 | M74: 43936.5
A75: User-specified scenario | B75: =IF($A$23,"n.a.",B74) -> 28823 | C75: =IF($A$23,"n.a.",ROUND(C74+(C72-C71)*0.75+(B72-B71)*0.25,1)) -> 30158.4 | D75: =IF($A$23,"n.a.",ROUND(D74+(D72-D71)*0.75+(C72-C71)*0.25,1)) -> 31395.2 | E75: =IF($A$23,"n.a.",ROUND(E74+(E72-E71)*0.75+(D72-D71)*0.25,1)) -> 32626.1 | F75: =IF($A$23,"n.a.",ROUND(F74+(F72-F71)*0.75+(E72-E71)*0.25,1)) -> 33888.9 | G75: =IF($A$23,"n.a.",ROUND(G74+(G72-G71)*0.75+(F72-F71)*0.25,1)) -> 35210.7 | H75: =IF($A$23,"n.a.",ROUND(H74+(H72-H71)*0.75+(G72-G71)*0.25,1)) -> 36599.5 | I75: =IF($A$23,"n.a.",ROUND(I74+(I72-I71)*0.75+(H72-H71)*0.25,1)) -> 38043.1 | J75: =IF($A$23,"n.a.",ROUND(J74+(J72-J71)*0.75+(I72-I71)*0.25,1)) -> 39551.9 | ... M75: =IF($A$23,"n.a.",ROUND(M74+(M72-M71)*0.75+(L72-L71)*0.25,1)) -> 44402.1
A76: Labor force (millions of people)
A77: January 2025 baseline | B77: 168.243 | C77: 170.662 | D77: 173.375 | E77: 174.006 | F77: 174.614 | G77: 175.295 | H77: 176.03 | I77: 176.801 | J77: 177.558 | K77: 178.176 | L77: 178.795 | M77: 179.386
A78: User-specified scenario | B78: =IF($A$23,"n.a.",B77) -> 168.243 | C78: =IF($A$23,"n.a.",C77) -> 170.662 | D78: =IF($A$23,"n.a.",D77) -> 173.375 | E78: =IF($A$23,"n.a.",E77) -> 174.006 | F78: =IF($A$23,"n.a.",F77) -> 174.614 | G78: =IF($A$23,"n.a.",G77) -> 175.295 | H78: =IF($A$23,"n.a.",H77) -> 176.03 | I78: =IF($A$23,"n.a.",I77) -> 176.801 | ... M78: =IF($A$23,"n.a.",M77) -> 179.386
A79: Interest rate on 10-year Treasury notes (percent)
A80: January 2025 baseline | B80: 4.188 | C80: 4.093 | D80: 3.935 | E80: 3.914 | F80: 3.894 | G80: 3.871 | H80: 3.85 | I80: 3.836 | J80: 3.826 | K80: 3.815 | L80: 3.797 | M80: 3.772
A81: User-specified scenario | B81: =IF($A$23,"n.a.",B80) -> 4.188 | C81: =IF($A$23,"n.a.",ROUND(C80+C14,3)) -> 4.193 | D81: =IF($A$23,"n.a.",ROUND(D80+D14,3)) -> 4.035 | E81: =IF($A$23,"n.a.",ROUND(E80+E14,3)) -> 4.014 | F81: =IF($A$23,"n.a.",ROUND(F80+F14,3)) -> 3.994 | G81: =IF($A$23,"n.a.",ROUND(G80+G14,3)) -> 3.971 | H81: =IF($A$23,"n.a.",ROUND(H80+H14,3)) -> 3.95 | I81: =IF($A$23,"n.a.",ROUND(I80+I14,3)) -> 3.936 | J81: =IF($A$23,"n.a.",ROUND(J80+J14,3)) -> 3.926 | ... M81: =IF($A$23,"n.a.",ROUND(M80+M14,3)) -> 3.872
A82: Inflation (percent)c
A83: January 2025 baseline | B83: 2.413 | C83: 2.198 | D83: 2.075 | E83: 1.995 | F83: 1.988 | G83: 1.992 | H83: 1.987 | I83: 1.986 | J83: 1.987 | K83: 1.991 | L83: 1.989 | M83: 1.99
A84: User-specified scenario | B84: =IF($A$23,"n.a.",B83) -> 2.413 | C84: =IF($A$23,"n.a.",ROUND(C83+C13,3)) -> 2.298 | D84: =IF($A$23,"n.a.",ROUND(D83+D13,3)) -> 2.175 | E84: =IF($A$23,"n.a.",ROUND(E83+E13,3)) -> 2.095 | F84: =IF($A$23,"n.a.",ROUND(F83+F13,3)) -> 2.088 | G84: =IF($A$23,"n.a.",ROUND(G83+G13,3)) -> 2.092 | H84: =IF($A$23,"n.a.",ROUND(H83+H13,3)) -> 2.087 | I84: =IF($A$23,"n.a.",ROUND(I83+I13,3)) -> 2.086 | J84: =IF($A$23,"n.a.",ROUND(J83+J13,3)) -> 2.087 | ... M84: =IF($A$23,"n.a.",ROUND(M83+M13,3)) -> 2.09
A85: GDP price index (2017 = 100)
A86: January 2025 baseline | B86: 125.223 | C86: 127.976 | D86: 130.631 | E86: 133.238 | F86: 135.887 | G86: 138.595 | H86: 141.349 | I86: 144.157 | J86: 147.023 | K86: 149.95 | L86: 152.934 | M86: 155.979
A87: User-specified scenario | B87: =IF($A$23,"n.a.",B86) -> 125.223 | C87: =IF($A$23,"n.a.",ROUND((C86/B86+C13/100)*B87,3)) -> 128.101 | D87: =IF($A$23,"n.a.",ROUND((D86/C86+D13/100)*C87,3)) -> 130.887 | E87: =IF($A$23,"n.a.",ROUND((E86/D86+E13/100)*D87,3)) -> 133.63 | F87: =IF($A$23,"n.a.",ROUND((F86/E86+F13/100)*E87,3)) -> 136.42 | G87: =IF($A$23,"n.a.",ROUND((G86/F86+G13/100)*F87,3)) -> 139.275 | H87: =IF($A$23,"n.a.",ROUND((H86/G86+H13/100)*G87,3)) -> 142.182 | I87: =IF($A$23,"n.a.",ROUND((I86/H86+I13/100)*H87,3)) -> 145.149 | J87: =IF($A$23,"n.a.",ROUND((J86/I86+J13/100)*I87,3)) -> 148.18 | ... M87: =IF($A$23,"n.a.",ROUND((M86/L86+M13/100)*L87,3)) -> 157.669
A88: Employment cost index (December 2005 = 100)d
A89: January 2025 baseline | B89: 168.291 | C89: 174.156 | D89: 180 | E89: 185.768 | F89: 191.526 | G89: 197.325 | H89: 203.213 | I89: 209.221 | J89: 215.381 | K89: 221.716 | L89: 228.225 | M89: 234.91
A90: User-specified scenario | B90: =IF($A$23,"n.a.",B89) -> 168.291 | C90: =IF($A$23,"n.a.",ROUND((C89/B89+C13/100)*B90,3)) -> 174.324 | D90: =IF($A$23,"n.a.",ROUND((D89/C89+D13/100)*C90,3)) -> 180.348 | E90: =IF($A$23,"n.a.",ROUND((E89/D89+E13/100)*D90,3)) -> 186.307 | F90: =IF($A$23,"n.a.",ROUND((F89/E89+F13/100)*E90,3)) -> 192.268 | G90: =IF($A$23,"n.a.",ROUND((G89/F89+G13/100)*F90,3)) -> 198.282 | H90: =IF($A$23,"n.a.",ROUND((H89/G89+H13/100)*G90,3)) -> 204.397 | I90: =IF($A$23,"n.a.",ROUND((I89/H89+I13/100)*H90,3)) -> 210.644 | J90: =IF($A$23,"n.a.",ROUND((J89/I89+J13/100)*I90,3)) -> 217.057 | ... M90: =IF($A$23,"n.a.",ROUND((M89/L89+M13/100)*L90,3)) -> 237.429
A93: Data source: Congressional Budget Office.
A95: Real values are nominal values that have been adjusted to remove the effects of changes in prices.
A97: See the “Contents” worksheet for a brief discussion of the formulas used in these tables.
A99: Unless otherwise noted, economic indicators are calendar year averages.
A101: GDP = gross domestic product; n.a. = not applicable.
A103: a. Measured using the GDP price index. Although all wage and price indexes change in this scenario, the table shows only the effects on the GDP price index.
A105: b. Although all interest rates change in this scenario, the table shows only the effects on the interest rate on 10-year Treasury notes.
A107: c. Includes a small interaction effect between interest rates and inflation.
A109: d. The employment cost index for wages and salaries of workers in private industry.
A112: Parameters
A113: Receipts Matrix | C113: 3.366015 | D113: 7.1344265 | E113: 3.9586524 | F113: 3.1787762 | G113: 2.5683348 | H113: 2.3651629 | I113: 1.7884586 | J113: 1.6276454 | K113: 1.1951171 | L113: 1.1698143 | M113: 1.0215589
C114: 0 | D114: 6.740815 | E114: 11.398476 | F114: 6.4757899 | G114: 5.1867778 | H114: 4.2336329 | I114: 3.8534222 | J114: 2.9446207 | K114: 2.6483769 | L114: 1.9667758 | M114: 1.9335182
C115: 0 | D115: 0 | E115: 8.9312261 | F115: 13.827504 | G115: 7.9073605 | H115: 6.3282635 | I115: 5.1828294 | J115: 4.6984024 | K115: 3.6037324 | L115: 3.2277211 | M115: 2.4067186
C116: 0 | D116: 0 | E116: 0 | F116: 10.31152 | G116: 15.482384 | H116: 8.8817367 | I116: 7.1062166 | J116: 5.8262285 | K116: 5.2749082 | L116: 4.0507085 | M116: 3.6232712
C117: 0 | D117: 0 | E117: 0 | F117: 0 | G117: 11.372028 | H117: 16.979846 | I117: 9.7360654 | J117: 7.7892466 | K117: 6.3862092 | L117: 5.7833796 | M117: 4.4393905
C118: 0 | D118: 0 | E118: 0 | F118: 0 | G118: 0 | H118: 12.108618 | I118: 17.482122 | J118: 10.074715 | K118: 8.056348 | L118: 6.6177484 | M118: 5.9799258
C119: 0 | D119: 0 | E119: 0 | F119: 0 | G119: 0 | H119: 0 | I119: 12.652144 | J119: 18.317511 | K119: 10.543613 | L119: 8.431541 | M119: 6.9247687
C120: 0 | D120: 0 | E120: 0 | F120: 0 | G120: 0 | H120: 0 | I120: 0 | J120: 13.378458 | K120: 19.216281 | L120: 11.083541 | M120: 8.8619166
C121: 0 | D121: 0 | E121: 0 | F121: 0 | G121: 0 | H121: 0 | I121: 0 | J121: 0 | K121: 13.83017 | L121: 19.655189 | M121: 11.347409
C122: 0 | D122: 0 | E122: 0 | F122: 0 | G122: 0 | H122: 0 | I122: 0 | J122: 0 | K122: 0 | L122: 14.308148 | M122: 20.263673
C123: 0 | D123: 0 | E123: 0 | F123: 0 | G123: 0 | H123: 0 | I123: 0 | J123: 0 | K123: 0 | L123: 0 | M123: 15.000353
A125: Offsets | C125: 38.674376 | D125: 39.52779 | E125: 41.076872 | F125: 42.599751 | G125: 44.250336 | H125: 45.889798 | I125: 47.685656 | J125: 49.520152 | K125: 51.424714 | L125: 53.397966 | M125: 55.443378
A127: Interest Rate Change | C127: =C81-C80 -> 0.1 | D127: =D81-D80 -> 0.1 | E127: =E81-E80 -> 0.1 | F127: =F81-F80 -> 0.1 | G127: =G81-G80 -> 0.1 | H127: =H81-H80 -> 0.1 | I127: =I81-I80 -> 0.1 | J127: =J81-J80 -> 0.1 | ... M127: =M81-M80 -> 0.1
A129: Interest Change Matrix | C129: 52.194 | D129: 72.44 | E129: 41.604 | F129: 33.166 | G129: 27.507 | H129: 24.802 | I129: 18.083 | J129: 16.269 | K129: 12.265 | L129: 12.07 | M129: 10.215
C130: 0 | D130: 54.98 | E130: 76.133 | F130: 43.307 | G130: 34.496 | H130: 28.579 | I130: 25.954 | J130: 19.027 | K130: 16.892 | L130: 12.59 | M130: 12.39
C131: 0 | D131: 0 | E131: 56.723 | F131: 80.096 | G131: 45.121 | H131: 35.912 | I131: 29.72 | J131: 27.184 | K131: 20.037 | L131: 17.55 | M131: 12.931
C132: 0 | D132: 0 | E132: 0 | F132: 60.441 | G132: 85.403 | H132: 48.331 | I132: 38.578 | J132: 31.995 | K132: 28.98 | L132: 21.3 | M132: 18.656
...

Sheet 5. Productivity_CBO
A1: This workbook supplements CBO’s report How Changes in Economic Conditions Might Affect the Federal Budget: 2025 to 2035.
A2: www.cbo.gov/publication/61198
A5: 5. Illustrative Scenario: How Productivity Growth That Was 0.1 Percentage Point Slower Each Year Than It Is in CBO’s Forecast Might Aﬀect the Federal Budget
A6: Billions of dollars
N8: Total
N9: 2026- | O9: 2026-
B10: 2024 | C10: 2025 | D10: 2026 | E10: 2027 | F10: 2028 | G10: 2029 | H10: 2030 | I10: 2031 | J10: 2032 | K10: 2033 | L10: 2034 | M10: 2035 | N10: 2030 | O10: 2035
A11: Changes in revenues | B11: n.a. | C11: -4.219 | D11: -11.04 | E11: -18.894 | F11: -27.509 | G11: -36.963 | H11: -47.412 | I11: -58.82 | J11: -71.374 | K11: -84.974 | L11: -99.661 | M11: -115.773 | N11: -141.818 | O11: -572.42
A13: Changes in outlays
A14: Mandatory outlays | B14: n.a. | C14: -0.023 | D14: -0.486 | E14: -1.061 | F14: -1.901 | G14: -2.476 | H14: -3.312 | I14: -4.229 | J14: -5.332 | K14: -6.691 | L14: -8.041 | M14: -9.694 | N14: -9.236 | O14: -43.223
A15: Discretionary outlaysa | B15: n.a. | C15: 0 | D15: 0 | E15: 0 | F15: 0 | G15: 0 | H15: 0 | I15: 0 | J15: 0 | K15: 0 | L15: 0 | M15: 0 | N15: 0 | O15: 0
A16: Net interest outlays
A17: Lower interest rates | B17: n.a. | C17: -0.596 | D17: -2.314 | E17: -4.533 | F17: -7.337 | G17: -10.657 | H17: -14.574 | I17: -18.938 | J17: -23.798 | K17: -28.932 | L17: -34.53 | M17: -40.346 | N17: -39.415 | O17: -185.959
A18: Debt service | B18: n.a. | C18: 0.038 | D18: 0.287 | E18: 0.675 | F18: 1.247 | G18: 2.007 | H18: 2.975 | I18: 4.15 | J18: 5.566 | K18: 7.239 | L18: 9.206 | M18: 11.455 | N18: 7.191 | O18: 44.807
B19: ____ | C19: ____ | D19: ____ | E19: ____ | F19: ____ | G19: ____ | H19: ____ | I19: ____ | J19: ____ | K19: ____ | L19: ____ | M19: ____ | N19: ____ | O19: ____
A20: Subtotal, net interest outlays | B20: n.a. | C20: -0.558 | D20: -2.027 | E20: -3.858 | F20: -6.09 | G20: -8.65 | H20: -11.599 | I20: -14.788 | J20: -18.232 | K20: -21.693 | L20: -25.324 | M20: -28.891 | N20: -32.224 | O20: -141.152
A22: Total change in outlays | B22: n.a. | C22: -0.581 | D22: -2.513 | E22: -4.919 | F22: -7.991 | G22: -11.126 | H22: -14.911 | I22: -19.017 | J22: -23.564 | K22: -28.384 | L22: -33.365 | M22: -38.585 | N22: -41.46 | O22: -184.375
A24: Increase (-) or decrease in the deficit relative to CBO’s baseline | B24: n.a. | C24: -3.638 | D24: -8.527 | E24: -13.975 | F24: -19.518 | G24: -25.837 | H24: -32.501 | I24: -39.803 | J24: -47.81 | K24: -56.59 | L24: -66.296 | M24: -77.188 | N24: -100.358 | O24: -388.045
A26: Deficit (-) or surplus
A27: January 2025 baseline | B27: -1832.381 | C27: -1865.251 | D27: -1713.258 | E27: -1686.942 | F27: -1910.776 | G27: -1938.268 | H27: -2139.721 | I27: -2232.786 | J27: -2370.582 | K27: -2637.299 | L27: -2597.25 | M27: -2531.378 | N27: -9388.965 | O27: -21758.26
A28: CBO’s illustrative scenario | B28: -1832.381 | C28: -1868.889 | D28: -1721.785 | E28: -1700.917 | F28: -1930.294 | G28: -1964.105 | H28: -2172.222 | I28: -2272.589 | J28: -2418.392 | K28: -2693.889 | L28: -2663.546 | M28: -2608.566 | N28: -9489.323 | O28: -22146.305
A30: Debt held by the public
A31: January 2025 baseline | B31: 28199.313 | C31: 30102.749 | D31: 31882.633 | E31: 33636.105 | F31: 35600.64 | G31: 37580.5 | H31: 39747.651 | I31: 41992.385 | J31: 44371.755 | K31: 46985.029 | L31: 49555.504 | M31: 52055.866 | N31: n.a. | O31: n.a.
A32: CBO’s illustrative scenario | B32: 28199.313 | C32: 30106.387 | D32: 31894.798 | E32: 33662.245 | F32: 35646.298 | G32: 37651.995 | H32: 39851.647 | I32: 42136.184 | J32: 44563.364 | K32: 47233.228 | L32: 49869.999 | M32: 52447.549 | N32: n.a. | O32: n.a.
A34: Deficit (-) or surplus (percentage of GDP)
A35: January 2025 baseline | B35: -6.3562158 | C35: -6.1894147 | D35: -5.4664504 | E35: -5.184518 | F35: -5.659123 | G35: -5.5304586 | H35: -5.8793652 | I35: -5.9080768 | J35: -6.0393242 | K35: -6.4690633 | L35: -6.1356563 | M35: -5.7614482 | N35: -5.5528141 | O35: -5.830748
A36: CBO’s illustrative scenario | B36: -6.3562158 | C36: -6.207 | D36: -5.504 | E36: -5.244 | F36: -5.741 | G36: -5.635 | H36: -6.009 | I36: -6.062 | J36: -6.219 | K36: -6.679 | L36: -6.369 | M36: -6.018 | N36: -5.637 | O36: -5.982
A38: Debt held by the public (percentage of GDP)
A39: January 2025 baseline | B39: 97.818585 | C39: 99.889183 | D39: 101.72714 | E39: 103.37462 | F39: 105.438 | G39: 107.22841 | H39: 109.21562 | I39: 111.1142 | J39: 113.04204 | K39: 115.25016 | L39: 117.06826 | M39: 118.47981 | N39: n.a. | O39: n.a.
A40: CBO’s illustrative scenario | B40: 97.818585 | C40: 99.983 | D40: 101.964 | E40: 103.775 | F40: 106.026 | G40: 108.026 | H40: 110.245 | I40: 112.396 | J40: 114.6 | K40: 117.109 | L40: 119.247 | M40: 120.997 | N40: n.a. | O40: n.a.
B43: Economic indicators in CBO’s January 2025 baseline and under the illustrative scenario
B45: 2024 | C45: 2025 | D45: 2026 | E45: 2027 | F45: 2028 | G45: 2029 | H45: 2030 | I45: 2031 | J45: 2032 | K45: 2033 | L45: 2034 | M45: 2035
A46: Real GDP growth (percent)
A47: January 2025 baseline | B47: 2.734 | C47: 2.124 | D47: 1.827 | E47: 1.763 | F47: 1.744 | G47: 1.786 | H47: 1.821 | I47: 1.822 | J47: 1.842 | K47: 1.826 | L47: 1.797 | M47: 1.76
A48: CBO’s illustrative scenario | B48: 2.734 | C48: 2.014 | D48: 1.713 | E48: 1.645 | F48: 1.623 | G48: 1.661 | H48: 1.693 | I48: 1.69 | J48: 1.707 | K48: 1.688 | L48: 1.656 | M48: 1.615
A49: Real GDP (billions of 2017 dollars)
A50: January 2025 baseline | B50: 23290.9 | C50: 23785.8 | D50: 24220.5 | E50: 24647.6 | F50: 25077.7 | G50: 25525.6 | H50: 25990.7 | I50: 26464.3 | J50: 26952 | K50: 27444.4 | L50: 27937.8 | M50: 28429.6
A51: CBO’s illustrative scenario | B51: 23290.9 | C51: 23760 | D51: 24167 | E51: 24564.6 | F51: 24963.3 | G51: 25377.9 | H51: 25807.6 | I51: 26243.8 | J51: 26691.9 | K51: 27142.5 | L51: 27592.1 | M51: 28037.8
A52: Nominal GDP (billions of dollars)
A53: January 2025 baseline | B53: 29166.2 | C53: 30441.1 | D53: 31640.6 | E53: 32841 | F53: 34078.4 | G53: 35378.4 | H53: 36738.8 | I53: 38151.3 | J53: 39626.7 | K53: 41154.2 | L53: 42727.6 | M53: 44345.4
A54: CBO’s illustrative scenario | B54: 29166.2 | C54: 30408.1 | D54: 31570.7 | E54: 32730.4 | F54: 33922.9 | G54: 35173.7 | H54: 36480 | I54: 37833.4 | J54: 39244.3 | K54: 40701.5 | L54: 42198.9 | M54: 43734.3
A55: Nominal GDP (billions of dollars, by fiscal year)
A56: January 2025 baseline | B56: 28823 | C56: 30136.1 | D56: 31341.3 | E56: 32538.1 | F56: 33764.5 | G56: 35047.1 | H56: 36393.7 | I56: 37792.1 | J56: 39252.4 | K56: 40767.9 | L56: 42330.4 | M56: 43936.5
A57: CBO’s illustrative scenario | B57: 28823 | C57: 30111.4 | D57: 31280.6 | E57: 32437.7 | F57: 33620.2 | G57: 34854.7 | H57: 36148.4 | I57: 37489 | J57: 38886.1 | K57: 40332.8 | L57: 41820.7 | M57: 43346
A58: Labor force (millions of people)
A59: January 2025 baseline | B59: 168.243 | C59: 170.662 | D59: 173.375 | E59: 174.006 | F59: 174.614 | G59: 175.295 | H59: 176.03 | I59: 176.801 | J59: 177.558 | K59: 178.176 | L59: 178.795 | M59: 179.386
A60: CBO’s illustrative scenario | B60: 168.243 | C60: 170.634 | D60: 173.316 | E60: 173.892 | F60: 174.491 | G60: 175.139 | H60: 175.839 | I60: 176.574 | J60: 177.294 | K60: 177.874 | L60: 178.454 | M60: 179.005
A61: Interest rate on 10-year Treasury notes (percent)
A62: January 2025 baseline | B62: 4.188 | C62: 4.093 | D62: 3.935 | E62: 3.914 | F62: 3.894 | G62: 3.871 | H62: 3.85 | I62: 3.836 | J62: 3.826 | K62: 3.815 | L62: 3.797 | M62: 3.772
A63: CBO’s illustrative scenario | B63: 4.188 | C63: 4.081 | D63: 3.911 | E63: 3.879 | F63: 3.848 | G63: 3.815 | H63: 3.784 | I63: 3.761 | J63: 3.742 | K63: 3.722 | L63: 3.696 | M63: 3.663
A64: Inflation (percent)b
A65: January 2025 baseline | B65: 2.413 | C65: 2.198 | D65: 2.075 | E65: 1.995 | F65: 1.988 | G65: 1.992 | H65: 1.987 | I65: 1.986 | J65: 1.987 | K65: 1.991 | L65: 1.989 | M65: 1.99
A66: CBO’s illustrative scenario | B66: 2.413 | C66: 2.198 | D66: 2.075 | E66: 1.995 | F66: 1.988 | G66: 1.992 | H66: 1.987 | I66: 1.986 | J66: 1.987 | K66: 1.991 | L66: 1.989 | M66: 1.99
A67: GDP price index (2017 = 100)
A68: January 2025 baseline | B68: 125.223 | C68: 127.976 | D68: 130.631 | E68: 133.238 | F68: 135.887 | G68: 138.595 | H68: 141.349 | I68: 144.157 | J68: 147.023 | K68: 149.95 | L68: 152.934 | M68: 155.979
A69: CBO’s illustrative scenario | B69: 125.223 | C69: 127.976 | D69: 130.631 | E69: 133.238 | F69: 135.887 | G69: 138.595 | H69: 141.349 | I69: 144.157 | J69: 147.023 | K69: 149.95 | L69: 152.934 | M69: 155.979
A70: Employment cost index (December 2005 = 100)c
A71: January 2025 baseline | B71: 168.291 | C71: 174.156 | D71: 180 | E71: 185.768 | F71: 191.526 | G71: 197.325 | H71: 203.213 | I71: 209.221 | J71: 215.381 | K71: 221.716 | L71: 228.225 | M71: 234.91
A72: CBO’s illustrative scenario | B72: 168.291 | C72: 173.996 | D72: 179.663 | E72: 185.264 | F72: 190.786 | G72: 196.358 | H72: 202.001 | I72: 207.744 | J72: 213.62 | K72: 219.649 | L72: 225.832 | M72: 232.166
A75: Data source: Congressional Budget Office.
A77: Real values are nominal values that have been adjusted to remove the effects of changes in prices.
A79: Unless otherwise noted, economic indicators are calendar year averages.
A81: GDP = gross domestic product; n.a. = not applicable.
A83: a. Discretionary outlays do not change in this scenario.
A85: b. Measured using the GDP price index.
A87: c. The employment cost index for wages and salaries of workers in private industry.

Sheet 6. Labor Force_CBO
A1: This workbook supplements CBO’s report How Changes in Economic Conditions Might Affect the Federal Budget: 2025 to 2035.
A2: www.cbo.gov/publication/61198
A5: 6. Illustrative Scenario: How Labor Force Growth That Was 0.1 Percentage Point Slower Each Year Than It Is in CBO’s Forecast Might Aﬀect the Federal Budget
A6: Billions of dollars
N8: Total
N9: 2026- | O9: 2026-
B10: 2024 | C10: 2025 | D10: 2026 | E10: 2027 | F10: 2028 | G10: 2029 | H10: 2030 | I10: 2031 | J10: 2032 | K10: 2033 | L10: 2034 | M10: 2035 | N10: 2030 | O10: 2035
A11: Changes in revenues | B11: n.a. | C11: -1.649 | D11: -4.283 | E11: -7.2 | F11: -10.373 | G11: -13.878 | H11: -17.782 | I11: -22.053 | J11: -26.788 | K11: -31.961 | L11: -37.56 | M11: -43.764 | N11: -53.516 | O11: -215.642
A13: Changes in outlays
A14: Mandatory outlays | B14: n.a. | C14: 0.281 | D14: 0.74 | E14: 1.211 | F14: 1.733 | G14: 2.29 | H14: 2.856 | I14: 3.532 | J14: 4.482 | K14: 5.455 | L14: 6.303 | M14: 7.304 | N14: 8.83 | O14: 35.906
A15: Discretionary outlaysa | B15: n.a. | C15: 0 | D15: 0 | E15: 0 | F15: 0 | G15: 0 | H15: 0 | I15: 0 | J15: 0 | K15: 0 | L15: 0 | M15: 0 | N15: 0 | O15: 0
A16: Net interest outlays
A17: Lower interest rates | B17: n.a. | C17: -0.3 | D17: -1.101 | E17: -2.174 | F17: -3.507 | G17: -5.131 | H17: -7.009 | I17: -9.071 | J17: -11.442 | K17: -13.92 | L17: -16.604 | M17: -19.399 | N17: -18.922 | O17: -89.358
A18: Debt service | B18: n.a. | C18: 0.017 | D18: 0.138 | E18: 0.329 | F18: 0.609 | G18: 0.982 | H18: 1.457 | I18: 2.036 | J18: 2.743 | K18: 3.591 | L18: 4.593 | M18: 5.776 | N18: 3.515 | O18: 22.254
B19: ____ | C19: ____ | D19: ____ | E19: ____ | F19: ____ | G19: ____ | H19: ____ | I19: ____ | J19: ____ | K19: ____ | L19: ____ | M19: ____ | N19: ____ | O19: ____
A20: Subtotal, net interest outlays | B20: n.a. | C20: -0.283 | D20: -0.963 | E20: -1.845 | F20: -2.898 | G20: -4.149 | H20: -5.552 | I20: -7.035 | J20: -8.699 | K20: -10.329 | L20: -12.011 | M20: -13.623 | N20: -15.407 | O20: -67.104
A22: Total change in outlays | B22: n.a. | C22: -0.002 | D22: -0.223 | E22: -0.634 | F22: -1.165 | G22: -1.859 | H22: -2.696 | I22: -3.503 | J22: -4.217 | K22: -4.874 | L22: -5.708 | M22: -6.319 | N22: -6.577 | O22: -31.198
A24: Increase (-) or decrease in the deficit relative to CBO’s baseline | B24: n.a. | C24: -1.647 | D24: -4.06 | E24: -6.566 | F24: -9.208 | G24: -12.019 | H24: -15.086 | I24: -18.55 | J24: -22.571 | K24: -27.087 | L24: -31.852 | M24: -37.445 | N24: -46.939 | O24: -184.444
A26: Deficit (-) or surplus
A27: January 2025 baseline | B27: -1832.381 | C27: -1865.251 | D27: -1713.258 | E27: -1686.942 | F27: -1910.776 | G27: -1938.268 | H27: -2139.721 | I27: -2232.786 | J27: -2370.582 | K27: -2637.299 | L27: -2597.25 | M27: -2531.378 | N27: -9388.965 | O27: -21758.26
A28: CBO’s illustrative scenario | B28: -1832.381 | C28: -1866.898 | D28: -1717.318 | E28: -1693.508 | F28: -1919.984 | G28: -1950.287 | H28: -2154.807 | I28: -2251.336 | J28: -2393.153 | K28: -2664.386 | L28: -2629.102 | M28: -2568.823 | N28: -9435.904 | O28: -21942.704
A30: Debt held by the public
A31: January 2025 baseline | B31: 28199.313 | C31: 30102.749 | D31: 31882.633 | E31: 33636.105 | F31: 35600.64 | G31: 37580.5 | H31: 39747.651 | I31: 41992.385 | J31: 44371.755 | K31: 46985.029 | L31: 49555.504 | M31: 52055.866 | N31: n.a. | O31: n.a.
A32: CBO’s illustrative scenario | B32: 28199.313 | C32: 30104.396 | D32: 31888.34 | E32: 33648.378 | F32: 35622.121 | G32: 37614 | H32: 39796.237 | I32: 42059.521 | J32: 44461.462 | K32: 47101.823 | L32: 49704.15 | M32: 52241.957 | N32: n.a. | O32: n.a.
A34: Deficit (-) or surplus (percentage of GDP)
A35: January 2025 baseline | B35: -6.3562158 | C35: -6.1894147 | D35: -5.4664504 | E35: -5.184518 | F35: -5.659123 | G35: -5.5304586 | H35: -5.8793652 | I35: -5.9080768 | J35: -6.0393242 | K35: -6.4690633 | L35: -6.1356563 | M35: -5.7614482 | N35: -5.5528141 | O35: -5.830748
A36: CBO’s illustrative scenario | B36: -6.3562158 | C36: -6.197 | D36: -5.484 | E36: -5.212 | F36: -5.698 | G36: -5.579 | H36: -5.94 | I36: -5.98 | J36: -6.124 | K36: -6.569 | L36: -6.247 | M36: -5.885 | N36: -5.592 | O36: -5.903
A38: Debt held by the public (percentage of GDP)
A39: January 2025 baseline | B39: 97.818585 | C39: 99.889183 | D39: 101.72714 | E39: 103.37462 | F39: 105.438 | G39: 107.22841 | H39: 109.21562 | I39: 111.1142 | J39: 113.04204 | K39: 115.25016 | L39: 117.06826 | M39: 118.47981 | N39: n.a. | O39: n.a.
A40: CBO’s illustrative scenario | B40: 97.818585 | C40: 99.934 | D40: 101.839 | E40: 103.565 | F40: 105.719 | G40: 107.608 | H40: 109.705 | I40: 111.723 | J40: 113.782 | K40: 116.133 | L40: 118.105 | M40: 119.679 | N40: n.a. | O40: n.a.
B43: Economic indicators in CBO’s January 2025 baseline and under the illustrative scenario
B45: 2024 | C45: 2025 | D45: 2026 | E45: 2027 | F45: 2028 | G45: 2029 | H45: 2030 | I45: 2031 | J45: 2032 | K45: 2033 | L45: 2034 | M45: 2035
A46: Real GDP growth (percent)
A47: January 2025 baseline | B47: 2.734 | C47: 2.124 | D47: 1.827 | E47: 1.763 | F47: 1.744 | G47: 1.786 | H47: 1.821 | I47: 1.822 | J47: 1.842 | K47: 1.826 | L47: 1.797 | M47: 1.76
A48: CBO’s illustrative scenario | B48: 2.734 | C48: 2.072 | D48: 1.773 | E48: 1.706 | F48: 1.686 | G48: 1.726 | H48: 1.76 | I48: 1.759 | J48: 1.778 | K48: 1.761 | L48: 1.73 | M48: 1.691
A49: Real GDP (billions of 2017 dollars)
A50: January 2025 baseline | B50: 23290.9 | C50: 23785.8 | D50: 24220.5 | E50: 24647.6 | F50: 25077.7 | G50: 25525.6 | H50: 25990.7 | I50: 26464.3 | J50: 26952 | K50: 27444.4 | L50: 27937.8 | M50: 28429.6
A51: CBO’s illustrative scenario | B51: 23290.9 | C51: 23773.5 | D51: 24195 | E51: 24607.8 | F51: 25022.7 | G51: 25454.5 | H51: 25902.5 | I51: 26358.1 | J51: 26826.7 | K51: 27299 | L51: 27771.2 | M51: 28240.8
A52: Nominal GDP (billions of dollars)
A53: January 2025 baseline | B53: 29166.2 | C53: 30441.1 | D53: 31640.6 | E53: 32841 | F53: 34078.4 | G53: 35378.4 | H53: 36738.8 | I53: 38151.3 | J53: 39626.7 | K53: 41154.2 | L53: 42727.6 | M53: 44345.4
A54: CBO’s illustrative scenario | B54: 29166.2 | C54: 30425.4 | D54: 31607.3 | E54: 32788 | F54: 34003.7 | G54: 35279.9 | H54: 36614.1 | I54: 37998.2 | J54: 39442.5 | K54: 40936.2 | L54: 42472.8 | M54: 44050.9
A55: Nominal GDP (billions of dollars, by fiscal year)
A56: January 2025 baseline | B56: 28823 | C56: 30136.1 | D56: 31341.3 | E56: 32538.1 | F56: 33764.5 | G56: 35047.1 | H56: 36393.7 | I56: 37792.1 | J56: 39252.4 | K56: 40767.9 | L56: 42330.4 | M56: 43936.5
A57: CBO’s illustrative scenario | B57: 28823 | C57: 30124.3 | D57: 31312.4 | E57: 32490 | F57: 33695.2 | G57: 34954.6 | H57: 36275.6 | I57: 37646.1 | J57: 39076 | K57: 40558.4 | L57: 42084.8 | M57: 43651.9
A58: Labor force (millions of people)
A59: January 2025 baseline | B59: 168.243 | C59: 170.662 | D59: 173.375 | E59: 174.006 | F59: 174.614 | G59: 175.295 | H59: 176.03 | I59: 176.801 | J59: 177.558 | K59: 178.176 | L59: 178.795 | M59: 179.386
A60: CBO’s illustrative scenario | B60: 168.243 | C60: 170.505 | D60: 173.055 | E60: 173.521 | F60: 173.963 | G60: 174.477 | H60: 175.043 | I60: 175.643 | J60: 176.228 | K60: 176.674 | L60: 177.119 | M60: 177.536
A61: Interest rate on 10-year Treasury notes (percent)
A62: January 2025 baseline | B62: 4.188 | C62: 4.093 | D62: 3.935 | E62: 3.914 | F62: 3.894 | G62: 3.871 | H62: 3.85 | I62: 3.836 | J62: 3.826 | K62: 3.815 | L62: 3.797 | M62: 3.772
A63: CBO’s illustrative scenario | B63: 4.188 | C63: 4.087 | D63: 3.924 | E63: 3.897 | F63: 3.872 | G63: 3.844 | H63: 3.818 | I63: 3.8 | J63: 3.786 | K63: 3.77 | L63: 3.749 | M63: 3.72
A64: Inflation (percent)b
A65: January 2025 baseline | B65: 2.413 | C65: 2.198 | D65: 2.075 | E65: 1.995 | F65: 1.988 | G65: 1.992 | H65: 1.987 | I65: 1.986 | J65: 1.987 | K65: 1.991 | L65: 1.989 | M65: 1.99
A66: CBO’s illustrative scenario | B66: 2.413 | C66: 2.198 | D66: 2.075 | E66: 1.995 | F66: 1.988 | G66: 1.992 | H66: 1.987 | I66: 1.986 | J66: 1.987 | K66: 1.991 | L66: 1.989 | M66: 1.99
A67: GDP price index (2017 = 100)
A68: January 2025 baseline | B68: 125.223 | C68: 127.976 | D68: 130.631 | E68: 133.238 | F68: 135.887 | G68: 138.595 | H68: 141.349 | I68: 144.157 | J68: 147.023 | K68: 149.95 | L68: 152.934 | M68: 155.979
A69: CBO’s illustrative scenario | B69: 125.223 | C69: 127.976 | D69: 130.631 | E69: 133.238 | F69: 135.887 | G69: 138.595 | H69: 141.349 | I69: 144.157 | J69: 147.023 | K69: 149.95 | L69: 152.934 | M69: 155.979
A70: Employment cost index (December 2005 = 100)c
A71: January 2025 baseline | B71: 168.291 | C71: 174.156 | D71: 180 | E71: 185.768 | F71: 191.526 | G71: 197.325 | H71: 203.213 | I71: 209.221 | J71: 215.381 | K71: 221.716 | L71: 228.225 | M71: 234.91
A72: CBO’s illustrative scenario | B72: 168.291 | C72: 174.226 | D72: 180.143 | E72: 185.987 | F72: 191.821 | G72: 197.698 | H72: 203.665 | I72: 209.755 | J72: 215.998 | K72: 222.416 | L72: 229.011 | M72: 235.782
A75: Data source: Congressional Budget Office.
A77: Real values are nominal values that have been adjusted to remove the effects of changes in prices.
A79: Unless otherwise noted, economic indicators are calendar year averages.
A81: GDP = gross domestic product; n.a. = not applicable.
A83: a. Discretionary outlays do not change in this scenario.
A85: b. Measured using the GDP price index.
A87: c. The employment cost index for wages and salaries of workers in private industry.

Sheet 7. Interest Rates_CBO
A1: This workbook supplements CBO’s report How Changes in Economic Conditions Might Affect the Federal Budget: 2025 to 2035.
A2: www.cbo.gov/publication/61198
A5: 7. Illustrative Scenario: How Interest Rates That Were 0.1 Percentage Point Higher Each Year Than They Are in CBO’s Forecast Might Aﬀect the Federal Budget
A6: Billions of dollars
N8: Total
N9: 2026- | O9: 2026-
B10: 2024 | C10: 2025 | D10: 2026 | E10: 2027 | F10: 2028 | G10: 2029 | H10: 2030 | I10: 2031 | J10: 2032 | K10: 2033 | L10: 2034 | M10: 2035 | N10: 2030 | O10: 2035
A11: Changes in revenues | B11: n.a. | C11: -2.563 | D11: -2.565 | E11: -1.678 | F11: -0.88 | G11: -0.173 | H11: 0.5 | I11: 1.011 | J11: 1.513 | K11: 1.933 | L11: 2.289 | M11: 2.635 | N11: -4.796 | O11: 4.585
A13: Changes in outlays
A14: Mandatory outlays | B14: n.a. | C14: 0 | D14: 0 | E14: 0 | F14: 0 | G14: 0 | H14: 0 | I14: 0 | J14: 0 | K14: 0 | L14: 0 | M14: 0 | N14: 0 | O14: 0
A15: Discretionary outlaysa | B15: n.a. | C15: 0 | D15: 0 | E15: 0 | F15: 0 | G15: 0 | H15: 0 | I15: 0 | J15: 0 | K15: 0 | L15: 0 | M15: 0 | N15: 0 | O15: 0
A16: Net interest outlays
A17: Higher interest rates | B17: n.a. | C17: 5.219 | D17: 12.742 | E17: 17.446 | F17: 21.701 | G17: 25.642 | H17: 29.476 | I17: 32.842 | J17: 36.317 | K17: 39.377 | L17: 42.587 | M17: 45.526 | N17: 107.007 | O17: 303.656
A18: Debt service | B18: n.a. | C18: 0.083 | D18: 0.593 | E18: 1.239 | F18: 2.035 | G18: 2.966 | H18: 4.043 | I18: 5.24 | J18: 6.579 | K18: 8.05 | L18: 9.66 | M18: 11.428 | N18: 10.876 | O18: 51.833
B19: ____ | C19: ____ | D19: ____ | E19: ____ | F19: ____ | G19: ____ | H19: ____ | I19: ____ | J19: ____ | K19: ____ | L19: ____ | M19: ____ | N19: ____ | O19: ____
A20: Subtotal, net interest outlays | B20: n.a. | C20: 5.302 | D20: 13.335 | E20: 18.685 | F20: 23.736 | G20: 28.608 | H20: 33.519 | I20: 38.082 | J20: 42.896 | K20: 47.427 | L20: 52.247 | M20: 56.954 | N20: 117.883 | O20: 355.489
A22: Total change in outlays | B22: n.a. | C22: 5.302 | D22: 13.335 | E22: 18.685 | F22: 23.736 | G22: 28.608 | H22: 33.519 | I22: 38.082 | J22: 42.896 | K22: 47.427 | L22: 52.247 | M22: 56.954 | N22: 117.883 | O22: 355.489
A24: Increase (-) or decrease in the deficit relative to CBO’s baseline | B24: n.a. | C24: -7.865 | D24: -15.9 | E24: -20.363 | F24: -24.616 | G24: -28.781 | H24: -33.019 | I24: -37.071 | J24: -41.383 | K24: -45.494 | L24: -49.958 | M24: -54.319 | N24: -122.679 | O24: -350.904
A26: Deficit (-) or surplus
A27: January 2025 baseline | B27: -1832.381 | C27: -1865.251 | D27: -1713.258 | E27: -1686.942 | F27: -1910.776 | G27: -1938.268 | H27: -2139.721 | I27: -2232.786 | J27: -2370.582 | K27: -2637.299 | L27: -2597.25 | M27: -2531.378 | N27: -9388.965 | O27: -21758.26
A28: CBO’s illustrative scenario | B28: -1832.381 | C28: -1873.116 | D28: -1729.158 | E28: -1707.305 | F28: -1935.392 | G28: -1967.049 | H28: -2172.74 | I28: -2269.857 | J28: -2411.965 | K28: -2682.793 | L28: -2647.208 | M28: -2585.697 | N28: -9511.644 | O28: -22109.164
A30: Debt held by the public
A31: January 2025 baseline | B31: 28199.313 | C31: 30102.749 | D31: 31882.633 | E31: 33636.105 | F31: 35600.64 | G31: 37580.5 | H31: 39747.651 | I31: 41992.385 | J31: 44371.755 | K31: 46985.029 | L31: 49555.504 | M31: 52055.866 | N31: n.a. | O31: n.a.
A32: CBO’s illustrative scenario | B32: 28199.313 | C32: 30110.614 | D32: 31906.398 | E32: 33680.233 | F32: 35669.384 | G32: 37678.025 | H32: 39878.195 | I32: 42160 | J32: 44580.753 | K32: 47239.521 | L32: 49859.954 | M32: 52414.635 | N32: n.a. | O32: n.a.
A34: Deficit (-) or surplus (percentage of GDP)
A35: January 2025 baseline | B35: -6.3562158 | C35: -6.1894147 | D35: -5.4664504 | E35: -5.184518 | F35: -5.659123 | G35: -5.5304586 | H35: -5.8793652 | I35: -5.9080768 | J35: -6.0393242 | K35: -6.4690633 | L35: -6.1356563 | M35: -5.7614482 | N35: -5.5528141 | O35: -5.830748
A36: CBO’s illustrative scenario | B36: -6.3562158 | C36: -6.216 | D36: -5.517 | E36: -5.247 | F36: -5.732 | G36: -5.613 | H36: -5.97 | I36: -6.006 | J36: -6.145 | K36: -6.581 | L36: -6.254 | M36: -5.885 | N36: -5.625 | O36: -5.925
A38: Debt held by the public (percentage of GDP)
A39: January 2025 baseline | B39: 97.818585 | C39: 99.889183 | D39: 101.72714 | E39: 103.37462 | F39: 105.438 | G39: 107.22841 | H39: 109.21562 | I39: 111.1142 | J39: 113.04204 | K39: 115.25016 | L39: 117.06826 | M39: 118.47981 | N39: n.a. | O39: n.a.
A40: CBO’s illustrative scenario | B40: 97.818585 | C40: 99.915 | D40: 101.803 | E40: 103.51 | F40: 105.642 | G40: 107.507 | H40: 109.574 | I40: 111.558 | J40: 113.575 | K40: 115.874 | L40: 117.788 | M40: 119.296 | N40: n.a. | O40: n.a.
B43: Economic indicators in CBO’s January 2025 baseline and under the illustrative scenario
B45: 2024 | C45: 2025 | D45: 2026 | E45: 2027 | F45: 2028 | G45: 2029 | H45: 2030 | I45: 2031 | J45: 2032 | K45: 2033 | L45: 2034 | M45: 2035
A46: Real GDP growth (percent)
A47: January 2025 baseline | B47: 2.734 | C47: 2.124 | D47: 1.827 | E47: 1.763 | F47: 1.744 | G47: 1.786 | H47: 1.821 | I47: 1.822 | J47: 1.842 | K47: 1.826 | L47: 1.797 | M47: 1.76
A48: CBO’s illustrative scenario | B48: 2.734 | C48: 2.124 | D48: 1.827 | E48: 1.763 | F48: 1.744 | G48: 1.786 | H48: 1.821 | I48: 1.822 | J48: 1.842 | K48: 1.826 | L48: 1.797 | M48: 1.76
A49: Real GDP (billions of 2017 dollars)
A50: January 2025 baseline | B50: 23290.9 | C50: 23785.8 | D50: 24220.5 | E50: 24647.6 | F50: 25077.7 | G50: 25525.6 | H50: 25990.7 | I50: 26464.3 | J50: 26952 | K50: 27444.4 | L50: 27937.8 | M50: 28429.6
A51: CBO’s illustrative scenario | B51: 23290.9 | C51: 23785.8 | D51: 24220.5 | E51: 24647.6 | F51: 25077.7 | G51: 25525.6 | H51: 25990.7 | I51: 26464.3 | J51: 26952 | K51: 27444.4 | L51: 27937.8 | M51: 28429.6
A52: Nominal GDP (billions of dollars)
A53: January 2025 baseline | B53: 29166.2 | C53: 30441.1 | D53: 31640.6 | E53: 32841 | F53: 34078.4 | G53: 35378.4 | H53: 36738.8 | I53: 38151.3 | J53: 39626.7 | K53: 41154.2 | L53: 42727.6 | M53: 44345.4
A54: CBO’s illustrative scenario | B54: 29166.2 | C54: 30441.1 | D54: 31640.6 | E54: 32841 | F54: 34078.4 | G54: 35378.4 | H54: 36738.8 | I54: 38151.3 | J54: 39626.7 | K54: 41154.2 | L54: 42727.6 | M54: 44345.4
A55: Nominal GDP (billions of dollars, by fiscal year)
A56: January 2025 baseline | B56: 28823 | C56: 30136.1 | D56: 31341.3 | E56: 32538.1 | F56: 33764.5 | G56: 35047.1 | H56: 36393.7 | I56: 37792.1 | J56: 39252.4 | K56: 40767.9 | L56: 42330.4 | M56: 43936.5
A57: CBO’s illustrative scenario | B57: 28823 | C57: 30136.1 | D57: 31341.3 | E57: 32538.1 | F57: 33764.5 | G57: 35047.1 | H57: 36393.7 | I57: 37792.1 | J57: 39252.4 | K57: 40767.9 | L57: 42330.4 | M57: 43936.5
A58: Labor force (millions of people)
A59: January 2025 baseline | B59: 168.243 | C59: 170.662 | D59: 173.375 | E59: 174.006 | F59: 174.614 | G59: 175.295 | H59: 176.03 | I59: 176.801 | J59: 177.558 | K59: 178.176 | L59: 178.795 | M59: 179.386
A60: CBO’s illustrative scenario | B60: 168.243 | C60: 170.662 | D60: 173.375 | E60: 174.006 | F60: 174.614 | G60: 175.295 | H60: 176.03 | I60: 176.801 | J60: 177.558 | K60: 178.176 | L60: 178.795 | M60: 179.386
A61: Interest rate on 10-year Treasury notes (percent)
A62: January 2025 baseline | B62: 4.188 | C62: 4.093 | D62: 3.935 | E62: 3.914 | F62: 3.894 | G62: 3.871 | H62: 3.85 | I62: 3.836 | J62: 3.826 | K62: 3.815 | L62: 3.797 | M62: 3.772
A63: CBO’s illustrative scenario | B63: 4.188 | C63: 4.193 | D63: 4.035 | E63: 4.014 | F63: 3.994 | G63: 3.971 | H63: 3.95 | I63: 3.936 | J63: 3.926 | K63: 3.915 | L63: 3.897 | M63: 3.872
A64: Inflation (percent)b
A65: January 2025 baseline | B65: 2.413 | C65: 2.198 | D65: 2.075 | E65: 1.995 | F65: 1.988 | G65: 1.992 | H65: 1.987 | I65: 1.986 | J65: 1.987 | K65: 1.991 | L65: 1.989 | M65: 1.99
A66: CBO’s illustrative scenario | B66: 2.413 | C66: 2.198 | D66: 2.075 | E66: 1.995 | F66: 1.988 | G66: 1.992 | H66: 1.987 | I66: 1.986 | J66: 1.987 | K66: 1.991 | L66: 1.989 | M66: 1.99
A67: GDP price index (2017 = 100)
A68: January 2025 baseline | B68: 125.223 | C68: 127.976 | D68: 130.631 | E68: 133.238 | F68: 135.887 | G68: 138.595 | H68: 141.349 | I68: 144.157 | J68: 147.023 | K68: 149.95 | L68: 152.934 | M68: 155.979
A69: CBO’s illustrative scenario | B69: 125.223 | C69: 127.976 | D69: 130.631 | E69: 133.238 | F69: 135.887 | G69: 138.595 | H69: 141.349 | I69: 144.157 | J69: 147.023 | K69: 149.95 | L69: 152.934 | M69: 155.979
A70: Employment cost index (December 2005 = 100)c
A71: January 2025 baseline | B71: 168.291 | C71: 174.156 | D71: 180 | E71: 185.768 | F71: 191.526 | G71: 197.325 | H71: 203.213 | I71: 209.221 | J71: 215.381 | K71: 221.716 | L71: 228.225 | M71: 234.91
A72: CBO’s illustrative scenario | B72: 168.291 | C72: 174.156 | D72: 180 | E72: 185.768 | F72: 191.526 | G72: 197.325 | H72: 203.213 | I72: 209.221 | J72: 215.381 | K72: 221.716 | L72: 228.225 | M72: 234.91
A75: Data source: Congressional Budget Office.
A77: Real values are nominal values that have been adjusted to remove the effects of changes in prices.
A79: Unless otherwise noted, economic indicators are calendar year averages.
A81: GDP = gross domestic product; n.a. = not applicable.
A83: a. Discretionary outlays do not change in this scenario.
A85: b. Measured using the GDP price index.
A87: c. The employment cost index for wages and salaries of workers in private industry.

Sheet 8. Inflation and Interest_CBO
A1: This workbook supplements CBO’s report How Changes in Economic Conditions Might Affect the Federal Budget: 2025 to 2035.
A2: www.cbo.gov/publication/61198
A5: 8. Illustrative Scenario: How Inflation and Interest Rates That Were 0.1 Percentage Point Higher Each Year Than They Are in CBO’s Forecast Might Aﬀect the Federal Budget
A6: Billions of dollars
N8: Total
N9: 2026- | O9: 2026-
B10: 2024 | C10: 2025 | D10: 2026 | E10: 2027 | F10: 2028 | G10: 2029 | H10: 2030 | I10: 2031 | J10: 2032 | K10: 2033 | L10: 2034 | M10: 2035 | N10: 2030 | O10: 2035
A11: Changes in revenues | B11: n.a. | C11: 1.559 | D11: 7.261 | E11: 13.503 | F11: 19.902 | G11: 26.691 | H11: 33.925 | I11: 41.556 | J11: 49.813 | K11: 58.187 | L11: 67.451 | M11: 77.183 | N11: 101.282 | O11: 395.472
A13: Changes in outlays
A14: Mandatory outlays | B14: n.a. | C14: 0.403 | D14: 3.296 | E14: 7.126 | F14: 11.473 | G14: 16.016 | H14: 21.023 | I14: 26.272 | J14: 32.243 | K14: 39.043 | L14: 45.333 | M14: 51.832 | N14: 58.934 | O14: 253.657
A15: Discretionary outlays | B15: n.a. | C15: 0 | D15: 1.088 | E15: 2.665 | F15: 4.464 | G15: 6.421 | H15: 8.545 | I15: 10.748 | J15: 13.046 | K15: 15.442 | L15: 17.94 | M15: 20.545 | N15: 23.183 | O15: 100.904
A16: Net interest outlays
A17: Higher interest rates | B17: n.a. | C17: 5.219 | D17: 12.742 | E17: 17.446 | F17: 21.701 | G17: 25.642 | H17: 29.476 | I17: 32.842 | J17: 36.317 | K17: 39.377 | L17: 42.587 | M17: 45.526 | N17: 107.007 | O17: 303.656
A18: Higher inflationa | B18: n.a. | C18: 2.059 | D18: 1.801 | E18: 1.736 | F18: 1.603 | G18: 1.466 | H18: 1.4 | I18: 1.412 | J18: 1.421 | K18: 1.435 | L18: 1.446 | M18: 1.52 | N18: 8.006 | O18: 15.24
A19: Debt service | B19: n.a. | C19: 0.066 | D19: 0.459 | E19: 0.968 | F19: 1.632 | G19: 2.44 | H19: 3.403 | I19: 4.501 | J19: 5.753 | K19: 7.167 | L19: 8.737 | M19: 10.456 | N19: 8.902 | O19: 45.516
B20: ____ | C20: ____ | D20: ____ | E20: ____ | F20: ____ | G20: ____ | H20: ____ | I20: ____ | J20: ____ | K20: ____ | L20: ____ | M20: ____ | N20: ____ | O20: ____
A21: Subtotal, net interest outlays | B21: n.a. | C21: 7.344 | D21: 15.002 | E21: 20.15 | F21: 24.936 | G21: 29.548 | H21: 34.279 | I21: 38.755 | J21: 43.491 | K21: 47.979 | L21: 52.77 | M21: 57.502 | N21: 123.915 | O21: 364.412
A23: Total change in outlays | B23: n.a. | C23: 7.747 | D23: 19.386 | E23: 29.941 | F23: 40.873 | G23: 51.985 | H23: 63.847 | I23: 75.775 | J23: 88.78 | K23: 102.464 | L23: 116.043 | M23: 129.879 | N23: 206.032 | O23: 718.973
A25: Increase (-) or decrease in the deficit relative to CBO’s baseline | B25: n.a. | C25: -6.188 | D25: -12.125 | E25: -16.438 | F25: -20.971 | G25: -25.294 | H25: -29.922 | I25: -34.219 | J25: -38.967 | K25: -44.277 | L25: -48.592 | M25: -52.696 | N25: -104.75 | O25: -323.501
A27: Deficit (-) or surplus
A28: January 2025 baseline | B28: -1832.381 | C28: -1865.251 | D28: -1713.258 | E28: -1686.942 | F28: -1910.776 | G28: -1938.268 | H28: -2139.721 | I28: -2232.786 | J28: -2370.582 | K28: -2637.299 | L28: -2597.25 | M28: -2531.378 | N28: -9388.965 | O28: -21758.26
A29: CBO’s illustrative scenario | B29: -1832.381 | C29: -1871.439 | D29: -1725.383 | E29: -1703.38 | F29: -1931.747 | G29: -1963.562 | H29: -2169.643 | I29: -2267.005 | J29: -2409.549 | K29: -2681.576 | L29: -2645.842 | M29: -2584.074 | N29: -9493.715 | O29: -22081.761
A31: Debt held by the public
A32: January 2025 baseline | B32: 28199.313 | C32: 30102.749 | D32: 31882.633 | E32: 33636.105 | F32: 35600.64 | G32: 37580.5 | H32: 39747.651 | I32: 41992.385 | J32: 44371.755 | K32: 46985.029 | L32: 49555.504 | M32: 52055.866 | N32: n.a. | O32: n.a.
A33: CBO’s illustrative scenario | B33: 28199.313 | C33: 30108.937 | D33: 31900.946 | E33: 33670.856 | F33: 35656.362 | G33: 37661.516 | H33: 39858.589 | I33: 42137.542 | J33: 44555.879 | K33: 47213.43 | L33: 49832.497 | M33: 52385.555 | N33: n.a. | O33: n.a.
A35: Deficit (-) or surplus (percentage of GDP)
A36: January 2025 baseline | B36: -6.3562158 | C36: -6.1894147 | D36: -5.4664504 | E36: -5.184518 | F36: -5.659123 | G36: -5.5304586 | H36: -5.8793652 | I36: -5.9080768 | J36: -6.0393242 | K36: -6.4690633 | L36: -6.1356563 | M36: -5.7614482 | N36: -5.5528141 | O36: -5.830748
A37: CBO’s illustrative scenario | B37: -6.3562158 | C37: -6.205 | D37: -5.496 | E37: -5.221 | F37: -5.7 | G37: -5.577 | H37: -5.928 | I37: -5.959 | J37: -6.092 | K37: -6.521 | L37: -6.191 | M37: -5.82 | N37: -5.594 | O37: -5.879
A39: Debt held by the public (percentage of GDP)
A40: January 2025 baseline | B40: 97.818585 | C40: 99.889183 | D40: 101.72714 | E40: 103.37462 | F40: 105.438 | G40: 107.22841 | H40: 109.21562 | I40: 111.1142 | J40: 113.04204 | K40: 115.25016 | L40: 117.06826 | M40: 118.47981 | N40: n.a. | O40: n.a.
A41: CBO’s illustrative scenario | B41: 97.818585 | C41: 99.836 | D41: 101.611 | E41: 103.202 | F41: 105.215 | G41: 106.96 | H41: 108.905 | I41: 110.763 | J41: 112.652 | K41: 114.821 | L41: 116.602 | M41: 117.98 | N41: n.a. | O41: n.a.
B44: Economic indicators in CBO’s January 2025 baseline and under the illustrative scenario
B46: 2024 | C46: 2025 | D46: 2026 | E46: 2027 | F46: 2028 | G46: 2029 | H46: 2030 | I46: 2031 | J46: 2032 | K46: 2033 | L46: 2034 | M46: 2035
A47: Real GDP growth (percent)
A48: January 2025 baseline | B48: 2.734 | C48: 2.124 | D48: 1.827 | E48: 1.763 | F48: 1.744 | G48: 1.786 | H48: 1.821 | I48: 1.822 | J48: 1.842 | K48: 1.826 | L48: 1.797 | M48: 1.76
A49: CBO’s illustrative scenario | B49: 2.734 | C49: 2.124 | D49: 1.827 | E49: 1.763 | F49: 1.744 | G49: 1.786 | H49: 1.821 | I49: 1.822 | J49: 1.842 | K49: 1.826 | L49: 1.797 | M49: 1.76
A50: Real GDP (billions of 2017 dollars)
A51: January 2025 baseline | B51: 23290.9 | C51: 23785.8 | D51: 24220.5 | E51: 24647.6 | F51: 25077.7 | G51: 25525.6 | H51: 25990.7 | I51: 26464.3 | J51: 26952 | K51: 27444.4 | L51: 27937.8 | M51: 28429.6
A52: CBO’s illustrative scenario | B52: 23290.9 | C52: 23785.8 | D52: 24220.5 | E52: 24647.6 | F52: 25077.7 | G52: 25525.6 | H52: 25990.7 | I52: 26464.3 | J52: 26952 | K52: 27444.4 | L52: 27937.8 | M52: 28429.6
A53: Nominal GDP (billions of dollars)
A54: January 2025 baseline | B54: 29166.2 | C54: 30441.1 | D54: 31640.6 | E54: 32841 | F54: 34078.4 | G54: 35378.4 | H54: 36738.8 | I54: 38151.3 | J54: 39626.7 | K54: 41154.2 | L54: 42727.6 | M54: 44345.4
A55: CBO’s illustrative scenario | B55: 29166.2 | C55: 30470.8 | D55: 31702.6 | E55: 32937.6 | F55: 34212.1 | G55: 35552 | H55: 36955.3 | I55: 38413.8 | J55: 39938.5 | K55: 41518.7 | L55: 43148.4 | M55: 44825.9
A56: Nominal GDP (billions of dollars, by fiscal year)
A57: January 2025 baseline | B57: 28823 | C57: 30136.1 | D57: 31341.3 | E57: 32538.1 | F57: 33764.5 | G57: 35047.1 | H57: 36393.7 | I57: 37792.1 | J57: 39252.4 | K57: 40767.9 | L57: 42330.4 | M57: 43936.5
A58: CBO’s illustrative scenario | B58: 28823 | C58: 30158.4 | D58: 31395.2 | E58: 32626.1 | F58: 33888.9 | G58: 35210.7 | H58: 36599.5 | I58: 38043.1 | J58: 39551.9 | K58: 41119.2 | L58: 42737.1 | M58: 44402.1
A59: Labor force (millions of people)
A60: January 2025 baseline | B60: 168.243 | C60: 170.662 | D60: 173.375 | E60: 174.006 | F60: 174.614 | G60: 175.295 | H60: 176.03 | I60: 176.801 | J60: 177.558 | K60: 178.176 | L60: 178.795 | M60: 179.386
A61: CBO’s illustrative scenario | B61: 168.243 | C61: 170.662 | D61: 173.375 | E61: 174.006 | F61: 174.614 | G61: 175.295 | H61: 176.03 | I61: 176.801 | J61: 177.558 | K61: 178.176 | L61: 178.795 | M61: 179.386
A62: Interest rate on 10-year Treasury notes (percent)
A63: January 2025 baseline | B63: 4.188 | C63: 4.093 | D63: 3.935 | E63: 3.914 | F63: 3.894 | G63: 3.871 | H63: 3.85 | I63: 3.836 | J63: 3.826 | K63: 3.815 | L63: 3.797 | M63: 3.772
A64: CBO’s illustrative scenario | B64: 4.188 | C64: 4.193 | D64: 4.035 | E64: 4.014 | F64: 3.994 | G64: 3.971 | H64: 3.95 | I64: 3.936 | J64: 3.926 | K64: 3.915 | L64: 3.897 | M64: 3.872
A65: Inflation (percent)b
A66: January 2025 baseline | B66: 2.413 | C66: 2.198 | D66: 2.075 | E66: 1.995 | F66: 1.988 | G66: 1.992 | H66: 1.987 | I66: 1.986 | J66: 1.987 | K66: 1.991 | L66: 1.989 | M66: 1.99
A67: CBO’s illustrative scenario | B67: 2.413 | C67: 2.298 | D67: 2.175 | E67: 2.095 | F67: 2.088 | G67: 2.092 | H67: 2.087 | I67: 2.086 | J67: 2.087 | K67: 2.091 | L67: 2.089 | M67: 2.09
A68: GDP price index (2017 = 100)
A69: January 2025 baseline | B69: 125.223 | C69: 127.976 | D69: 130.631 | E69: 133.238 | F69: 135.887 | G69: 138.595 | H69: 141.349 | I69: 144.157 | J69: 147.023 | K69: 149.95 | L69: 152.934 | M69: 155.979
A70: CBO’s illustrative scenario | B70: 125.223 | C70: 128.101 | D70: 130.887 | E70: 133.63 | F70: 136.42 | G70: 139.275 | H70: 142.182 | I70: 145.149 | J70: 148.18 | K70: 151.278 | L70: 154.44 | M70: 157.669
A71: Employment cost index (December 2005 = 100)c
A72: January 2025 baseline | B72: 168.291 | C72: 174.156 | D72: 180 | E72: 185.768 | F72: 191.526 | G72: 197.325 | H72: 203.213 | I72: 209.221 | J72: 215.381 | K72: 221.716 | L72: 228.225 | M72: 234.91
A73: CBO’s illustrative scenario | B73: 168.291 | C73: 174.324 | D73: 180.348 | E73: 186.307 | F73: 192.268 | G73: 198.282 | H73: 204.397 | I73: 210.644 | J73: 217.057 | K73: 223.658 | L73: 230.448 | M73: 237.429
A76: Data source: Congressional Budget Office.
A78: Real values are nominal values that have been adjusted to remove the effects of changes in prices.
A80: Unless otherwise noted, economic indicators are calendar year averages.
A82: GDP = gross domestic product; n.a. = not applicable.
A84: a. Includes a small interaction effect between higher interest rates and inflation.
A86: b. Measured using the GDP price index.
A88: c. The employment cost index for wages and salaries of workers in private industry.
