Workbook

Sheet Contents
A1: This file presents the data from the figures in CBO's May 2025 report The Long-Term Budget Outlook Under Alternative Scenarios for the Economy and the Budget.
A2: www.cbo.gov/publication/61332
A5: Contents
A7: ='Figure 1'!A5 -> Figure 1. Federal Debt Under the Extended Baseline and Eight Alternative Scenarios, by Fiscal Year
A8: ='Figure 2'!A5 -> Figure 2. Real Gross National Product per Person Under the Extended Baseline and Eight Alternative Scenarios, by Calendar Year
A9: ='Figure 3'!A5 -> Figure 3. Average Primary Deficits Under the Extended Baseline and the Scenario With a Constant Debt-to-GDP Ratio, by Fiscal Year

Sheet Figure 1
A1: This file presents the data from the figures in CBO's May 2025 report The Long-Term Budget Outlook Under Alternative Scenarios for the Economy and the Budget.
A2: www.cbo.gov/publication/61332
A5: Figure 1. Federal Debt Under the Extended Baseline and Eight Alternative Scenarios, by Fiscal Year
A6: Percentage of gross domestic product
C8: If total factor productivity growth differed | F8: If interest rates differed | I8: If sensitivity of private investment to deficits differed | L8: If revenues and spending differed
A9: Fiscal year | B9: Extended baseline | C9: Faster growth | D9: Slower growth | F9: Higher interest rates | G9: Lower interest rates | I9: Greater sensitivity | J9: Lesser sensitivity | L9: Historical averages | M9: Constant debt-to-GDP ratio
A10: 2025 | B10: 99.891 | C10: 99.491 | D10: 100.293 | F10: 99.938 | G10: 99.844 | I10: 99.891 | J10: 99.891 | L10: 100.71 | M10: 99.889
A11: 2026 | B11: 101.73 | C11: 100.854 | D11: 102.615 | F11: 101.876 | G11: 101.584 | I11: 102.136 | J11: 101.328 | L11: 103.947 | M11: 99.889
A12: 2027 | B12: 103.379 | C12: 101.951 | D12: 104.825 | F12: 103.678 | G12: 103.08 | I12: 104.239 | J12: 102.557 | L12: 107.591 | M12: 99.889
A13: 2028 | B13: 105.443 | C13: 103.392 | D13: 107.529 | F13: 105.953 | G13: 104.935 | I13: 106.832 | J13: 104.161 | L13: 111.792 | M13: 99.889
A14: 2029 | B14: 107.234 | C14: 104.5 | D14: 110.026 | F14: 108.016 | G14: 106.457 | I14: 109.253 | J14: 105.431 | L14: 115.703 | M14: 99.889
A15: 2030 | B15: 109.223 | C15: 105.733 | D15: 112.797 | F15: 110.34 | G15: 108.115 | I15: 112.019 | J15: 106.804 | L15: 119.915 | M15: 99.889
A16: 2031 | B16: 111.122 | C16: 106.813 | D16: 115.552 | F16: 112.642 | G16: 109.62 | I16: 114.821 | J16: 108.025 | L16: 124.249 | M16: 99.889
A17: 2032 | B17: 113.051 | C17: 107.853 | D17: 118.411 | F17: 115.045 | G17: 111.088 | I17: 117.785 | J17: 109.215 | L17: 128.8 | M17: 99.889
A18: 2033 | B18: 115.26 | C18: 109.096 | D18: 121.638 | F18: 117.805 | G18: 112.767 | I18: 121.187 | J18: 110.614 | L18: 133.817 | M18: 99.889
A19: 2034 | B19: 117.079 | C19: 109.891 | D19: 124.539 | F19: 120.255 | G19: 113.982 | I19: 124.346 | J19: 111.571 | L19: 138.64 | M19: 99.889
A20: 2035 | B20: 118.491 | C20: 110.226 | D20: 127.095 | F20: 122.384 | G20: 114.717 | I20: 127.251 | J20: 112.075 | L20: 143.263 | M20: 99.889
A21: 2036 | B21: 120.256 | C21: 110.855 | D21: 130.069 | F21: 124.953 | G21: 115.731 | I21: 130.678 | J21: 112.887 | L21: 148.464 | M21: 99.889
... A35: 2050 | B35: 145.647 | C35: 113.844 | D35: 179.759 | F35: 174.842 | G35: 121.637 | I35: 206.739 | J35: 121.727 | L35: 242.169 | M35: 99.889
A36: 2051 | B36: 147.721 | C36: 113.782 | D36: 184.182 | F36: 180.027 | G36: 121.604 | I36: 215.982 | J36: 122.383 | M36: 99.889
A37: 2052 | B37: 149.857 | C37: 113.699 | D37: 188.764 | F37: 185.534 | G37: 121.53 | I37: 226.182 | J37: 123.066 | M37: 99.889
A38: 2053 | B38: 151.98 | C38: 113.525 | D38: 193.426 | F38: 191.308 | G38: 121.341 | I38: 237.412 | J38: 123.704 | M38: 99.889
A39: 2054 | B39: 154.144 | C39: 113.308 | D39: 198.228 | F39: 197.423 | G39: 121.09 | I39: 249.905 | J39: 124.354 | M39: 99.889
A40: 2055 | B40: 156.327 | C40: 113.031 | D40: 203.149 | F40: 203.881 | G40: 120.76 | J40: 124.994 | M40: 99.889
A43: Back to Table of Contents

Sheet Figure 2
A1: This file presents the data from the figures in CBO's May 2025 report The Long-Term Budget Outlook Under Alternative Scenarios for the Economy and the Budget.
A2: www.cbo.gov/publication/61332
A5: Figure 2. Real Gross National Product per Person Under the Extended Baseline and Eight Alternative Scenarios, by Calendar Year
A6: Thousands of 2025 dollars
C8: If total factor productivity growth differed | F8: If interest rates differed | I8: If sensitivity of private investment to deficits differed | L8: If revenues and spending differed
A9: Calendar year | B9: Extended baseline | C9: Faster growth | D9: Slower growth | F9: Higher interest rates | G9: Lower interest rates | I9: Greater sensitivity | J9: Lesser sensitivity | L9: Historical averages | M9: Constant debt-to-GDP ratio
A10: 2025 | B10: 89.926 | C10: 90.198 | D10: 89.654 | F10: 89.926 | G10: 89.926 | I10: 89.926 | J10: 89.926 | L10: 89.913 | M10: 89.926
A11: 2026 | B11: 90.986 | C11: 91.56 | D11: 90.414 | F11: 90.983 | G11: 90.989 | I11: 90.641 | J11: 91.329 | L11: 91.066 | M11: 90.986
A12: 2027 | B12: 91.998 | C12: 92.902 | D12: 91.101 | F12: 91.989 | G12: 92.007 | I12: 91.341 | J12: 92.632 | L12: 92.081 | M12: 92.111
A13: 2028 | B13: 92.976 | C13: 94.231 | D13: 91.736 | F13: 92.958 | G13: 92.994 | I13: 92.02 | J13: 93.871 | L13: 92.912 | M13: 93.187
A14: 2029 | B14: 93.979 | C14: 95.605 | D14: 92.38 | F14: 93.949 | G14: 94.01 | I14: 92.708 | J14: 95.132 | L14: 93.764 | M14: 94.315
A15: 2030 | B15: 95.034 | C15: 97.055 | D15: 93.054 | F15: 94.986 | G15: 95.081 | I15: 93.406 | J15: 96.465 | L15: 94.705 | M15: 95.48
A16: 2031 | B16: 96.109 | C16: 98.55 | D16: 93.73 | F16: 96.041 | G16: 96.177 | I16: 94.11 | J16: 97.811 | L16: 95.664 | M16: 96.681
A17: 2032 | B17: 97.234 | C17: 100.117 | D17: 94.438 | F17: 97.14 | G17: 97.328 | I17: 94.846 | J17: 99.202 | L17: 96.641 | M17: 97.929
A18: 2033 | B18: 98.37 | C18: 101.717 | D18: 95.138 | F18: 98.244 | G18: 98.493 | I18: 95.565 | J18: 100.605 | L18: 97.622 | M18: 99.192
A19: 2034 | B19: 99.515 | C19: 103.351 | D19: 95.831 | F19: 99.354 | G19: 99.673 | I19: 96.27 | J19: 102.016 | L19: 98.593 | M19: 100.488
A20: 2035 | B20: 100.89 | C20: 105.25 | D20: 96.726 | F20: 100.686 | G20: 101.09 | I20: 97.172 | J20: 103.658 | L20: 99.781 | M20: 101.992
A21: 2036 | B21: 102.336 | C21: 107.25 | D21: 97.668 | F21: 102.081 | G21: 102.582 | I21: 98.115 | J21: 105.369 | L21: 101.02 | M21: 103.545
... A35: 2050 | B35: 123.528 | C35: 139.487 | D35: 109.688 | F35: 121.416 | G35: 125.29 | I35: 107.38 | J35: 130.169 | L35: 116.943 | M35: 127.018
A36: 2051 | B36: 125.136 | C36: 142.167 | D36: 110.474 | F36: 122.761 | G36: 127.086 | I36: 107.496 | J36: 132.052 | M36: 128.839
A37: 2052 | B37: 126.772 | C37: 144.92 | D37: 111.262 | F37: 124.108 | G37: 128.922 | I37: 107.482 | J37: 133.968 | M37: 130.696
A38: 2053 | B38: 128.429 | C38: 147.743 | D38: 112.043 | F38: 125.446 | G38: 130.793 | I38: 107.305 | J38: 135.912 | M38: 132.585
A39: 2054 | B39: 130.107 | C39: 150.634 | D39: 112.82 | F39: 126.773 | G39: 132.698 | I39: 106.944 | J39: 137.877 | M39: 134.498
A40: 2055 | B40: 131.808 | C40: 153.6 | D40: 113.594 | F40: 128.09 | G40: 134.642 | J40: 139.872 | M40: 136.445
A43: Back to Table of Contents

Sheet Figure 3
A1: This file presents the data from the figures in CBO's May 2025 report The Long-Term Budget Outlook Under Alternative Scenarios for the Economy and the Budget.
A2: www.cbo.gov/publication/61332
A5: Figure 3. Average Primary Deficits Under the Extended Baseline and the Scenario With a Constant Debt-to-GDP Ratio, by Fiscal Year
A6: Percentage of gross domestic product
A8: Fiscal years | B8: Extended baseline | C8: Constant debt-to-GDP ratio
A9: 2025–2029 | B9: 2.266 | C9: 0.851
A10: 2030–2035 | B10: 2.154 | C10: 0.394
A11: 2036-2040 | B11: 1.918 | C11: 0.36
A12: 2041–2045 | B12: 1.813 | C12: 0.279
A13: 2046–2050 | B13: 1.818 | C13: 0.22
A14: 2051–2055 | B14: 1.852 | C14: 0.183
A17: Back to Table of Contents

Sheet higher_tfp_data
A1: year | B1: population (via census) | C1: real gdp per capita | D1: real gdp | E1: g (cbo ai)
A2: ='Figure 2'!A10 -> 2025 | B2: 338016 | C2: ='Figure 2'!C10 -> 90.198 | D2: =B2*C2 -> 30488367 | E2: 1.94975
A3: ='Figure 2'!A11 -> 2026 | B3: 339513 | C3: ='Figure 2'!C11 -> 91.56 | D3: =B3*C3 -> 31085810 | E3: =((D3-D2)/D2) * 100 -> 1.9595773
A4: ='Figure 2'!A12 -> 2027 | B4: 340970 | C4: ='Figure 2'!C12 -> 92.902 | D4: =B4*C4 -> 31676795 | E4: =((D4-D3)/D3) * 100 -> 1.9011396
A5: ='Figure 2'!A13 -> 2028 | B5: 342385 | C5: ='Figure 2'!C13 -> 94.231 | D5: =B5*C5 -> 32263281 | E5: =((D5-D4)/D4) * 100 -> 1.8514689
A6: ='Figure 2'!A14 -> 2029 | B6: 343754 | C6: ='Figure 2'!C14 -> 95.605 | D6: =B6*C6 -> 32864601 | E6: =((D6-D5)/D5) * 100 -> 1.8637913
A7: ='Figure 2'!A15 -> 2030 | B7: 345074 | C7: ='Figure 2'!C15 -> 97.055 | D7: =B7*C7 -> 33491157 | E7: =((D7-D6)/D6) * 100 -> 1.9064765
A8: ='Figure 2'!A16 -> 2031 | B8: 346339 | C8: ='Figure 2'!C16 -> 98.55 | D8: =B8*C8 -> 34131708 | E8: =((D8-D7)/D7) * 100 -> 1.9125985
A9: ='Figure 2'!A17 -> 2032 | B9: 347545 | C9: ='Figure 2'!C17 -> 100.117 | D9: =B9*C9 -> 34795163 | E9: =((D9-D8)/D8) * 100 -> 1.9438063
A10: ='Figure 2'!A18 -> 2033 | B10: 348702 | C10: ='Figure 2'!C18 -> 101.717 | D10: =B10*C10 -> 35468921 | E10: =((D10-D9)/D9) * 100 -> 1.936357
A11: ='Figure 2'!A19 -> 2034 | B11: 349808 | C11: ='Figure 2'!C19 -> 103.351 | D11: =B11*C11 -> 36153007 | E11: =((D11-D10)/D10) * 100 -> 1.9286893
A12: ='Figure 2'!A20 -> 2035 | B12: 350861 | C12: ='Figure 2'!C20 -> 105.25 | D12: =B12*C12 -> 36928120 | E12: =((D12-D11)/D11) * 100 -> 2.1439811
A13: ='Figure 2'!A21 -> 2036 | B13: 351861 | C13: ='Figure 2'!C21 -> 107.25 | D13: =B13*C13 -> 37737092 | E13: =((D13-D12)/D12) * 100 -> 2.1906666
A14: ='Figure 2'!A22 -> 2037 | B14: 352806 | C14: ='Figure 2'!C22 -> 109.285 | D14: =B14*C14 -> 38556404 | E14: =((D14-D13)/D13) * 100 -> 2.1711038
... A23: ='Figure 2'!A31 -> 2046 | B23: 358936 | C23: ='Figure 2'!C31 -> 129.308 | D23: =B23*C23 -> 46413296 | E23: =((D23-D22)/D22) * 100 -> 2.0391297
